Workbook
Name \A: #REF!
Name \B: #REF!
Name \C: #REF!
Name \D: #REF!
Name \E: #REF!
Name \F: #REF!
Name \G: #REF!
Name \H: #REF!
Name \I: #REF!
Name \J: #REF!
Name \K: #REF!
Name \L: #REF!
Name \M: '[1]RT 21'!#REF!
Name \MM: '[1]RT 21'!#REF!
Name \P: '[1]RT 21'!#REF!
Name \PP: '[1]RT 21'!#REF!
Name \S: '[1]RT 21'!#REF!
Name \SS: '[1]RT 21'!#REF!
Name ____________________________JUL11: '[2]FY03-04 Budget'!#REF!
Name ____________________________JUL29: '[2]FY03-04 Budget'!#REF!
Name ____________________________JUL34: '[2]FY03-04 Budget'!#REF!
Name ____________________________JUN30: '[2]FY03-04 Budget'!#REF!
Name ____________________________JUN36: '[2]FY03-04 Budget'!#REF!
Name ____________________________MAY10: '[3]MAY '!$E$10
Name ____________________________MAY11: '[3]MAY '!$E$11
Name ____________________________MAY14: '[3]MAY '!$E$14
Name ____________________________MAY15: '[3]MAY '!$E$15
Name ____________________________MAY16: '[3]MAY '!$E$16
Name ____________________________MAY17: '[3]MAY '!$E$17
Name ____________________________MAY18: '[3]MAY '!$E$18
Name ____________________________MAY19: '[3]MAY '!$E$19
Name ____________________________MAY20: '[3]MAY '!$E$20
Name ____________________________MAY21: '[3]MAY '!$E$21
Name ____________________________MAY22: '[3]MAY '!$E$22
Name ____________________________MAY23: '[3]MAY '!$E$23
Name ____________________________MAY24: '[3]MAY '!$E$24
Name ____________________________MAY25: '[3]MAY '!$E$25
Name ____________________________MAY26: '[3]MAY '!$E$26
Name ____________________________MAY27: '[3]MAY '!$E$27
Name ____________________________MAY28: '[3]MAY '!$E$28
Name ____________________________MAY30: '[3]MAY '!$E$30
Name ____________________________MAY33: '[3]MAY '!$E$33
Name ____________________________MAY34: '[3]MAY '!$E$34
Name ____________________________MAY35: '[3]MAY '!$E$35
Name ____________________________MAY4: '[3]MAY '!$E$4
Name ____________________________MAY5: '[3]MAY '!$E$5
Name ____________________________MAY6: '[3]MAY '!$E$6
Name ____________________________MAY7: '[3]MAY '!$E$7
Name ____________________________MAY8: '[3]MAY '!$E$8
Name ____________________________MAY9: '[3]MAY '!$E$9
Name _____________________JUL11: '[2]FY03-04 Budget'!#REF!
Name _____________________JUL29: '[2]FY03-04 Budget'!#REF!
Name _____________________JUL34: '[2]FY03-04 Budget'!#REF!
Name _____________________JUN30: '[2]FY03-04 Budget'!#REF!
Name _____________________JUN36: '[2]FY03-04 Budget'!#REF!
Name _____________________MAY10: '[3]MAY '!$E$10
Name _____________________MAY11: '[3]MAY '!$E$11
Name _____________________MAY14: '[3]MAY '!$E$14
Name _____________________MAY15: '[3]MAY '!$E$15
Name _____________________MAY16: '[3]MAY '!$E$16

Sheet VRH Rates
B3: Operating Cost Rates | C3: FY 26-27
B5: South Shore | I5: Marginal Op Cost per VSH
C6: Form | D6: Per VSH | E6: Per VSM | F6: Fixed | J6: Tot. Op Cost/VSH | L6: NOTES
B7: TTD Fixed Route Bus | C7: =D27 -> TTDTTD | D7: 123.17 | E7: 1.6 | F7: 2077415.2 | J7: 214.66 | L7: Based on 24/25 actuals plus 4% inflation/yr
B8: TTD Paratransit | C8: =D27 -> TTDTTD | D8: =D7 -> 123.17 | E8: =E7 -> 1.6 | J8: =J7 -> 214.66 | L8: Based on 24/25 actuals plus 4% inflation/yr
B9: Lake Link | C9: =D29 -> SSTMAVia | D9: 65.23 | F9: 43215 | G9: 27195 | H9: =90000+1650+840 -> 92490 | J9: 68.7 | L9: SSTMA Lake Link contract costs for 2027. Plus Fixed Admin costs
B10: Route 30 | C10: =D28 -> TTDVia | J10: 147.8
B12: North Shore
B14: TART Fixed Route | C14: =D30 -> TARTTART | D14: 66.45 | E14: 1.7 | F14: 3188061.3 | J14: 185.83 | L14: Based on 24-25 actuals cost model from Existing Conditions report (+4% inflation/yr) | X14: 24-25 | Y14: 26-27*
B15: TART Connect | C15: =D32 -> TARTDowntowner | D15: 46.56 | F15: 1724488 | J15: 107.23 | L15: Based on 24-25 actuals cost model from Existing Conditions report (+5% inflation/yr to reflect contract-specified escation rates) | X15: ='[30]TART cost model 24-25'!$B$44 -> 4003350 | Y15: =X15*(1.05)^2 -> 4413693.4
B16: Placer TART Paratransit | C16: =D31 -> TARTTruckee | D16: 127.77784 | F16: 9338.3477 | J16: 134.52933 | L16: Based on 24-25 actuals cost model from Existing Conditions report (+4% inflation/yr)
A18: My Ride to Work | B18: Bus(TART) | J18: =284.34*(1+0.03)^2 -> 301.65631 | L18: Based on contract cost from TART/MRTW FY 24-25 (+3% inflation/yr)
B19: Van(TART) | J19: =96.85*(1+0.03)^2 -> 102.74816 | L19: Based on contract cost from TART/MRTW FY 24-25 (+3% inflation/yr)
B20: Shuttle (P&R) | C20: =D33 -> TNTTMAMRTW | J20: =195.13*(1.03) -> 200.9839 | L20: Based on Park and Ride contract cost from TNTTMA/MRTW FY 25-26 (+3% inflation/yr)
B21: Van(P&R) | J21: =128.75*1.03 -> 132.6125 | L21: Based on Park and Ride contract cost from TNTTMA/MRTW FY 25-26 (+3% inflation/yr)
H24: =SUM(F9:H9) -> 162900
B25: Agency/Operator Combinations
B27: TTD | C27: TTD | D27: =CONCATENATE(B27,C27) -> TTDTTD
B28: TTD | C28: Via | D28: =CONCATENATE(B28,C28) -> TTDVia
B29: SSTMA | C29: Via | D29: =CONCATENATE(B29,C29) -> SSTMAVia
B30: TART | C30: TART | D30: =CONCATENATE(B30,C30) -> TARTTART
B31: TART | C31: Truckee | D31: =CONCATENATE(B31,C31) -> TARTTruckee
B32: TART | C32: Downtowner | D32: =CONCATENATE(B32,C32) -> TARTDowntowner
B33: TNTTMA | C33: MRTW | D33: =CONCATENATE(B33,C33) -> TNTTMAMRTW

Sheet costs
O1: Blue = | P1: User Inputs
O2: Green = | P2: Cost Data
B3: State Route Conditions | C3: Local Route Conditions | D3: Service/Route | E3: Agency | F3: Operator | G3: Passenger-Trips | H3: Vehicle Service Hours | I3: Vehicle Service Miles | J3: Cost per VSH | K3: Total Operating Costs | T3: Data Year | W3: Questions
B4: Nevada Route | C4: Carson City, Douglas County | D4: 19X | E4: TTD | F4: TTD | G4: 10747 | H4: 2250.4 | I4: 61381 | J4: =VLOOKUP(F4,$V$31:$W$36,2,FALSE) -> 214.66 | K4: =H4*J4 -> 483070.86 | T4: 24-25 | W4: Could separate out fixed costs but this is harder to do for private contractors. When making large changes, fixed costs will change, particularly for private contractors
B5: Nevada Route | C5: Douglas County | D5: 22 | E5: TTD | F5: TTD | G5: 18457 | H5: 4409.6 | I5: 121654 | J5: =VLOOKUP(F5,$V$31:$W$36,2,FALSE) -> 214.66 | K5: =H5*J5 -> 946564.74 | T5: 24-25
B6: Nevada Seasonal Route | C6: Washoe County | D6: 28 | E6: TTD | F6: TTD | G6: 24699 | H6: 1192.7 | I6: 22330 | J6: =VLOOKUP(F6,$V$31:$W$36,2,FALSE) -> 214.66 | K6: =H6*J6 -> 256024.98 | T6: 24-25
B7: California Seasonal Route | C7: El Dorado County | D7: 30 | E7: TTD | F7: Via | G7: 10700 | H7: 3500 | I7: 9850 | J7: =VLOOKUP(F7,$V$31:$W$36,2,FALSE) -> 68.7 | K7: =H7*J7 -> 240450 | T7: 26-27 | U7: estimate
B8: California Route (portion in NV) | C8: CSLT, El Dorado County, Douglas County | D8: 50 | E8: TTD | F8: TTD | G8: 170332 | H8: 9418.6 | I8: 134562 | J8: =VLOOKUP(F8,$V$31:$W$36,2,FALSE) -> 214.66 | K8: =H8*J8 -> 2021796.7 | T8: 24-25
B9: California Route (portion in NV) | C9: CSLT, El Dorado County, Douglas County | D9: 51 | E9: TTD | F9: TTD | G9: 115 | H9: 167 | I9: 1700 | J9: =VLOOKUP(F9,$V$31:$W$36,2,FALSE) -> 214.66 | K9: =H9*J9 -> 35848.22 | T9: 24-25
B10: California Route | C10: CSLT, El Dorado County | D10: 55 | E10: TTD | F10: TTD | G10: 55609 | H10: 9312.2 | I10: 111689 | J10: =VLOOKUP(F10,$V$31:$W$36,2,FALSE) -> 214.66 | K10: =H10*J10 -> 1998956.9 | T10: 24-25
B11: CA/NV | D11: ADA Para | E11: TTD | F11: TTD | G11: 14556 | H11: 5429 | I11: 71677 | J11: =VLOOKUP(F11,$V$31:$W$36,2,FALSE) -> 214.66 | K11: =H11*J11 -> 1165389.1 | T11: 24-25
B12: CA/NV | C12: Zone 1 (Douglas County), Zone 2 (CSLT), Zone 3 (CSLT) | D12: Lake Link | E12: SSTMA | F12: Via | G12: 223047 | H12: 47002 | I12: 366322 | J12: =VLOOKUP(F12,$V$31:$W$36,2,FALSE) -> 68.7 | K12: =H12*J12 -> 3229037.4 | T12: 25-26 | U12: VSH are from contract not actual
B13: Califorrnia route | C13: Placer County | D13: West Shore | E13: TART | F13: TART | G13: 21205 | H13: 4237.5 | I13: 82391.1 | J13: =VLOOKUP(F13,$V$31:$W$36,2,FALSE) -> 185.83 | K13: =H13*J13 -> 787454.62 | T13: 25-26
B14: California route | C14: Placer County | D14: N Shore | E14: TART | F14: TART | G14: 92011 | H14: 4983.5 | I14: 113132.1 | J14: =VLOOKUP(F14,$V$31:$W$36,2,FALSE) -> 185.83 | K14: =H14*J14 -> 926083.81 | T14: 25-26
B15: Nevada route | C15: Washoe County | D15: Nevada | E15: TART | F15: TART | G15: 34977 | H15: 4219.3125 | I15: 63697 | J15: =VLOOKUP(F15,$V$31:$W$36,2,FALSE) -> 185.83 | K15: =H15*J15 -> 784074.84 | T15: 25-26
B16: California route | C16: Placer County | D16: Main Line | E16: TART | F16: TART | G16: =SUM(G13:G15) -> 148193 | H16: =SUM(H13:H15) -> 13440.312 | I16: =SUM(I13:I15) -> 259220.2 | J16: =VLOOKUP(F16,$V$31:$W$36,2,FALSE) -> 185.83 | K16: =H16*J16 -> 2497613.3
B17: California route | C17: Placer County, Nevada County | D17: 89 | E17: TART | F17: TART | G17: 71136 | H17: 8331.75 | I17: 167948.7 | J17: =VLOOKUP(F17,$V$31:$W$36,2,FALSE) -> 185.83 | K17: =H17*J17 -> 1548289.1 | T17: 25-26
B18: California route | C18: Placer County, Nevada County | D18: 267 | E18: TART | F18: TART | G18: 73556 | H18: 8420.2333 | I18: 176999.3 | J18: =VLOOKUP(F18,$V$31:$W$36,2,FALSE) -> 185.83 | K18: =H18*J18 -> 1564732 | T18: 25-26
B19: California route | C19: Placer County | D19: Night | E19: TART | F19: TART | G19: 4725 | H19: 2985 | I19: 57781.2 | J19: =VLOOKUP(F19,$V$31:$W$36,2,FALSE) -> 185.83 | K19: =H19*J19 -> 554702.55 | T19: 25-26
B20: California route | D20: ADA Para | E20: TART | F20: Truckee | G20: 3573 | H20: 1951.65 | I20: 34749 | J20: =VLOOKUP(F20,$V$31:$W$36,2,FALSE) -> 134.52933 | K20: =H20*J20 -> 262554.16 | T20: 25-26
B21: California route | C21: Placer County | D21: Placer TART Connect | E21: TART | F21: Placer Via | G21: 157369 | H21: 27342.51 | I21: 544888.71 | J21: =VLOOKUP(F21,$V$31:$W$36,2,FALSE) -> 107.23 | K21: =H21*J21 -> 2931937.3 | T21: 25-26
B22: California route | C22: Placer County, Nevada County | D22: Park&Ride (Winter) | E22: TNTTMA | F22: MRTW | H22: 2500 | J22: =VLOOKUP(F22,$V$31:$W$36,2,FALSE) -> 200.9839 | K22: =H22*J22 -> 502459.75 | U22: Estimate
B23: California route | C23: Placer County, Nevada County | D23: Park&Ride (Summ) | E23: TNTTMA | F23: MRTW | H23: 500 | J23: =VLOOKUP(F23,$V$31:$W$36,2,FALSE) -> 200.9839 | K23: =H23*J23 -> 100491.95 | U23: Estimate
B24: CA/NV | C24: Placer County, Nevada County, Washoe County | D24: NLTE | E24: TNTTMA | F24: MRTW | H24: 1200 | J24: =VLOOKUP(F24,$V$31:$W$36,2,FALSE) -> 200.9839 | K24: =H24*J24 -> 241180.68 | U24: Estimate based on budget costs for 25-26
D25: Total | K25: =SUM(K4:K24) -> 23078713
V30: Operating Cost per Vehicle Hour Lookup Table
V31: TTD | W31: =+'VRH Rates'!J7 -> 214.66
V32: Via | W32: =+'VRH Rates'!J9 -> 68.7
V33: TART | W33: =+'VRH Rates'!J14 -> 185.83
V34: Placer Via | W34: =+'VRH Rates'!J15 -> 107.23
V35: MRTW | W35: =+'VRH Rates'!J20 -> 200.9839 | X35: Using Bus costs
V36: Truckee | W36: =+'VRH Rates'!J16 -> 134.52933
P40: TTD Total Marginal Operating Cost FY 2024-25
O41: FY 2024-25 | P41: 4444985.4
O42: FY 2026-27 | P42: =P41*(1.03)^2 -> 4715685
O44: Total VSH | P44: 32225

Sheet Example
E2: Tahoe Regional Transit Operating Cost Scenario Worksheet
E4: Blue = User Inputs
E5: Green = Placeholder Values
E7: Service Element | F7: Annual Vehicle Hours | G7: Operator | H7: Marginal Operating Cost per Vehicle Hour | I7: Annual Operating Cost | J7: Total Annual Costs
E8: Route 50 | F8: 9400 | G8: TTD | H8: =VLOOKUP(G8,$M$34:$N$36,2,FALSE) -> 120 | I8: =ROUND(H8*F8,-3) -> 1128000
E10: Lake Link | F10: 27400 | G10: VIA | H10: =VLOOKUP(G10,$M$34:$N$36,2,FALSE) -> 80 | I10: =ROUND(H10*F10,-3) -> 2192000
E11: East Shore Express | F11: 2000 | G11: TTD | H11: =VLOOKUP(G11,$M$34:$N$36,2,FALSE) -> 120 | I11: =ROUND(H11*F11,-3) -> 240000
E12: TTD Paratransit
E13: SR 267 | F13: 5000 | G13: Placer County | H13: =VLOOKUP(G13,$M$34:$N$36,2,FALSE) -> 140 | I13: =ROUND(H13*F13,-3) -> 700000
E14: SR 89
E15: Mainline
E19: Etc
E20: Total Marginal Operating Costs | J20: =SUM(I8:I19) -> 4260000
E23: Annual Fixed Costs
E24: TTD | J24: 2000000
E25: VIA | J25: 200000
E26: Placer County | J26: 3000000
E28: Total Tahoe-Wide Annual Transit Operating/Administrative Costs | J28: =SUM(J20:J26) -> 9460000
E30: Total Tahoe-Wide Operating Revenue
M33: Marginal Operating Cost per Vehicle Hour Lookup Table
M34: TTD | N34: 120
M35: VIA | N35: 80
M36: Placer County | N36: 140
