Workbook
Name \A: #REF!
Name \B: #REF!
Name \C: #REF!
Name \D: #REF!
Name \E: #REF!
Name \F: #REF!
Name \G: #REF!
Name \H: #REF!
Name \I: #REF!
Name \J: #REF!
Name \K: #REF!
Name \L: #REF!
Name \M: '[1]RT 21'!#REF!
Name \MM: '[1]RT 21'!#REF!
Name \P: '[1]RT 21'!#REF!
Name \PP: '[1]RT 21'!#REF!
Name \S: '[1]RT 21'!#REF!
Name \SS: '[1]RT 21'!#REF!
Name ____________________________JUL11: '[2]FY03-04 Budget'!#REF!
Name ____________________________JUL29: '[2]FY03-04 Budget'!#REF!
Name ____________________________JUL34: '[2]FY03-04 Budget'!#REF!
Name ____________________________JUN30: '[2]FY03-04 Budget'!#REF!
Name ____________________________JUN36: '[2]FY03-04 Budget'!#REF!
Name ____________________________MAY10: '[3]MAY '!$E$10
Name ____________________________MAY11: '[3]MAY '!$E$11
Name ____________________________MAY14: '[3]MAY '!$E$14
Name ____________________________MAY15: '[3]MAY '!$E$15
Name ____________________________MAY16: '[3]MAY '!$E$16
Name ____________________________MAY17: '[3]MAY '!$E$17
Name ____________________________MAY18: '[3]MAY '!$E$18
Name ____________________________MAY19: '[3]MAY '!$E$19
Name ____________________________MAY20: '[3]MAY '!$E$20
Name ____________________________MAY21: '[3]MAY '!$E$21
Name ____________________________MAY22: '[3]MAY '!$E$22
Name ____________________________MAY23: '[3]MAY '!$E$23
Name ____________________________MAY24: '[3]MAY '!$E$24
Name ____________________________MAY25: '[3]MAY '!$E$25
Name ____________________________MAY26: '[3]MAY '!$E$26
Name ____________________________MAY27: '[3]MAY '!$E$27
Name ____________________________MAY28: '[3]MAY '!$E$28
Name ____________________________MAY30: '[3]MAY '!$E$30
Name ____________________________MAY33: '[3]MAY '!$E$33
Name ____________________________MAY34: '[3]MAY '!$E$34
Name ____________________________MAY35: '[3]MAY '!$E$35
Name ____________________________MAY4: '[3]MAY '!$E$4
Name ____________________________MAY5: '[3]MAY '!$E$5
Name ____________________________MAY6: '[3]MAY '!$E$6
Name ____________________________MAY7: '[3]MAY '!$E$7
Name ____________________________MAY8: '[3]MAY '!$E$8
Name ____________________________MAY9: '[3]MAY '!$E$9
Name _____________________JUL11: '[2]FY03-04 Budget'!#REF!
Name _____________________JUL29: '[2]FY03-04 Budget'!#REF!
Name _____________________JUL34: '[2]FY03-04 Budget'!#REF!
Name _____________________JUN30: '[2]FY03-04 Budget'!#REF!
Name _____________________JUN36: '[2]FY03-04 Budget'!#REF!
Name _____________________MAY10: '[3]MAY '!$E$10
Name _____________________MAY11: '[3]MAY '!$E$11
Name _____________________MAY14: '[3]MAY '!$E$14
Name _____________________MAY15: '[3]MAY '!$E$15
Name _____________________MAY16: '[3]MAY '!$E$16

Sheet For Slides
A1: HILL COUNTRY TRANSIT DISTRICT
A2: FY2024 Proposed Budget (1/1/24 - 12/31/24)
A3: Presented to Board of Directors 11/20/23
C6: In Service | D6: In Service
B7: Commuter Bus Allocation Based on Census 2020 Population by City | S7: Commuter Bus Allocation Based on Census 2020 Population by City
C8: Vehicles | D8: Vehicles | F8: Cost Estimate | G8: Population | J8: Hours | T8: Cost Estimate | U8: Population | W8: Allocated Cost | X8: Hours
B9: TEMPLE | C9: 9 | D9: 12 | G9: 82073 | H9: =G9/G14 -> 0.24921128 | I9: =H9*$F$14 -> 209935.58 | J9: =F155 -> 39832 | K9: =J9/J14 -> 0.33765089 | L9: =J9/(J9+J10) -> 0.80293501 | S9: TEMPLE | U9: 82073 | V9: =U9/U14 -> 0.24921128 | W9: =V9*$F$14 -> 209935.58 | X9: =$F$30*V9 -> 2332.6176
B10: BELTON | C10: 2 | D10: 3 | G10: 23054 | H10: =G10/G14 -> 0.07000252 | I10: =H10*$F$14 -> 58970.123 | J10: =F134 -> 9776 | K10: =J10/J14 -> 0.082869931 | L10: =J10/(J9+J10) -> 0.19706499 | S10: BELTON | U10: 23054 | V10: =U10/U14 -> 0.07000252 | W10: =V10*$F$14 -> 58970.123 | X10: =$F$30*V10 -> 655.22359
B11: KILLEEN | C11: 11 | D11: 15 | G11: 153143 | H11: =G11/G14 -> 0.4650124 | I11: =H11*$F$14 -> 391726.45 | J11: =F112 -> 49192 | K11: =J11/J14 -> 0.41699444 | L11: =J11/(J11+J12+J13) -> 0.71960211 | S11: KILLEEN | U11: 153143 | V11: =U11/U14 -> 0.4650124 | W11: =V11*$F$14 -> 391726.45 | X11: =$F$30*V11 -> 4352.5161
B12: COPPERAS COVE | C12: 2 | D12: 3 | G12: 37964 | H12: =G12/G14 -> 0.11527612 | I12: =H12*$F$14 -> 97108.604 | J12: =F70 -> 9600 | K12: =J12/J14 -> 0.081378001 | L12: =J12/(J11+J12+J13) -> 0.140433 | S12: COPPERAS COVE | U12: 37964 | V12: =U12/U14 -> 0.11527612 | W12: =V12*$F$14 -> 97108.604 | X12: =$F$30*V12 -> 1078.9845
B13: HARKER HEIGHTS | C13: 2 | D13: 3 | G13: 33097 | H13: =G13/G14 -> 0.10049768 | I13: =H13*$F$14 -> 84659.242 | J13: =F91 -> 9568 | K13: =J13/J14 -> 0.081106741 | L13: =J13/(J11+J12+J13) -> 0.13996489 | S13: HARKER HEIGHTS | U13: 33097 | V13: =U13/U14 -> 0.10049768 | W13: =V13*$F$14 -> 84659.242 | X13: =$F$30*V13 -> 940.65824
C14: =SUM(C9:C13) -> 26 | D14: =SUM(D9:D13) -> 36 | F14: =12*260*3*90 -> 842400 | G14: =SUM(G9:G13) -> 329331 | H14: =SUM(H9:H13) -> 1 | I14: =SUM(I9:I13) -> 842400 | J14: =SUM(J9:J13) -> 117968 | K14: =SUM(K9:K13) -> 1 | T14: =12*260*3*90 -> 842400 | U14: =SUM(U9:U13) -> 329331 | V14: =SUM(V9:V13) -> 1 | W14: =SUM(W9:W13) -> 842400 | X14: =SUM(X9:X13) -> 9360
B16: Average Fare | C16: 1
B18: FY24 Budget Targets
B19: As of 6/6/2023
B20: Fully Allocated Expenses | C20: Avg. Daily | D20: Avg. Fleet During | F20: Annual Vehicle Revenue Hours | I20: Annual Passengers | L20: Proposed | P20: FY23
B21: Microtransit On-demand All Urban Zones | C21: Service Hours | D21: Service Hours | G21: Contingency | H21: Contingency | L21: FY24 | P21: Budget
B22: All Zones - Avg. Wait Times 30min Peak | C22: 260 Weekdays | F22: Budget | G22: +10% | H22: +20% | I22: Low | J22: Med | K22: High | L22: Budget | M22: +10% | N22: +20% | O22: Diff Lo/Hi
B23: 7am - 11am + 3pm - 7pm | C23: 8 | D23: =D14 -> 36 | F23: =(C23*D23*260) -> 74880 | G23: =F23*1.1 -> 82368 | H23: =F23*1.2 -> 89856 | I23: =F23*5 -> 374400 | J23: =F23*5.5 -> 411840 | K23: =F23*6 -> 449280 | L23: =F23*65 -> 4867200 | M23: =G23*65 -> 5353920 | N23: =H23*65 -> 5840640 | R23: =L63+L84+L105+L127+L148 -> 4867200
B24: All Zones - Avg. Wait Times 40min Off Peak | C24: 260 Weekdays
B25: 11am - 3pm + 7pm - 9pm | C25: 6 | D25: =C14 -> 26 | F25: =(C25*D25*260) -> 40560 | G25: =F25*1.1 -> 44616 | H25: =F25*1.2 -> 48672 | I25: =F25*3 -> 121680 | J25: =F25*4 -> 162240 | K25: =F25*5 -> 202800 | L25: =F25*65 -> 2636400 | M25: =G25*65 -> 2900040 | N25: =H25*65 -> 3163680 | R25: =L65+L86+L107+L129+L150 -> 2636400
B26: All Zones - Avg. Wait Times 30min Off Peak | C26: 52 Weekend Days
B27: TNC Service Provider | L27: =L67+L88+L109+L131+L151 -> 670453 | R27: =L67+L88+L109+L131+L151 -> 670453
B28: Medicaid Trips (50 daily) | C28: 8 | D28: 6 | F28: =F68+F89+F110+F132+F153 -> 2528 | G28: =F28*1.1 -> 2780.8 | H28: =F28*1.2 -> 3033.6 | I28: =F28*1.5 -> 3792 | J28: =G28*1.5 -> 4171.2 | K28: =H28*1.5 -> 4550.4 | L28: =F28*65 -> 164320 | M28: =G28*65 -> 180752 | N28: =H28*65 -> 197184 | R28: =L68+L89+L110+L132+L153 -> 164320
B29: Total Microtransit On-demand | F29: =SUM(F23:F28) -> 117968 | G29: =SUM(G23:G28) -> 129764.8 | H29: =SUM(H23:H28) -> 141561.6 | I29: =SUM(I23:I28) -> 499872 | J29: =SUM(J23:J28) -> 578251.2 | K29: =SUM(K23:K28) -> 656630.4 | L29: =SUM(L23:L28) -> 8338373 | M29: =SUM(M23:M28) -> 8434712 | N29: =SUM(N23:N28) -> 9201504
B30: Commuter Bus - Stops in Temple, Belton, Nolanville, Harker Heights, Killeen, Copperas Cove | C30: 12 | D30: 3 | F30: =(C30*D30*260) -> 9360 | G30: =F30*1.1 -> 10296 | H30: =F30*1.2 -> 11232 | I30: =10*5*2*290 -> 29000 | J30: =10*7*2*290 -> 40600 | K30: =10*8*2*290 -> 46400 | L30: =F30*90 -> 842400 | M30: =12*259*86*6 -> 1603728 | N30: =12*259*86*6 -> 1603728
B31: Rural | D31: 20 | F31: 32958.05 | J31: 70000 | L31: 2641604 | M31: 2592992 | N31: 2592992
B32: Fort Cavazos (No Fare) | F32: 56548 | J32: 169644 | L32: =4241400-(F32*10) -> 3675920 | S32: County | T32: State & Fed Funding Allocation | U32: NEMT Revenue | V32: Local Funding Contributions | W32: FY24 Budget Target | X32: FY24 County Funding Commitment
B33: Total Projected Expense | F33: =F29+F30+F31+F32 -> 216834.05 | G33: =G29+G30+G31+G32 -> 140060.8 | H33: =H29+H30+H31+H32 -> 152793.6 | I33: =I29+I30+I31+I32 -> 528872 | J33: =J29+J30+J31+J32 -> 858495.2 | K33: =K29+K30+K31+K32 -> 703030.4 | L33: =L29+L30+L31+L32 -> 15498297 | M33: =SUM(M29:M31) -> 12631432 | N33: =SUM(N29:N31) -> 13398224 | O33: =N33-L33 -> -2100073 | P33: =5149835+2883500+3001770 -> 11035105
B34: Projected Revenue
B35: Federal Grant Revenue | L35: =(L48+L51+L54)*-1 -> -6164398 | M35: =-(2970479+1673250+1253517) -> -5897246 | N35: =-(2970479+1673250+1253517) -> -5897246 | P35: =-(2970479+1673250+1253517) -> -5897246 | S35: Bell County | T35: 60476.325 | U35: 9383 | V35: 134383 | W35: 100793 | X35: 125000 | Z35: =ROUND(W35,0) -> 100793
B36: Federal Grant Carbon Reduction Grant | L36: -500000 | S36: Coryell County | T36: 197197.34 | U36: 30595 | V36: 104111 | W36: 301309 | X36: 50000 | Z36: =ROUND(W36,0) -> 301309
B37: State Revenue | L37: =(L49+L52+L55)*-1 -> -1525568 | M37: =-(415133+519759+601585) -> -1536477 | N37: =-(415133+519759+601585) -> -1536477 | P37: =-(415133+519759+601585) -> -1536477 | S37: Hamilton County | T37: 174565.1 | U37: 0 | V37: 0 | W37: 174565 | X37: 0 | Z37: =ROUND(W37,0) -> 174565
B38: Urban Medicaid Revenue | L38: -1113000 | M38: -1400000 | N38: -1400000 | P38: =-917223-634691-404368 -> -1956282 | S38: Lampasas County | T38: 179759.38 | U38: 27890 | V38: 119839 | W38: 299598 | X38: 68433 | Z38: =ROUND(W38,0) -> 299598
B39: Fare Revenue | L39: =((J29+J30+J31)*C16)*-1 -> -688851.2 | S39: Llano County | T39: 303680.2 | U39: 47116 | V39: 202451 | W39: 506131 | X39: 155335 | Z39: =ROUND(W39,0) -> 506131
B40: Killeen Local | L40: =L117*-1 -> -650000 | S40: Mason County | T40: 88117.345 | U40: 13671 | V40: 58744 | W40: 146862 | X40: 45073 | Z40: =ROUND(W40,0) -> 146862
B41: Temple Local | L41: =L162*-1 -> -308936.66 | S41: Milam County | T41: 601053.05 | U41: 93254 | V41: 215287 | W41: 816341 | X41: 75000 | Z41: =ROUND(W41,0) -> 816341
B42: Belton Local | L42: =L141*-1 -> -55372.768 | S42: Mills County | T42: 116500.41 | U42: 0 | V42: 0 | W42: 116500 | X42: 0 | Z42: =ROUND(W42,0) -> 116500
B43: Copperas Cove Local | L43: =L77*-1 -> -94462.808 | S43: San Saba | T43: 133752.85 | U43: 20752 | V43: 45752 | W43: 179505 | X43: 25000 | Z43: =ROUND(W43,0) -> 179505
B44: Harker Heights Local | L44: =L98*-1 -> -64999.85 | T44: =SUM(T35:T43) -> 1855102 | U44: =SUM(U35:U43) -> 242661 | V44: =SUM(V35:V43) -> 880567 | W44: =SUM(W35:W43) -> 2641604 | X44: =SUM(X35:X43) -> 543841 | Z44: =SUM(Z35:Z43) -> 2641604
B45: Rural Local ($242,661 Medicaid + $543,841 Counties) | L45: =(242661+543841)*-1 -> -786502
B46: Fort Cavazos | L46: =4241400*-1 -> -4241400 | S46: Total Revenues
B47: Total Revenue All Sources | L47: =SUM(L34:L46) -> -16193491 | M47: =SUM(M35:M38) -> -8833723 | N47: =SUM(N35:N38) -> -8833723 | P47: =SUM(P35:P38) -> -9390005 | S47: Federal Grant Revenue | T47: =-L35-L36 -> 6664398 | U47: =ROUND(T47/$T$55,2) -> 0.41
B48: Killeen UZA Federal Revenue Allocation | L48: 2970472 | S48: State Grant Revenue | T48: =-L37 -> 1525568 | U48: =ROUNDUP(T48/$T$55,2) -> 0.1
B49: Killeen State UZA Allocation | L49: =379929 -> 379929 | S49: Urban Medicaid Revenue | T49: =-L38 -> 1113000 | U49: =ROUND(T49/$T$55,2) -> 0.07
B50: Total Killeen | L50: =SUM(L48:L49) -> 3350401 | S50: Fare Revenue | T50: =-L39 -> 688851.2 | U50: =ROUND(T50/$T$55,2) -> 0.04
B51: Temple UZA Federal UZA Revenue Allocation | L51: 1940409 | P51: 1673250 | S51: Urban Local | T51: =-L40-L41-L42-L43-L44 -> 1173772.1 | U51: =ROUND(T51/$T$55,2) -> 0.07
B52: Temple State FY24 UZA Revenue Allocation + 5311 Grant Revenue | L52: =362108+158000 -> 520108 | P52: 519759 | S52: Rural Medicaid Revenue | T52: 242661 | U52: =ROUNDUP(T52/$T$55,2) -> 0.02
B53: Total Temple | L53: =SUM(L51:L52) -> 2460517 | S53: Rural Local | T53: 543841 | U53: =ROUND(T53/$T$55,2) -> 0.03
B54: Rural Federal Allocation | L54: 1253517 | S54: Fort Cavazos | T54: =-L46 -> 4241400 | U54: =ROUND(T54/$T$55,2) -> 0.26
B55: Rural State Allocation | L55: 625531 | S55: Total | T55: =SUM(T47:T54) -> 16193491
B56: Total Rural | L56: =SUM(L54:L55) -> 1879048 | P56: =L56+L53+L50 -> 7689966 | R56: =P56-L33 -> -7808331
B58: Estimates for Microtransit On-demand Copperas Cove Zones
C60: Avg. Daily | D60: Avg. Fleet During | F60: Annual Vehicle Revenue Hours | I60: Annual Passengers | L60: Proposed
C61: Service Hours | D61: Service Hours | G61: Contingency | H61: Contingency | L61: FY24
B62: All Zones - Avg. Wait Times 30min Peak | C62: 260 Weekdays | F62: Budget | G62: +10% | H62: +20% | I62: Low | J62: Med | K62: High | L62: Budget | M62: +10% | N62: +20% | O62: Diff Lo/Hi
B63: 7am - 11am + 3pm - 7pm | C63: 8 | D63: 3 | F63: =(C63*D63*260) -> 6240 | G63: =F63*1.1 -> 6864 | H63: =F63*1.2 -> 7488 | I63: =F63*5 -> 31200 | J63: =F63*5.5 -> 34320 | K63: =F63*6 -> 37440 | L63: =F63*65 -> 405600 | M63: =G63*65 -> 446160 | N63: =H63*65 -> 486720
B64: All Zones - Avg. Wait Times 40min Off Peak | C64: 260 Weekdays
B65: 11am - 3pm + 7pm - 9pm | C65: 6 | D65: 2 | F65: =(C65*D65*260) -> 3120 | G65: =F65*1.1 -> 3432 | H65: =F65*1.2 -> 3744 | I65: =F65*3 -> 9360 | J65: =F65*4 -> 12480 | K65: =F65*5 -> 15600 | L65: =F65*65 -> 202800 | M65: =G65*65 -> 223080 | N65: =H65*65 -> 243360
B66: All Zones - Avg. Wait Times 30min Off Peak | C66: 52 Weekend Days
B67: TNC Service Provider | J67: =L67/10 -> 3000 | L67: 30000
B68: Medicaid Trips | C68: 8 | D68: 0.5 | F68: =(C68*D68*60) -> 240 | G68: =F68*1.1 -> 264 | H68: =F68*1.2 -> 288 | I68: =F68*1.5 -> 360 | J68: =G68*1.5 -> 396 | K68: =H68*1.5 -> 432 | L68: =F68*65 -> 15600 | M68: =G68*65 -> 17160 | N68: =H68*65 -> 18720
B69: Commuter Bus Allocation | I69: =I30*$H$12 -> 3343.0075 | J69: =J30*$H$12 -> 4680.2105 | K69: =K30*$H$12 -> 5348.812 | L69: =I12 -> 97108.604 | M69: =L69*1.1 -> 106819.46 | N69: =L69*1.2 -> 116530.32
B70: Total | F70: =SUM(F63:F68) -> 9600 | G70: =SUM(G63:G68) -> 10560 | H70: =SUM(H63:H68) -> 11520 | I70: =SUM(I63:I69) -> 44263.007 | J70: =SUM(J63:J69) -> 54876.21 | K70: =SUM(K63:K69) -> 58820.812 | L70: =SUM(L63:L69) -> 751108.6 | M70: =SUM(M63:M69) -> 793219.46 | N70: =SUM(N63:N69) -> 865330.32 | O70: =N70-L70 -> 114221.72
B71: Projected Revenue | L71: =J70*C16 -> 54876.21 | P71: =L71+L74+L75 -> 198804.5
B72: =B36 -> Federal Grant Carbon Reduction Grant | C72: Based on hours in each city | L72: =(L36*K12)*-1 -> 40689
B73: Federal Revenue | L73: =L48*L12 -> 417152.3 | P73: =L73+L72 -> 457841.3
B74: State Revenue | L74: =L49*L12 -> 53354.57 | P74: =P73/2 -> 228920.65
B75: NEMT Revenue | L75: =(L38*K12)*-1 -> 90573.715 | P75: =P74-P71 -> 30116.155
B76: Total Revenue Sources | L76: =SUM(L71:L75) -> 656645.8
B77: Net Required Subsidy | L77: =L70-L76 -> 94462.808 | P77: =P75 -> 30116.155
B79: Estimates for Microtransit On-demand Harker Heights
C81: Avg. Daily | D81: Avg. Fleet During | F81: Annual Vehicle Revenue Hours | I81: Annual Passengers | L81: Proposed
C82: Service Hours | D82: Service Hours | G82: Contingency | H82: Contingency | L82: FY24
B83: All Zones - Avg. Wait Times 30min Peak | C83: 260 Weekdays | F83: Budget | G83: +10% | H83: +20% | I83: Low | J83: Med | K83: High | L83: Budget | M83: +10% | N83: +20% | O83: Diff Lo/Hi
B84: 7am - 11am + 3pm - 7pm | C84: 8 | D84: 3 | F84: =(C84*D84*260) -> 6240 | G84: =F84*1.1 -> 6864 | H84: =F84*1.2 -> 7488 | I84: =F84*5 -> 31200 | J84: =F84*5.5 -> 34320 | K84: =F84*6 -> 37440 | L84: =F84*65 -> 405600 | M84: =G84*65 -> 446160 | N84: =H84*65 -> 486720
B85: All Zones - Avg. Wait Times 40min Off Peak | C85: 260 Weekdays
B86: 11am - 3pm + 7pm - 9pm | C86: 6 | D86: 2 | F86: =(C86*D86*260) -> 3120 | G86: =F86*1.2 -> 3744 | H86: =F86*1.3 -> 4056 | I86: =F86*3 -> 9360 | J86: =F86*4 -> 12480 | K86: =F86*5 -> 15600 | L86: =F86*65 -> 202800 | M86: =G86*65 -> 243360 | N86: =H86*65 -> 263640
B87: All Zones - Avg. Wait Times 30min Off Peak | C87: 52 Weekend Days
B88: TNC Service Provider | J88: =L88/10 -> 1045.3 | L88: 10453
B89: Medicaid Trips | C89: 8 | D89: 0.5 | F89: =(C89*D89*52) -> 208 | G89: =F89*1.1 -> 228.8 | H89: =F89*1.2 -> 249.6 | I89: =F89*1.5 -> 312 | J89: =G89*1.5 -> 343.2 | K89: =H89*1.5 -> 374.4 | L89: =F89*65 -> 13520 | M89: =G89*65 -> 14872 | N89: =H89*65 -> 16224
B90: Commuter Bus Allocation | I90: =I30*$H$13 -> 2914.4326 | J90: =J30*$H$13 -> 4080.2056 | K90: =K30*$H$13 -> 4663.0921 | L90: =I13 -> 84659.242 | M90: =L90*1.1 -> 93125.166 | N90: =L90*1.2 -> 101591.09
B91: Total | F91: =SUM(F84:F89) -> 9568 | G91: =SUM(G84:G89) -> 10836.8 | H91: =SUM(H84:H89) -> 11793.6 | I91: =SUM(I84:I90) -> 43786.433 | J91: =SUM(J84:J90) -> 52268.706 | K91: =SUM(K84:K90) -> 58077.492 | L91: =SUM(L84:L90) -> 717032.24 | M91: =SUM(M84:M90) -> 797517.17 | N91: =SUM(N84:N90) -> 868175.09 | O91: =N91-L91 -> 151142.85
B92: Projected Revenue | L92: =J91*C16 -> 52268.706 | P92: =L92+L95+L96 -> 195717.23
B93: =B36 -> Federal Grant Carbon Reduction Grant | C93: Based on hours in each city | L93: =(L36*K13)*-1 -> 40553.37
B94: Federal Revenue | L94: =L48*L13 -> 415761.79 | P94: =L94+L93 -> 456315.16
B95: State Revenue | L95: =L49*L13 -> 53176.721 | P95: =P94/2 -> 228157.58
B96: NEMT Revenue | L96: =(L38*K13)*-1 -> 90271.803 | P96: =P95-P92 -> 32440.352
B97: Total Revenue Sources | L97: =SUM(L92:L96) -> 652032.39
B98: Net Required Subsidy | L98: =L91-L97 -> 64999.85 | P98: =P96 -> 32440.352
B100: Estimates for Microtransit On-demand Killeen
C102: Avg. Daily | D102: Avg. Fleet During | F102: Annual Vehicle Revenue Hours | I102: Annual Passengers | L102: Proposed
C103: Service Hours | D103: Service Hours | G103: Contingency | H103: Contingency | L103: FY24
B104: All Zones - Avg. Wait Times 30min Peak | C104: 260 Weekdays | F104: Budget | G104: +10% | H104: +20% | I104: Low | J104: Med | K104: High | L104: Budget | M104: +10% | N104: +20% | O104: Diff Lo/Hi
B105: 7am - 11am + 3pm - 7pm | C105: 8 | D105: =D11 -> 15 | F105: =(C105*D105*260) -> 31200 | G105: =F105*1.1 -> 34320 | H105: =F105*1.2 -> 37440 | I105: =F105*5 -> 156000 | J105: =F105*5.5 -> 171600 | K105: =F105*6 -> 187200 | L105: =F105*65 -> 2028000 | M105: =G105*65 -> 2230800 | N105: =H105*65 -> 2433600 | R105: =G11 -> 153143 | S105: =R105/R108 -> 0.68305204 | T105: Killeen
B106: All Zones - Avg. Wait Times 40min Off Peak | C106: 260 Weekdays | R106: =G12 -> 37964 | S106: =R106/R108 -> 0.16932793 | T106: Cove
B107: 11am - 3pm + 7pm - 9pm | C107: 6 | D107: =C11 -> 11 | F107: =(C107*D107*260) -> 17160 | G107: =F107*1.2 -> 20592 | H107: =F107*1.3 -> 22308 | I107: =F107*3 -> 51480 | J107: =F107*4 -> 68640 | K107: =F107*5 -> 85800 | L107: =F107*65 -> 1115400 | M107: =G107*65 -> 1338480 | N107: =H107*65 -> 1450020 | R107: =G13 -> 33097 | S107: =R107/R108 -> 0.14762002 | T107: Heights
B108: All Zones - Avg. Wait Times 30min Off Peak | C108: 52 Weekend Days | R108: =SUM(R105:R107) -> 224204
B109: TNC Service Provider | J109: =L109/10 -> 35000 | L109: 350000
B110: Medicaid Trips | C110: 8 | D110: 2 | F110: =(C110*D110*52) -> 832 | G110: =F110*1.1 -> 915.2 | H110: =F110*1.2 -> 998.4 | I110: =F110*1.5 -> 1248 | J110: =G110*1.5 -> 1372.8 | K110: =H110*1.5 -> 1497.6 | L110: =F110*65 -> 54080 | M110: =G110*65 -> 59488 | N110: =H110*65 -> 64896
...

Sheet Financial Plan OUTPUTS>>>

Sheet T1 Summary Table
E7: TABLE 1: Tahoe Basin Operating Financial Forecast Summary With Recommended Plan Elements
F9: FY 26-27(2027) | G9: FY 27-28 (2028) | H9: FY 28-29 (2029) | I9: FY 29-30 (2030) | J9: FY 30-31 (2031) | L9: 2027 %s
E11: Estimated Total Operating Cost (Status Quo) | F11: =SUM('T2-4 A1 TTD LL Costs'!G220,'T2-4 A1 TTD LL Costs'!G243,'T5-7 TART TNTTMA FinancialPlan'!G129,'T5-7 TART TNTTMA FinancialPlan'!G175) -> 23108271 | G11: =SUM('T2-4 A1 TTD LL Costs'!H220,'T2-4 A1 TTD LL Costs'!H243,'T5-7 TART TNTTMA FinancialPlan'!H129,'T5-7 TART TNTTMA FinancialPlan'!H175) -> 24018006 | H11: =SUM('T2-4 A1 TTD LL Costs'!I220,'T2-4 A1 TTD LL Costs'!I243,'T5-7 TART TNTTMA FinancialPlan'!I129,'T5-7 TART TNTTMA FinancialPlan'!I175) -> 24434407 | I11: =SUM('T2-4 A1 TTD LL Costs'!J220,'T2-4 A1 TTD LL Costs'!J243,'T5-7 TART TNTTMA FinancialPlan'!J129,'T5-7 TART TNTTMA FinancialPlan'!J175) -> 25544180 | J11: =SUM('T2-4 A1 TTD LL Costs'!K220,'T2-4 A1 TTD LL Costs'!K243,'T5-7 TART TNTTMA FinancialPlan'!K129,'T5-7 TART TNTTMA FinancialPlan'!K175) -> 26541674
E12: Estimated Total Operating Cost (w/ Service Plan) | F12: =SUM('T2-4 A1 TTD LL Costs'!G221,'T2-4 A1 TTD LL Costs'!G244,'T5-7 TART TNTTMA FinancialPlan'!G130,'T5-7 TART TNTTMA FinancialPlan'!G176) -> 23599171 | G12: =SUM('T2-4 A1 TTD LL Costs'!H221,'T2-4 A1 TTD LL Costs'!H244,'T5-7 TART TNTTMA FinancialPlan'!H130,'T5-7 TART TNTTMA FinancialPlan'!H176) -> 26067506 | H12: =SUM('T2-4 A1 TTD LL Costs'!I221,'T2-4 A1 TTD LL Costs'!I244,'T5-7 TART TNTTMA FinancialPlan'!I130,'T5-7 TART TNTTMA FinancialPlan'!I176) -> 27095907 | I12: =SUM('T2-4 A1 TTD LL Costs'!J221,'T2-4 A1 TTD LL Costs'!J244,'T5-7 TART TNTTMA FinancialPlan'!J130,'T5-7 TART TNTTMA FinancialPlan'!J176) -> 28307580 | J12: =SUM('T2-4 A1 TTD LL Costs'!K221,'T2-4 A1 TTD LL Costs'!K244,'T5-7 TART TNTTMA FinancialPlan'!K130,'T5-7 TART TNTTMA FinancialPlan'!K176) -> 29636474
E14: Total Revenue | F14: =SUM('T2-4 A1 TTD LL Costs'!G223,'T2-4 A1 TTD LL Costs'!G246,'T5-7 TART TNTTMA FinancialPlan'!G132,'T5-7 TART TNTTMA FinancialPlan'!G178) -> 27076406 | G14: =SUM('T2-4 A1 TTD LL Costs'!H223,'T2-4 A1 TTD LL Costs'!H246,'T5-7 TART TNTTMA FinancialPlan'!H132,'T5-7 TART TNTTMA FinancialPlan'!H178) -> 24601799 | H14: =SUM('T2-4 A1 TTD LL Costs'!I223,'T2-4 A1 TTD LL Costs'!I246,'T5-7 TART TNTTMA FinancialPlan'!I132,'T5-7 TART TNTTMA FinancialPlan'!I178) -> 24468850 | I14: =SUM('T2-4 A1 TTD LL Costs'!J223,'T2-4 A1 TTD LL Costs'!J246,'T5-7 TART TNTTMA FinancialPlan'!J132,'T5-7 TART TNTTMA FinancialPlan'!J178) -> 24646600 | J14: =SUM('T2-4 A1 TTD LL Costs'!K223,'T2-4 A1 TTD LL Costs'!K246,'T5-7 TART TNTTMA FinancialPlan'!K132,'T5-7 TART TNTTMA FinancialPlan'!K178) -> 25211000
E15: Core Recurring Transit Operating Revenue (FTA, TDA) | F15: =SUM('T2-4 A1 TTD LL Costs'!G224,'T2-4 A1 TTD LL Costs'!G247,'T5-7 TART TNTTMA FinancialPlan'!G133,'T5-7 TART TNTTMA FinancialPlan'!G179) -> 13243732 | G15: =SUM('T2-4 A1 TTD LL Costs'!H224,'T2-4 A1 TTD LL Costs'!H247,'T5-7 TART TNTTMA FinancialPlan'!H133,'T5-7 TART TNTTMA FinancialPlan'!H179) -> 12413500 | H15: =SUM('T2-4 A1 TTD LL Costs'!I224,'T2-4 A1 TTD LL Costs'!I247,'T5-7 TART TNTTMA FinancialPlan'!I133,'T5-7 TART TNTTMA FinancialPlan'!I179) -> 12408500 | I15: =SUM('T2-4 A1 TTD LL Costs'!J224,'T2-4 A1 TTD LL Costs'!J247,'T5-7 TART TNTTMA FinancialPlan'!J133,'T5-7 TART TNTTMA FinancialPlan'!J179) -> 12558400 | J15: =SUM('T2-4 A1 TTD LL Costs'!K224,'T2-4 A1 TTD LL Costs'!K247,'T5-7 TART TNTTMA FinancialPlan'!K133,'T5-7 TART TNTTMA FinancialPlan'!K179) -> 12552400 | L15: =F15/$F$14 -> 0.48912444 | M15: =G15/$F$14 -> 0.45846188 | N15: =H15/$F$14 -> 0.45827722 | O15: =I15/$F$14 -> 0.4638134 | P15: =J15/$F$14 -> 0.46359181
E16: Other State/Federal Funds (LCTOP, CRP) | F16: =SUM('T2-4 A1 TTD LL Costs'!G225,'T2-4 A1 TTD LL Costs'!G248,'T5-7 TART TNTTMA FinancialPlan'!G134,'T5-7 TART TNTTMA FinancialPlan'!G180) -> 545416 | G16: =SUM('T2-4 A1 TTD LL Costs'!H225,'T2-4 A1 TTD LL Costs'!H248,'T5-7 TART TNTTMA FinancialPlan'!H134,'T5-7 TART TNTTMA FinancialPlan'!H180) -> 545090 | H16: =SUM('T2-4 A1 TTD LL Costs'!I225,'T2-4 A1 TTD LL Costs'!I248,'T5-7 TART TNTTMA FinancialPlan'!I134,'T5-7 TART TNTTMA FinancialPlan'!I180) -> 273500 | I16: =SUM('T2-4 A1 TTD LL Costs'!J225,'T2-4 A1 TTD LL Costs'!J248,'T5-7 TART TNTTMA FinancialPlan'!J134,'T5-7 TART TNTTMA FinancialPlan'!J180) -> 8000 | J16: =SUM('T2-4 A1 TTD LL Costs'!K225,'T2-4 A1 TTD LL Costs'!K248,'T5-7 TART TNTTMA FinancialPlan'!K134,'T5-7 TART TNTTMA FinancialPlan'!K180) -> 273500 | L16: =F16/$F$14 -> 0.020143589 | M16: =G16/$F$14 -> 0.020131549 | N16: =H16/$F$14 -> 0.010101045 | O16: =I16/$F$14 -> 0.00029546019 | P16: =J16/$F$14 -> 0.010101045
E17: Public Local Funds (County, City, TOT, etc.) | F17: =SUM('T2-4 A1 TTD LL Costs'!G226,'T2-4 A1 TTD LL Costs'!G249,'T5-7 TART TNTTMA FinancialPlan'!G135,'T5-7 TART TNTTMA FinancialPlan'!G181) -> 9808072 | G17: =SUM('T2-4 A1 TTD LL Costs'!H226,'T2-4 A1 TTD LL Costs'!H249,'T5-7 TART TNTTMA FinancialPlan'!H135,'T5-7 TART TNTTMA FinancialPlan'!H181) -> 9969831 | H17: =SUM('T2-4 A1 TTD LL Costs'!I226,'T2-4 A1 TTD LL Costs'!I249,'T5-7 TART TNTTMA FinancialPlan'!I135,'T5-7 TART TNTTMA FinancialPlan'!I181) -> 10122150 | I17: =SUM('T2-4 A1 TTD LL Costs'!J226,'T2-4 A1 TTD LL Costs'!J249,'T5-7 TART TNTTMA FinancialPlan'!J135,'T5-7 TART TNTTMA FinancialPlan'!J181) -> 10415500 | J17: =SUM('T2-4 A1 TTD LL Costs'!K226,'T2-4 A1 TTD LL Costs'!K249,'T5-7 TART TNTTMA FinancialPlan'!K135,'T5-7 TART TNTTMA FinancialPlan'!K181) -> 10720400 | L17: =F17/$F$14 -> 0.36223685 | M17: =G17/$F$14 -> 0.36821102 | N17: =H17/$F$14 -> 0.37383654 | O17: =I17/$F$14 -> 0.3846707 | P17: =J17/$F$14 -> 0.39593142
E18: SB 125 | F18: =SUM('T2-4 A1 TTD LL Costs'!G227,'T2-4 A1 TTD LL Costs'!G250,'T5-7 TART TNTTMA FinancialPlan'!G136,'T5-7 TART TNTTMA FinancialPlan'!G182) -> 1575000 | G18: =SUM('T2-4 A1 TTD LL Costs'!H227,'T2-4 A1 TTD LL Costs'!H250,'T5-7 TART TNTTMA FinancialPlan'!H136,'T5-7 TART TNTTMA FinancialPlan'!H182) -> 0 | H18: =SUM('T2-4 A1 TTD LL Costs'!I227,'T2-4 A1 TTD LL Costs'!I250,'T5-7 TART TNTTMA FinancialPlan'!I136,'T5-7 TART TNTTMA FinancialPlan'!I182) -> 0 | I18: =SUM('T2-4 A1 TTD LL Costs'!J227,'T2-4 A1 TTD LL Costs'!J250,'T5-7 TART TNTTMA FinancialPlan'!J136,'T5-7 TART TNTTMA FinancialPlan'!J182) -> 0 | J18: =SUM('T2-4 A1 TTD LL Costs'!K227,'T2-4 A1 TTD LL Costs'!K250,'T5-7 TART TNTTMA FinancialPlan'!K136,'T5-7 TART TNTTMA FinancialPlan'!K182) -> 0 | L18: =F18/$F$14 -> 0.058168724 | M18: =G18/$F$14 -> 0 | N18: =H18/$F$14 -> 0 | O18: =I18/$F$14 -> 0 | P18: =J18/$F$14 -> 0
E19: Private/Non Profit Funds | F19: =SUM('T2-4 A1 TTD LL Costs'!G228,'T2-4 A1 TTD LL Costs'!G229,'T2-4 A1 TTD LL Costs'!G251,'T5-7 TART TNTTMA FinancialPlan'!G137,'T5-7 TART TNTTMA FinancialPlan'!G183) -> 882905 | G19: =SUM('T2-4 A1 TTD LL Costs'!H228,'T2-4 A1 TTD LL Costs'!H229,'T2-4 A1 TTD LL Costs'!H251,'T5-7 TART TNTTMA FinancialPlan'!H137,'T5-7 TART TNTTMA FinancialPlan'!H183) -> 945578 | H19: =SUM('T2-4 A1 TTD LL Costs'!I228,'T2-4 A1 TTD LL Costs'!I229,'T2-4 A1 TTD LL Costs'!I251,'T5-7 TART TNTTMA FinancialPlan'!I137,'T5-7 TART TNTTMA FinancialPlan'!I183) -> 936900 | I19: =SUM('T2-4 A1 TTD LL Costs'!J228,'T2-4 A1 TTD LL Costs'!J229,'T2-4 A1 TTD LL Costs'!J251,'T5-7 TART TNTTMA FinancialPlan'!J137,'T5-7 TART TNTTMA FinancialPlan'!J183) -> 936900 | J19: =SUM('T2-4 A1 TTD LL Costs'!K228,'T2-4 A1 TTD LL Costs'!K229,'T2-4 A1 TTD LL Costs'!K251,'T5-7 TART TNTTMA FinancialPlan'!K137,'T5-7 TART TNTTMA FinancialPlan'!K183) -> 936900 | L19: =F19/$F$14 -> 0.03260791 | M19: =G19/$F$14 -> 0.034922582 | N19: =H19/$F$14 -> 0.034602081 | O19: =I19/$F$14 -> 0.034602081 | P19: =J19/$F$14 -> 0.034602081
E20: Fares | F20: =SUM('T2-4 A1 TTD LL Costs'!G252,'T5-7 TART TNTTMA FinancialPlan'!G138,'T5-7 TART TNTTMA FinancialPlan'!G184) -> 449156 | G20: =SUM('T2-4 A1 TTD LL Costs'!H252,'T5-7 TART TNTTMA FinancialPlan'!H138,'T5-7 TART TNTTMA FinancialPlan'!H184) -> 395700 | H20: =SUM('T2-4 A1 TTD LL Costs'!I252,'T5-7 TART TNTTMA FinancialPlan'!I138,'T5-7 TART TNTTMA FinancialPlan'!I184) -> 395700 | I20: =SUM('T2-4 A1 TTD LL Costs'!J252,'T5-7 TART TNTTMA FinancialPlan'!J138,'T5-7 TART TNTTMA FinancialPlan'!J184) -> 395700 | J20: =SUM('T2-4 A1 TTD LL Costs'!K252,'T5-7 TART TNTTMA FinancialPlan'!K138,'T5-7 TART TNTTMA FinancialPlan'!K184) -> 395700 | L20: =F20/$F$14 -> 0.016588465 | M20: =G20/$F$14 -> 0.0146142 | N20: =H20/$F$14 -> 0.0146142 | O20: =I20/$F$14 -> 0.0146142 | P20: =J20/$F$14 -> 0.0146142
E21: Other (Membership, Program Management) | F21: =SUM('T5-7 TART TNTTMA FinancialPlan'!G185) -> 325359 | G21: =SUM('T5-7 TART TNTTMA FinancialPlan'!H185) -> 325400 | H21: =SUM('T5-7 TART TNTTMA FinancialPlan'!I185) -> 325400 | I21: =SUM('T5-7 TART TNTTMA FinancialPlan'!J185) -> 325400 | J21: =SUM('T5-7 TART TNTTMA FinancialPlan'!K185) -> 325400 | L21: =F21/$F$14 -> 0.012016329 | M21: =G21/$F$14 -> 0.012017843 | N21: =H21/$F$14 -> 0.012017843 | O21: =I21/$F$14 -> 0.012017843 | P21: =J21/$F$14 -> 0.012017843
E23: Surplus/Deficit (Status Quo) | F23: =F14-F11 -> 3968135.5 | G23: =G14-G11 -> 583793.2 | H23: =H14-H11 -> 34443.325 | I23: =I14-I11 -> -897579.57 | J23: =J14-J11 -> -1330674
E24: Surplus/Deficit (w/ Service Plan) | F24: =F14-F12 -> 3477235.5 | G24: =G14-G12 -> -1465706.8 | H24: =H14-H12 -> -2627056.7 | I24: =I14-I12 -> -3660979.6 | J24: =J14-J12 -> -4425474 | L24: =SUM(L16,L18,L19,L20,L21) -> 0.13952502 | M24: =SUM(M16,M18,M19,M20,M21) -> 0.081686174
E30: Inflation assumptions in footnote in text
E31: What are notes attached to?
M32: Drop in 5307 funds from no more carryover in 27-28
F41: 1 | G41: TDA
F42: =F41/0.4 -> 2.5 | G42: 5311
G45: 1=.4*X

Sheet Questions
D4: Question | E4: Lake Link | F4: What revenues can we count on for 27-28 for Lake Link?
E6: Kira | F6: Do we recommend Transportation user fee?

Sheet T2-4 A1 TTD LL Costs
G1: FY 26-27 | H1: FY 27-28 | I1: FY 28-29 | J1: FY 29-30 | K1: FY 30-31 | O1: 1.04 | P1: Inflation escalator (general)
A2: TTD | B2: 24-25 VSH | E2: Cost per hr | G2: ='VRH Rates'!D7 -> 123.17 | H2: =G2*$O$1 -> 128.0968 | I2: =H2*$O$1 -> 133.22067 | J2: =I2*$O$1 -> 138.5495 | K2: =J2*$O$1 -> 144.09148 | O2: 1.01 | P2: Growth of FTA funds
B3: ='Operating Stats'!F43 -> 35679.5 | E3: Cost per mi | G3: ='VRH Rates'!E7 -> 1.6 | H3: =G3*$O$1 -> 1.664 | I3: =H3*$O$1 -> 1.73056 | J3: =I3*1.1 -> 1.903616 | K3: =J3*1.03 -> 1.9607245
B5: 24-25 VSM
B6: ='Operating Stats'!G43 -> 534843
A7: Lake Link | B7: 25-26 VSH | E7: Cost per hr | G7: ='VRH Rates'!D9 -> 65.23 | H7: =G7*$O$1 -> 67.8392 | I7: =H7*$O$1 -> 70.552768 | J7: =I7*$O$1 -> 73.374879 | K7: =J7*$O$1 -> 76.309874
B8: ='Operating Stats'!F44 -> 47002 | E8: Cost per mi | G8: 0 | H8: =G8*$O$1 -> 0 | I8: =H8*$O$1 -> 0 | J8: =I8*1.1 -> 0 | K8: =J8*1.03 -> 0
B9: 25-26 VSM
B10: ='Operating Stats'!G15 -> 366322 | E10: Population Change Rate | G10: 0.00025 | H10: 0.00025 | I10: 0.00025 | J10: 0.00025 | K10: 0.00025 | M10: RTP pop projections
D13: TABLE 2: South Shore Operating Costs
G15: FY 26-27 | H15: FY 27-28 | I15: FY 28-29 | J15: FY 29-30 | K15: FY 30-31
D17: TTD Base Case Operating Cost 1
E18: Marginal Operating Costs | G18: =($B$3*G2)+($B$6*G3) -> 5250392.8 | H18: =($B$3*H2)+($B$6*H3) -> 5460408.5 | I18: =($B$3*I2)+($B$6*I3) -> 5678824.9 | J18: =($B$3*J2)+($B$6*J3) -> 5961512.5 | K18: =($B$3*K2)+($B$6*K3) -> 6189791.7
E19: Fixed Costs | G19: ='VRH Rates'!F7 -> 2077415.2 | H19: =G19*$O$1 -> 2160511.8 | I19: =H19*$O$1 -> 2246932.2 | J19: =I19*$O$1 -> 2336809.5 | K19: =J19*$O$1 -> 2430281.9
E20: Emerald Bay Shuttle (Route 30)3 | G20: 517288 | H20: 523384 | I20: 0 | J20: 0 | K20: 0 | M20: =H20/G20-1 -> 0.011784538
E21: Total | G21: =SUM(G18:G20) -> 7845096 | H21: =SUM(H18:H20) -> 8144304.3 | I21: =SUM(I18:I19) -> 7925757.1 | J21: =SUM(J18:J19) -> 8298322.1 | K21: =SUM(K18:K19) -> 8620073.6
D23: Lake Link Base Case Operating Cost 2
E24: Marginal Operating Costs | G24: =($B$8*G7)+($B$10*G8) -> 3065940.5 | H24: =($B$8*H7)+($B$10*H8) -> 3188578.1 | I24: =($B$8*I7)+($B$10*I8) -> 3316121.2 | J24: =($B$8*J7)+($B$10*J8) -> 3448766 | K24: =($B$8*K7)+($B$10*K8) -> 3586716.7
E25: Fixed Costs | G25: ='VRH Rates'!F9+'VRH Rates'!G9+'VRH Rates'!H9 -> 162900 | H25: =G25*$O$1 -> 169416 | I25: =H25*$O$1 -> 176192.64 | J25: =I25*$O$1 -> 183240.35 | K25: =J25*$O$1 -> 190569.96 | Q25: Inflation | R25: 0 | S25: 1.04 | T25: 1.08 | U25: 1.12 | V25: 1.16
E26: Total | G26: =SUM(G24:G25) -> 3228840.5 | H26: =SUM(H24:H25) -> 3357994.1 | I26: =SUM(I24:I25) -> 3492313.8 | J26: =SUM(J24:J25) -> 3632006.4 | K26: =SUM(K24:K25) -> 3777286.7 | Q26: Implementation Plan - Do not Delete
D28: Service Plan Element Marginal Operating Costs | M28: =G21+G26 -> 11073936 | R28: FY 26-27 | S28: FY 27-28 | T28: FY 28-29 | U28: FY 29-30 | V28: FY 30-31
E29: =Q29 -> Eliminate 19X and Replace with US 50 Service (4 Round Trips) | G29: =IF(R29=1,ROUND('[31] T25 Service Alts'!$M$26,-2),0) -> 476500 | H29: =IF(S29=1,ROUND('[31] T25 Service Alts'!$M$26*S25,-2),0) -> 495600 | I29: =IF(T29=1,ROUND('[31] T25 Service Alts'!$M$26*T25,-2),0) -> 514600 | J29: =IF(U29=1,ROUND('[31] T25 Service Alts'!$M$26*U25,-2),0) -> 533700 | K29: =IF(V29=1,ROUND('[31] T25 Service Alts'!$M$26*V25,-2),0) -> 552700 | Q29: Eliminate 19X and Replace with US 50 Service (4 Round Trips) | R29: 1 | S29: 1 | T29: 1 | U29: 1 | V29: 1
E30: =Q30 -> Seasonal Expansion of Route 28 to Spooner Mobility Hub | G30: =IF(R30=1,ROUND('[31] T25 Service Alts'!$M$32,-2),0) -> 0 | H30: =IF(S30=1,ROUND('[31] T25 Service Alts'!$M$30*S25,-2),0) -> 137200 | I30: =IF(T30=1,ROUND('[31] T25 Service Alts'!$M$30*T25,-2),0) -> 142400 | J30: =IF(U30=1,ROUND('[31] T25 Service Alts'!$M$30*U25,-2),0) -> 147700 | K30: =IF(V30=1,ROUND('[31] T25 Service Alts'!$M$30*V25,-2),0) -> 153000 | Q30: Seasonal Expansion of Route 28 to Spooner Mobility Hub | R30: 0 | S30: 1 | T30: 1 | U30: 1 | V30: 1
E31: =Q31 -> Continue to Operate the Emerald Bay Shuttle (Route 30) Beyond the Pilot Period | G31: =IF(R31=1,ROUND('[31] T25 Service Alts'!$M$37,-2),0) -> 0 | H31: =IF(S31=1,ROUND('[31] T25 Service Alts'!$M$37*S25,-2),0) -> 0 | I31: =IF(T31=1,ROUND('[31] T25 Service Alts'!$M$35*T25,-2),0) -> 558700 | J31: =IF(U31=1,ROUND('[31] T25 Service Alts'!$M$35*U25,-2),0) -> 579400 | K31: =IF(V31=1,ROUND('[31] T25 Service Alts'!$M$35*V25,-2),0) -> 600100 | Q31: Continue to Operate the Emerald Bay Shuttle (Route 30) Beyond the Pilot Period | R31: 0 | S31: 0 | T31: 1 | U31: 1 | V31: 1
E32: Pilot Co-mingled Paratransit/Microtransit Service to Meyers 4 | G32: =IF(R32=1,ROUND('[31] T25 Service Alts'!$M$43,-2),0) -> 0 | H32: =IF(S32=1,ROUND('[31] T25 Service Alts'!$M$41*S25,-2),0) -> 357300 | I32: =IF(T32=1,ROUND('[31] T25 Service Alts'!$M$41*T25,-2),0) -> 371000 | J32: =IF(U32=1,ROUND('[31] T25 Service Alts'!$M$41*U25,-2),0) -> 384800 | K32: =IF(V32=1,ROUND('[31] T25 Service Alts'!$M$41*V25,-2),0) -> 398500 | Q32: Pilot Co-mingled Paratransit/Microtransit Service to Meyers | R32: 0 | S32: 1 | T32: 1 | U32: 1 | V32: 1
E33: =Q33 -> Discontinue Route 50 Deviation to LTCC during Summer | G33: =IF(R33=1,ROUND('[31] T25 Service Alts'!$M$37,-2),0) -> -10600 | H33: =IF(S33=1,ROUND('[31] T25 Service Alts'!$M$37*S25,-2),0) -> -11000 | I33: =IF(T33=1,ROUND('[31] T25 Service Alts'!$M$37*T25,-2),0) -> -11400 | J33: =IF(U33=1,ROUND('[31] T25 Service Alts'!$M$37*U25,-2),0) -> -11800 | K33: =IF(V33=1,ROUND('[31] T25 Service Alts'!$M$37*V25,-2),0) -> -12300 | Q33: Discontinue Route 50 Deviation to LTCC during Summer | R33: 1 | S33: 1 | T33: 1 | U33: 1 | V33: 1
E35: TTD Service Plan Costs | G35: =SUM(G29:G31,G33) -> 465900 | H35: =SUM(H29:H31,H33) -> 621800 | I35: =SUM(I29:I31,I33) -> 1204300 | J35: =SUM(J29:J31,J33) -> 1249000 | K35: =SUM(K29:K31,K33) -> 1293500 | M35: =SUM(G35:K35) -> 4834500
E36: Lake Link Service Plan Costs | G36: =SUM(G32) -> 0 | H36: =SUM(H32) -> 357300 | I36: =SUM(I32) -> 371000 | J36: =SUM(J32) -> 384800 | K36: =SUM(K32) -> 398500 | M36: =SUM(G36:K36) -> 1511600
E37: Total Service Plan Costs | G37: =SUM(G29:G34) -> 465900 | H37: =SUM(H29:H34) -> 979100 | I37: =SUM(I29:I34) -> 1575300 | J37: =SUM(J29:J34) -> 1633800 | K37: =SUM(K29:K34) -> 1692000 | M37: =SUM(G37:K37) -> 6346100
D39: Total South Shore Transit Operating Cost (Status Quo) | G39: =G21+G26 -> 11073936 | H39: =H21+H26 -> 11502298 | I39: =I21+I26 -> 11418071 | J39: =J21+J26 -> 11930328 | K39: =K21+K26 -> 12397360
D40: Total South Shore Transit Operating Cost (with Service Plan Elements) | G40: =G21+G26+G35 -> 11539836 | H40: =H21+H26+H35 -> 12124098 | I40: =I21+I26+I35 -> 12622371 | J40: =J21+J26+J35 -> 13179328 | K40: =K21+K26+K35 -> 13690860
D42: Note 1: TTD base case costs based upon FY 2024-25 actual expenses and the LSC Cost Model (Existing Conditions Memo) plus 4% annual inflation and FY 2024-25 service levels. Assumes 4% annual inflation rate moving forward.
D43: Note 2: Lake Link base case costs based upon the current approved SSTMA/Downtowner contract and 2027 projected service levels. Assumes 4% annual inflation rate moving forward.
D44: Note 3: Base Case operating costs reflect 2026 and 2027 operating seasons and correspond with OWP FYs and contract costs.
D45: Note 4: Uses Lake Link costs to project future costs, assuming that this co-mingled service would be operated by a third-party contractor.
D46: Source: LSC Transportation Consultants, Inc.
D55: TABLE A1: South Shore Financial Plan - Operating | M55: 5-Year Plan Revenues/ Costs
B56: APPENDIX
G57: FY 26-27 | H57: FY 27-28 | I57: FY 28-29 | J57: FY 29-30 | K57: FY 30-31 | O57: Notes
D59: OPERATING REVENUE - RECCURING FUNDS
E60: FTA 5307 (Lake Tahoe UZA)1 - Formula Based | G60: ='FTA Allocation Split (26-27)'!G34 -> 1569548.1 | H60: =ROUND(G60*$O$2,-2) -> 1585200 | I60: =ROUND(H60*$O$2,-2) -> 1601100 | J60: =ROUND(I60*$O$2,-2) -> 1617100 | K60: =ROUND(J60*$O$2,-2) -> 1633300 | M60: =SUM(G60:K60) -> 8006248.1 | O60: 1% increase annually
E61: FTA 5307 (Formally CMAQ Funds)1 | G61: 596121 | H61: =ROUND(G61*$O$2,-2) -> 602100 | I61: =ROUND(H61*$O$2,-2) -> 608100 | J61: =ROUND(I61*$O$2,-2) -> 614200 | K61: =ROUND(J61*$O$2,-2) -> 620300 | M61: =SUM(G61:K61) -> 3040821 | O61: 1% increase annually
E62: FTA 5307 (Lake Tahoe UZA)1 - Carryover Revenue | G62: 946281.95 | H62: -- | I62: -- | J62: -- | K62: --
E63: FTA 5310 (Lake Tahoe UZA)1 - Formula Based | G63: ='25_26 FTA Funding Split (INFO)'!J35 -> 0 | H63: =ROUND('FTA Allocation Split (26-27)'!J35*'T2-4 A1 TTD LL Costs'!O2,-2) -> 76000 | I63: 0 | J63: =ROUND('FTA Allocation Split (26-27)'!J35*'T2-4 A1 TTD LL Costs'!O2^4,-2) -> 78300 | K63: 0 | M63: =SUM(G63:K63) -> 154300 | O63: 1% increase yearly
E64: FTA 5310 (Lake Tahoe UZA)1 - Carryover Revenue | G64: 30277 | H64: -- | I64: -- | J64: -- | K64: -- | M64: =SUM(G64:K64) -> 30277 | O64: 1% increase yearly
E65: FTA 5311 (NV DOT)1 | G65: 1798577 | H65: =ROUND(G65*1.01,-2) -> 1816600 | I65: =ROUND(H65*1.01,-2) -> 1834800 | J65: =ROUND(I65*1.01,-2) -> 1853100 | K65: =ROUND(J65*1.01,-2) -> 1871600 | M65: =SUM(G65:K65) -> 9174677 | O65: 1% increase yearly. NV gets $9.8 million total FTA 5311
E66: Local Transportation Fund (LTF)2 | G66: 1263326 | H66: =ROUND(G66*(1+H10),-2) -> 1263600 | I66: =ROUND(H66*(1+I10),-2) -> 1263900 | J66: =ROUND(I66*(1+J10),-2) -> 1264200 | K66: =ROUND(J66*(1+K10),-2) -> 1264500 | M66: =SUM(G66:K66) -> 6319526 | O66: Annual change based on projected County population change
E67: State Transit Assistance (STA)2 | G67: 581801 | H67: =ROUND(G67*(1+H10),-2) -> 581900 | I67: =H67 -> 581900 | J67: =I67 -> 581900 | K67: =J67 -> 581900 | M67: =SUM(G67:K67) -> 2909401 | O67: Annual change based on projected County population change
E68: Total Reccuring Apportioned Funds | G68: =SUM(G60:G67) -> 6785932 | H68: =SUM(H60:H67) -> 5925400 | I68: =SUM(I60:I67) -> 5889800 | J68: =SUM(J60:J67) -> 6008800 | K68: =SUM(K60:K67) -> 5971600 | M68: =SUM(G68:K68) -> 30581532
D70: OPERATING REVENUE - VARIABLE FUNDS
E71: Tahoe Transportation District (TTD)
E72: Fare Revenues (Passenger Revenues)3 | G72: ='Operating Stats'!E7*'Fare Rates'!C7+'Operating Stats'!E8*'Fare Rates'!C7+'Operating Stats'!E9*'Fare Rates'!C9+'Operating Stats'!E10*'Fare Rates'!C10+'Operating Stats'!E11*'Fare Rates'!C6+'Operating Stats'!E12*'Fare Rates'!C6+'Operating Stats'!E13*'Fare Rates'!C6 -> 53500 | H72: 0 | I72: 0 | J72: 0 | K72: 0 | M72: =SUM(G72:K72) -> 53500 | O72: Are we sticking with $0 fare rec or are we changing to something lower ($2)?
E73: Low Carbon Transit Operations Program (LCTOP) - Operating4 | G73: 265506 | H73: 0 | I73: =ROUND(G73,-2) -> 265500 | J73: 0 | K73: =I73 -> 265500 | M73: =SUM(G73:K73) -> 796506 | O73: TTD gets every other year
E74: Electrification Credits4 | G74: 8000 | H74: =G74 -> 8000 | I74: =G74 -> 8000 | J74: =H74 -> 8000 | K74: =I74 -> 8000 | M74: =SUM(G74:K74) -> 40000
E75: SB 125 (Operating) | G75: 825000 | H75: 0 | I75: 0 | J75: =I75*(1+J10) -> 0 | K75: =J75*(1+K10) -> 0 | M75: =SUM(G75:K75) -> 825000
E76: Nevada State Parks4 | G76: 85000 | H76: =G76 -> 85000 | I76: =H76 -> 85000 | J76: =I76 -> 85000 | K76: =J76 -> 85000 | M76: =SUM(G76:K76) -> 425000
E77: Tahoe Douglas Visitor Authority4 | G77: 120000 | H77: =G77 -> 120000 | I77: =H77 -> 120000 | J77: =I77 -> 120000 | K77: =J77 -> 120000 | M77: =SUM(G77:K77) -> 600000
E78: Interest Revenue4 | G78: 18000 | H78: =G78 -> 18000 | I78: =H78 -> 18000 | J78: =I78 -> 18000 | K78: =J78 -> 18000 | M78: =SUM(G78:K78) -> 90000
E79: Keep Tahoe Blue (Emerald Bay Shuttle)5 | G79: 8322 | H79: =38000-G79 -> 29678 | I79: 0 | J79: 0 | K79: 0 | M79: =SUM(G79:K79) -> 38000 | O79: Total allocated through FY 27-28: $38,000
E80: Carbon Reduction Program (Emerald Bay Shuttle)5 | G80: 271910 | H80: =809000-G80 -> 537090 | I80: 0 | J80: 0 | K80: 0 | M80: =SUM(G80:K80) -> 809000 | O80: Total allocated through FY 27-28: $809,000
E81: El Dorado County (Emerald Bay Shuttle)5 | G81: 331240 | H81: =431395-G81 -> 100155 | I81: 0 | J81: 0 | K81: 0 | M81: =SUM(G81:K81) -> 431395 | O81: Total allocated through FY 27-28: 431,395 (AQMD, VMT Reduction Fund)
E82: Placer County (Emerald Bay Shuttle)5 | G82: 8324 | H82: =38000-G82 -> 29676 | I82: 0 | J82: 0 | K82: 0 | M82: =SUM(G82:K82) -> 38000 | O82: Total allocated through FY 27-28: $38,000
E84: Lake Link | F84: 2026 | G84: FY 26-27(2027) | H84: FY 27-28 (2028) | I84: FY 28-29 (2029) | J84: FY 29-30 (2030) | K84: FY 30-31 (2031)
E85: SB 125 (Operating) | F85: =G85 -> 750000 | G85: 750000 | H85: 0 | I85: 0 | J85: 0 | K85: 0 | M85: =SUM(G85:K85) -> 750000 | O85: Assumes AB 125 allocation in FY 2026-27
E86: Douglas County6 | F86: 650000 | G86: 750000 | H86: 850000 | I86: =H86 -> 850000 | J86: =I86 -> 850000 | K86: =J86 -> 850000 | M86: =SUM(G86:K86) -> 4150000
E87: City of South Lake Tahoe6 | F87: 850000 | G87: 1100000 | H87: =G87 -> 1100000 | I87: =H87 -> 1100000 | J87: =I87 -> 1100000 | K87: =J87 -> 1100000 | M87: =SUM(G87:K87) -> 5500000
B88: =G88/F88-1 -> 0.12180187 | E88: Tahoe Blue Events Center Mitigation Fee7 | F88: 613053 | G88: 687724 | H88: =MIN(ROUND(G88*1.06,-2),750000) -> 729000 | I88: =MIN(ROUND(H88*1.06,-2),750000) -> 750000 | J88: =MIN(ROUND(I88*1.06,-2),750000) -> 750000 | K88: =MIN(ROUND(J88*1.06,-2),750000) -> 750000 | M88: =SUM(G88:K88) -> 3666724 | O88: Assumes no sur charge inflation
E89: South Lake Tahoe Tourism Improvement District (SLTTID)8 | F89: 25000 | G89: 0 | H89: 0 | I89: =H89 -> 0 | J89: =I89 -> 0 | K89: =J89 -> 0 | M89: =SUM(G89:K89) -> 0
E90: Heavenly8 | F90: 15000 | G90: 0 | H90: 0 | I90: =H90 -> 0 | J90: =I90 -> 0 | K90: =J90 -> 0 | M90: =SUM(G90:K90) -> 0
E91: Ceasars Entertainment8 | F91: 65000 | G91: 0 | H91: 0 | I91: =H91 -> 0 | J91: =I91 -> 0 | K91: =J91 -> 0 | M91: =SUM(G91:K91) -> 0
E92: Roundhill Pines Resort8 | F92: 85000 | G92: 0 | H92: 0 | I92: =H92 -> 0 | J92: =I92 -> 0 | K92: =J92 -> 0 | M92: =SUM(G92:K92) -> 0
E93: Advance Learning8 | F93: 25000 | G93: 0 | H93: 0 | I93: =H93 -> 0 | J93: =I93 -> 0 | K93: =J93 -> 0 | M93: =SUM(G93:K93) -> 0
E94: Lake Tahoe Visitor's Authority8 | F94: 62100 | G94: 0 | H94: 0 | I94: =H94 -> 0 | J94: =I94 -> 0 | K94: =J94 -> 0 | M94: =SUM(G94:K94) -> 0
E95: Lake Tahoe Community College (LTCC)8 | F95: 25000 | G95: 0 | H95: 0 | I95: =H95 -> 0 | J95: =I95 -> 0 | K95: =J95 -> 0 | M95: =SUM(G95:K95) -> 0
E97: TTD Variable Funds | F97: =SUM(F85:F95) -> 3165153 | G97: =SUM(G72:G82) -> 1994802 | H97: =SUM(H72:H82) -> 927599 | I97: =SUM(I72:I82) -> 496500 | J97: =SUM(J72:J82) -> 231000 | K97: =SUM(K72:K82) -> 496500 | O97: I think it is best to say recurring
E98: Lake Link Variable Funds | G98: =SUM(G85:G95) -> 3287724 | H98: =SUM(H85:H95) -> 2679000 | I98: =SUM(I85:I95) -> 2700000 | J98: =SUM(J85:J95) -> 2700000 | K98: =SUM(K85:K95) -> 2700000
E99: South Shore Total Variable Funds | G99: =SUM(G73:G95) -> 5229026 | H99: =SUM(H73:H95) -> 3606599 | I99: =SUM(I73:I95) -> 3196500 | J99: =SUM(J73:J95) -> 2931000 | K99: =SUM(K73:K95) -> 3196500
D101: SUMMARY OF TOTAL SOUTH SHORE TRANSIT OPERATING REVENUE
E102: TTD Operating Revenue | G102: =SUM(G68,G97) -> 8780734 | H102: =SUM(H68,H97) -> 6852999 | I102: =SUM(I68,I97) -> 6386300 | J102: =SUM(J68,J97) -> 6239800 | K102: =SUM(K68,K97) -> 6468100 | M102: =SUM(G102:K102) -> 34727933
E103: Lake Link Operating Revenue | G103: =G98 -> 3287724 | H103: =H98 -> 2679000 | I103: =I98 -> 2700000 | J103: =J98 -> 2700000 | K103: =K98 -> 2700000 | M103: =SUM(G103:K103) -> 14066724
E104: Total South Shore Operating Revenue | G104: =SUM(G102:G103) -> 12068458 | H104: =SUM(H102:H103) -> 9531999 | I104: =SUM(I102:I103) -> 9086300 | J104: =SUM(J102:J103) -> 8939800 | K104: =SUM(K102:K103) -> 9168100 | M104: =SUM(G104:K104) -> 48794657
E106: TTD Operating Costs (Status Quo) | G106: =G21 -> 7845096 | H106: =H21 -> 8144304.3 | I106: =I21 -> 7925757.1 | J106: =J21 -> 8298322.1 | K106: =K21 -> 8620073.6 | M106: =SUM(G106:K106) -> 40833553
E107: Lake Link Operating Costs (Status Quo) | G107: =G26 -> 3228840.5 | H107: =H26 -> 3357994.1 | I107: =I26 -> 3492313.8 | J107: =J26 -> 3632006.4 | K107: =K26 -> 3777286.7 | M107: =SUM(G107:K107) -> 17488441
E108: TOTAL South Shore Transit Operating Costs (Status Quo) | G108: =G106+G107 -> 11073936 | H108: =H106+H107 -> 11502298 | I108: =I106+I107 -> 11418071 | J108: =J106+J107 -> 11930328 | K108: =K106+K107 -> 12397360 | M108: =SUM(G108:K108) -> 58321995
E109: TTD Operating Costs (w/ Service Plan) | G109: =G21+G35 -> 8310996 | H109: =H21+H35 -> 8766104.3 | I109: =I21+I35 -> 9130057.1 | J109: =J21+J35 -> 9547322.1 | K109: =K21+K35 -> 9913573.6 | M109: =SUM(G109:K109) -> 45668053
E110: Lake Link Operating Costs (w/ Service Plan) | G110: =G26+G36 -> 3228840.5 | H110: =H26+H36 -> 3715294.1 | I110: =I26+I36 -> 3863313.8 | J110: =J26+J36 -> 4016806.4 | K110: =K26+K36 -> 4175786.7 | M110: =SUM(G110:K110) -> 19000041
E111: TOTAL South Shore Transit Operating Costs (w/ Service Plan) | G111: =+G40 -> 11539836 | H111: =+H40 -> 12124098 | I111: =+I40 -> 12622371 | J111: =+J40 -> 13179328 | K111: =+K40 -> 13690860 | M111: =SUM(G111:K111) -> 63156495
E113: TTD Operating Surplus/Deficit (Status Quo) | G113: =G102-G106 -> 935638.01 | H113: =H102-H106 -> -1291305.3 | I113: =I102-I106 -> -1539457.1 | J113: =J102-J106 -> -2058522.1 | K113: =K102-K106 -> -2151973.6 | M113: =SUM(G113:K113) -> -6105620.1
E114: TTD Operating Surplus/Deficit (w/ Service Plan) | G114: =G102-G109 -> 469738.01 | H114: =H102-H109 -> -1913105.3 | I114: =I102-I109 -> -2743757.1 | J114: =J102-J109 -> -3307522.1 | K114: =K102-K109 -> -3445473.6 | M114: =SUM(G114:K114) -> -10940120
E115: Lake Link Operating Surplus/Deficit (Status Quo) | G115: =G103-G107 -> 58883.54 | H115: =H103-H107 -> -678994.08 | I115: =I103-I107 -> -792313.84 | J115: =J103-J107 -> -932006.4 | K115: =K103-K107 -> -1077286.7 | M115: =SUM(G115:K115) -> -3421717.4
E116: Lake Link Operating Surplus/Deficit (w/ Service Plan) | G116: =G103-G110 -> 58883.54 | H116: =H103-H110 -> -1036294.1 | I116: =I103-I110 -> -1163313.8 | J116: =J103-J110 -> -1316806.4 | K116: =K103-K110 -> -1475786.7 | M116: =SUM(G116:K116) -> -4933317.4
E117: Combined South Shore Operating Surplus/Deficit (Status Quo) | G117: =G104-G108 -> 994521.55 | H117: =H104-H108 -> -1970299.4 | I117: =I104-I108 -> -2331771 | J117: =J104-J108 -> -2990528.5 | K117: =K104-K108 -> -3229260.3 | M117: =SUM(G117:K117) -> -9527337.5
E118: Combined South Shore Operating Surplus/Deficit (w/ Service Plan) | G118: =G104-G111 -> 528621.55 | H118: =H104-H111 -> -2592099.4 | I118: =I104-I111 -> -3536071 | J118: =J104-J111 -> -4239528.5 | K118: =K104-K111 -> -4522760.3 | M118: =SUM(G118:K118) -> -14361838
E121: Note 1: Assumes 1% increase annually.
E122: Note 2: Reflects assumption that total LTF allocation and STA revenue changes annually based on RTP projected population change. Assumes no change in TRPA TDA Split.
E123: Note 3: Fares shown come from Emerald Bay Shuttle.
E124: Note 4: Assumes no annual change from FY 2026-27 budget.
E125: Note 5: Represents total revenue committed for 2026 and 2027 seasons.
E126: Note 6: Assumes funding support at existing levels beyond the end of the current written agreements.
E127: Note 7: Assumes $3 surcharge allocated to transit and no increase in max annual attendee cap.
...

Sheet T5-7 TART TNTTMA FinancialPlan
F1: FY 25-26 | G1: FY 26-27 | H1: FY 27-28 | I1: FY 28-29 | J1: FY 29-30 | K1: FY 30-31 | O1: 1.04 | P1: Inflation escalator (general) | Q1: 1 | R1: 1.03 | S1: =R1*$O$1 -> 1.0712 | T1: =S1*$O$1 -> 1.114048 | U1: =T1*$O$1 -> 1.1586099 | V1: =U1*$O$1 -> 1.2049543
A2: TART | B2: 25-26 VSH | E2: Cost per hr | G2: ='VRH Rates'!D14 -> 66.45 | H2: =G2*$O$1 -> 69.108 | I2: =H2*$O$1 -> 71.87232 | J2: =I2*$O$1 -> 74.747213 | K2: =J2*$O$1 -> 77.737101
B3: 35129 | E3: Cost per mi | G3: ='VRH Rates'!E14 -> 1.7 | H3: =G3*$O$1 -> 1.768 | I3: =H3*$O$1 -> 1.83872 | J3: =I3*1.1 -> 2.022592 | K3: =J3*1.03 -> 2.0832698
B5: 25-26 VSM
B6: 696698
A7: TART | B7: 25-26 VSH | E7: Cost per hr | G7: ='VRH Rates'!D15 -> 46.56 | H7: =G7*$O$1 -> 48.4224 | I7: =H7*$O$1 -> 50.359296 | J7: =I7*$O$1 -> 52.373668 | K7: =J7*$O$1 -> 54.468615
A8: Connect | B8: 27343 | E8: Cost per mi | G8: 0 | H8: =G8*$O$1 -> 0 | I8: =H8*$O$1 -> 0 | J8: =I8*1.1 -> 0 | K8: =J8*1.03 -> 0
B10: 25-26 VSM | E10: Base ridership growth (from 25-26 Status Quo) | G10: 1.02 | H10: =+G10*1.02 -> 1.0404 | I10: =+H10*1.02 -> 1.061208 | J10: =+I10*1.02 -> 1.0824322 | K10: =+J10*1.02 -> 1.1040808
B11: 544889 | E11: Population Change Rate | G11: 0.00025 | H11: 0.00025 | I11: 0.00025 | J11: 0.00025 | K11: 0.00025 | M11: RTP pop projections
D14: TABLE 5: North Shore Operating Costs
D16: Plan Element | F16: FY 25-26 | G16: FY 26-27 | H16: FY 27-28 | I16: FY 28-29 | J16: FY 29-30 | K16: FY 30-31
D18: Placer TART Base Case Operating Cost 1
E19: Marginal Operating Costs | G19: =($B$3*G2)+($B$6*G3) -> 3518708.7 | H19: =($B$3*H2)+($B$6*H3) -> 3659457 | I19: =($B$3*I2)+($B$6*I3) -> 3805835.3 | J19: =($B$3*J2)+($B$6*J3) -> 4034930.6 | K19: =($B$3*K2)+($B$6*K3) -> 4182236.5
E20: Fixed Costs | G20: ='VRH Rates'!F14 -> 3188061.3 | H20: =G20*$O$1 -> 3315583.8 | I20: =H20*$O$1 -> 3448207.1 | J20: =I20*$O$1 -> 3586135.4 | K20: =J20*$O$1 -> 3729580.8
E21: Total | F21: =SUM(F19:F20) -> 0 | G21: =SUM(G19:G20) -> 6706770 | H21: =SUM(H19:H20) -> 6975040.8 | I21: =SUM(I19:I20) -> 7254042.4 | J21: =SUM(J19:J20) -> 7621066.1 | K21: =SUM(K19:K20) -> 7911817.3
D23: Placer TART Connect Base Case Operating Cost
E24: Marginal Operating Costs | G24: =($B$8*G7)+($B$11*G8) -> 1273090.1 | H24: =($B$8*H7)+($B$11*H8) -> 1324013.7 | I24: =($B$8*I7)+($B$11*I8) -> 1376974.2 | J24: =($B$8*J7)+($B$11*J8) -> 1432053.2 | K24: =($B$8*K7)+($B$11*K8) -> 1489335.3
E25: Fixed Costs | G25: ='VRH Rates'!F15 -> 1724488 | H25: =G25*$O$1 -> 1793467.5 | I25: =H25*$O$1 -> 1865206.2 | J25: =I25*$O$1 -> 1939814.5 | K25: =J25*$O$1 -> 2017407
E26: Total | F26: =SUM(F24:F25) -> 0 | G26: =SUM(G24:G25) -> 2997578.1 | H26: =SUM(H24:H25) -> 3117481.2 | I26: =SUM(I24:I25) -> 3242180.5 | J26: =SUM(J24:J25) -> 3371867.7 | K26: =SUM(K24:K25) -> 3506742.4 | Q26: Implementation Plan - Do not Delete
D28: TNT/TMA Program Operating Costs2
E29: North Lake Tahoe Express | G29: ='TNTTMA $'!F22 -> 694260 | H29: =G29*$O$1 -> 722030.4 | I29: =H29*$O$1 -> 750911.62 | J29: =I29*$O$1 -> 780948.08 | K29: =J29*$O$1 -> 812186
E30: Park and Ride Shuttles | F30: ='TNTTMA $'!E43 -> 756470 | G30: ='TNTTMA $'!F43 -> 894233 | H30: =G30*$O$1 -> 930002.32 | I30: =H30*$O$1 -> 967202.41 | J30: =I30*$O$1 -> 1005890.5 | K30: =J30*$O$1 -> 1046126.1
E31: Van Pools | F31: ='TNTTMA $'!J43 -> 220818 | G31: ='TNTTMA $'!K43 -> 195800 | H31: =G31*$O$1 -> 203632 | I31: =H31*$O$1 -> 211777.28 | J31: =I31*$O$1 -> 220248.37 | K31: =J31*$O$1 -> 229058.31
E32: Program Administration | F32: ='TNTTMA $'!J22 -> 276289 | G32: ='TNTTMA $'!K22 -> 321870 | H32: =G32*$O$1 -> 334744.8 | I32: =H32*$O$1 -> 348134.59 | J32: =I32*$O$1 -> 362059.98 | K32: =J32*$O$1 -> 376542.37
E33: Regional Transit Marketing | F33: ='TNTTMA $'!P22 -> 225984 | G33: ='TNTTMA $'!Q22 -> 223823 | H33: =G33*$O$1 -> 232775.92 | I33: =H33*$O$1 -> 242086.96 | J33: =I33*$O$1 -> 251770.44 | K33: =J33*$O$1 -> 261841.25
E34: Total TNT/TMA Program Operating Costs | G34: =SUM(G29:G33) -> 2329986 | H34: =SUM(H29:H33) -> 2423185.4 | I34: =SUM(I29:I33) -> 2520112.9 | J34: =SUM(J29:J33) -> 2620917.4 | K34: =SUM(K29:K33) -> 2725754.1
D35: Service Plan Element Marginal Operating Costs | R35: FY 26-27 | S35: FY 27-28 | T35: FY 28-29 | U35: FY 29-30 | V35: FY 30-31
E36: =Q36 -> Reinstate TART Connect Service in Incline Village | G36: =IF(R36=1,ROUND('[32]T5-F15-18 TART 24-25 Perf'!$L$24*O1^2,-2),0) -> 0 | H36: =IF(S36=1,ROUND('[32]T5-F15-18 TART 24-25 Perf'!$L$24*O1^3,-2),0) -> 1044400 | I36: =IF(T36=1,ROUND('[32]T5-F15-18 TART 24-25 Perf'!$L$24*O1^4,-2),0) -> 1086200 | J36: =IF(U36=1,ROUND('[32]T5-F15-18 TART 24-25 Perf'!$L$24*O1^5,-2),0) -> 1129600 | K36: =IF(V36=1,ROUND('[32]T5-F15-18 TART 24-25 Perf'!$L$24*S1^6,-2),0) -> 1402800 | Q36: Reinstate TART Connect Service in Incline Village | R36: 0 | S36: 1 | T36: 1 | U36: 1 | V36: 1
E37: =Q37 -> Increase Van Pools between Reno and Truckee/North Lake Tahoe | G37: =IF(R37=1,ROUND('TNTTMA $'!$J$46*O1,-2),0) -> 25000 | H37: =IF(S37=1,ROUND('TNTTMA $'!$J$46*O1^2,-2),0) -> 26000 | I37: =IF(T37=1,ROUND('TNTTMA $'!$J$46*O1^3,-2),0) -> 0 | J37: =IF(U37=1,ROUND('TNTTMA $'!$J$46*O1^4,-2),0) -> 0 | K37: =IF(V37=1,ROUND('TNTTMA $'!$J$46*O1^5,-2),0) -> 0 | Q37: Increase Van Pools between Reno and Truckee/North Lake Tahoe | R37: 1 | S37: 1 | T37: 0 | U37: 0 | V37: 0
E39: Total Service Plan Costs | G39: =SUM(G36:G37) -> 25000 | H39: =SUM(H36:H37) -> 1070400 | I39: =SUM(I36:I37) -> 1086200 | J39: =SUM(J36:J37) -> 1129600 | K39: =SUM(K36:K37) -> 1402800
D41: Total North Shore Transit Operating Cost | F41: =F21+F39 -> 0 | G41: =G21+G26+G34+G39 -> 12059334 | H41: =H21+H26+H34+H39 -> 13586107 | I41: =I21+I26+I34+I39 -> 14102536 | J41: =J21+J26+J34+J39 -> 14743451 | K41: =K21+K26+K34+K39 -> 15547114
D43: Note 1: Base Case costs based upon FY 2024-25 actual expenses plus 4% inflation and FY 2025-26 service levels. Assumes 4% annual inflation rate moving forward.
D44: Note 2: Excludes Town of Truckee event shuttles.
D45: Source: LSC Transportation Consultants, Inc.
B51: Questions
D54: TABLE A2: North Shore Financial Plan - Operating | M54: 5-Year Plan Revenues/ Costs
F56: FY 25-26 | G56: FY 26-27 | H56: FY 27-28 | I56: FY 28-29 | J56: FY 29-30 | K56: FY 30-31 | O56: Notes
D58: OPERATING REVENUE - RECCURING APPORTIONED FUNDS | F58: Budget | G58: Budget | T58: 74K for 5311
E59: FTA 5307 (Lake Tahoe UZA) 1 | F59: 2500000 | G59: 2660000 | H59: =ROUND(G59*1.01,-2) -> 2686600 | I59: =ROUND(H59*1.01,-2) -> 2713500 | J59: =ROUND(I59*1.01,-2) -> 2740600 | K59: =ROUND(J59*1.01,-2) -> 2768000 | M59: =SUM(G59:K59) -> 13568700 | O59: 1% increase yearly
E60: FTA 5311 (Caltrans) 1 | F60: 450000 | G60: 290000 | H60: =ROUND(G60*1.01,-2) -> 292900 | I60: =ROUND(H60*1.01,-2) -> 295800 | J60: =ROUND(I60*1.01,-2) -> 298800 | K60: =ROUND(J60*1.01,-2) -> 301800 | M60: =SUM(G60:K60) -> 1479300
E61: Local Transportation Fund (LTF) 2 | F61: 2246565 | G61: =ROUND(913053+1675000,-2) -> 2588100 | H61: =ROUND(G61*(1+H$11),-2) -> 2588700 | I61: =ROUND(H61*(1+I$11),-2) -> 2589300 | J61: =ROUND(I61*(1+J$11),-2) -> 2589900 | K61: =ROUND(J61*(1+K$11),-2) -> 2590500 | M61: =SUM(G61:K61) -> 12946500 | O61: Annual change based on projected County population change
E62: State Transit Assistance (STA) 2 | F62: 1110118 | G62: =ROUND(819627,-2) -> 819600 | H62: =ROUND(G62*(1+H$11),-2) -> 819800 | I62: =ROUND(H62*(1+I$11),-2) -> 820000 | J62: =ROUND(I62*(1+J$11),-2) -> 820200 | K62: =ROUND(J62*(1+K$11),-2) -> 820400 | M62: =SUM(G62:K62) -> 4100000 | O62: Annual change based on projected County population change
E63: State of Good Repair (SGR) 2 | F63: 102929 | G63: =ROUND(100084,-2) -> 100100 | H63: =ROUND(G63*(1+H$11),-2) -> 100100 | I63: =ROUND(H63*(1+I$11),-2) -> 100100 | J63: =ROUND(I63*(1+J$11),-2) -> 100100 | K63: =ROUND(J63*(1+K$11),-2) -> 100100 | M63: =SUM(G63:K63) -> 500500 | O63: Annual change based on projected County population change
E64: Total Reccuring Apportioned Funds | F64: =SUM(F59:F63) -> 6409612 | G64: =SUM(G59:G63) -> 6457800 | H64: =SUM(H59:H63) -> 6488100 | I64: =SUM(I59:I63) -> 6518700 | J64: =SUM(J59:J63) -> 6549600 | K64: =SUM(K59:K63) -> 6580800 | M64: =SUM(G64:K64) -> 32595000
D66: OPERATING REVENUE - VARIABLE FUNDS | T66: 74K for 5311
E67: Placer County
E68: Placer County (Transient Occupancy Tax) | F68: 5463510 | G68: =2900000+150000+1874954+277500+144946 -> 5347400 | H68: =ROUND(G68*$O$1,-1) -> 5561300 | I68: =ROUND(H68*$O$1,-1) -> 5783750 | J68: =ROUND(I68*$O$1,-1) -> 6015100 | K68: =ROUND(J68*$O$1,-1) -> 6255700 | M68: =SUM(G68:K68) -> 28963250 | O68: 4% annually with inflation
E69: Washoe RTC | F69: 288746 | G69: 296055 | H69: =ROUND(G69*1.02,-2) -> 302000 | I69: =ROUND(H69*1.02,-2) -> 308000 | J69: =ROUND(I69*1.02,-2) -> 314200 | K69: =ROUND(J69*1.02,-2) -> 320500 | M69: =SUM(G69:K69) -> 1540755 | O69: 2% annual increase to match the average recently
E70: Town of Truckee | F70: 256402 | G70: 230478 | H70: =ROUND(G70,-2) -> 230500 | I70: =H70 -> 230500 | J70: =I70 -> 230500 | K70: =J70 -> 230500 | M70: =SUM(G70:K70) -> 1152478 | O70: No change
E71: North Shore Resort Partners | F71: 60000 | G71: 47900 | H71: =G71 -> 47900 | I71: =H71 -> 47900 | J71: =I71 -> 47900 | K71: =J71 -> 47900 | M71: =SUM(G71:K71) -> 239500 | O71: No change
E72: North Shore Local Partners (Free Fares) | F72: 148500 | G72: 139000 | H72: =G72 -> 139000 | I72: =H72 -> 139000 | J72: =I72 -> 139000 | K72: =J72 -> 139000 | M72: =SUM(G72:K72) -> 695000 | O72: No change
E73: Martis Zones of Benefit | F73: 50000 | G73: 0 | H73: 0 | I73: 0 | J73: 0 | K73: 0 | M73: =SUM(G73:K73) -> 0
E75: TNT/TMA
E76: Placer County (Transient Occupancy Tax) | F76: =SUM('TNTTMA $'!F9,'TNTTMA $'!E29,'TNTTMA $'!J29,'TNTTMA $'!P9) -> 686713 | G76: ='TNTTMA $'!V9 -> 1290060 | H76: =ROUND(G76*$O$1,-2) -> 1341700 | I76: =ROUND(H76*$O$1,-2) -> 1395400 | J76: =ROUND(I76*$O$1,-2) -> 1451200 | K76: =ROUND(J76*$O$1,-2) -> 1509200 | M76: =SUM(G76:K76) -> 6987560 | O76: 4% growth
E77: North Tahoe Community Alliance | F77: =SUM('TNTTMA $'!E30) -> 487173 | G77: ='TNTTMA $'!V10 -> 0 | H77: =G77 -> 0 | I77: =H77 -> 0 | J77: =I77 -> 0 | K77: =J77 -> 0 | M77: =SUM(G77:K77) -> 0 | O77: Flat growth
E78: Washoe County | F78: =SUM('TNTTMA $'!F11) -> 12500 | G78: ='TNTTMA $'!V11 -> 12500 | H78: =G78 -> 12500 | I78: =H78 -> 12500 | J78: =I78 -> 12500 | K78: =J78 -> 12500 | M78: =SUM(G78:K78) -> 62500 | O78: Flat growth
E79: Nevada County | G79: ='TNTTMA $'!V12 -> 16339 | H79: =ROUND(G79,-2) -> 16300 | I79: =ROUND(H79,-2) -> 16300 | J79: =ROUND(I79,-2) -> 16300 | K79: =ROUND(J79,-2) -> 16300 | M79: =SUM(G79:K79) -> 81539
E80: Town of Truckee | F80: =SUM('TNTTMA $'!F13,'TNTTMA $'!P10) -> 36764 | G80: ='TNTTMA $'!V13 -> 37615 | H80: =ROUND(G80,-2) -> 37600 | I80: =H80 -> 37600 | J80: =I80 -> 37600 | K80: =J80 -> 37600 | M80: =SUM(G80:K80) -> 188015
E81: Other Truckee | G81: ='TNTTMA $'!V14 -> 2927 | H81: =ROUND(G81,-2) -> 2900 | I81: =ROUND(H81,-2) -> 2900 | J81: =ROUND(I81,-2) -> 2900 | K81: =ROUND(J81,-2) -> 2900 | M81: =SUM(G81:K81) -> 14527
E82: Reno-Tahoe Airport Authority | F82: ='TNTTMA $'!F12 -> 12500 | G82: ='TNTTMA $'!V15 -> 12500 | H82: =G82 -> 12500 | I82: =H82 -> 12500 | J82: =I82 -> 12500 | K82: =J82 -> 12500 | M82: =SUM(G82:K82) -> 62500
E83: Northstar Resort | F83: ='TNTTMA $'!E32 -> 21413 | G83: ='TNTTMA $'!V16 -> 3862 | H83: =ROUND(G83,-2) -> 3900 | I83: =H83 -> 3900 | J83: =I83 -> 3900 | K83: =J83 -> 3900 | M83: =SUM(G83:K83) -> 19462
E84: Palisades Tahoe | F84: ='TNTTMA $'!E33 -> 119304 | G84: ='TNTTMA $'!V17 -> 124076 | H84: =ROUND(G84,-2) -> 124100 | I84: =H84 -> 124100 | J84: =I84 -> 124100 | K84: =J84 -> 124100 | M84: =SUM(G84:K84) -> 620476
E85: Travel North Tahoe Nevada | F85: =SUM('TNTTMA $'!F10,'TNTTMA $'!P12) -> 36421 | G85: ='TNTTMA $'!V18 -> 26421 | H85: =ROUND(G85,-2) -> 26400 | I85: =H85 -> 26400 | J85: =I85 -> 26400 | K85: =J85 -> 26400 | M85: =SUM(G85:K85) -> 132021
E86: RCMF | F86: ='TNTTMA $'!P11 -> 20000 | G86: ='TNTTMA $'!V19 -> 20000 | H86: =G86 -> 20000 | I86: =H86 -> 20000 | J86: =I86 -> 20000 | K86: =J86 -> 20000 | M86: =SUM(G86:K86) -> 100000
E87: Fare Revenue (NLTE) | F87: ='TNTTMA $'!E15 -> 445263 | G87: ='TNTTMA $'!V20 -> 377656 | H87: =ROUND(G87,-2) -> 377700 | I87: =H87 -> 377700 | J87: =I87 -> 377700 | K87: =J87 -> 377700 | M87: =SUM(G87:K87) -> 1888456
E88: Membership | F88: ='TNTTMA $'!J9 -> 120694 | G88: ='TNTTMA $'!V21 -> 125267 | H88: =ROUND(G88,-2) -> 125300 | I88: =H88 -> 125300 | J88: =I88 -> 125300 | K88: =J88 -> 125300 | M88: =SUM(G88:K88) -> 626467
E89: Management Revenues | F89: =SUM('TNTTMA $'!J11,'TNTTMA $'!J10,'TNTTMA $'!J12) -> 183025 | G89: ='TNTTMA $'!V22 -> 200092 | H89: =ROUND(G89,-2) -> 200100 | I89: =H89 -> 200100 | J89: =I89 -> 200100 | K89: =J89 -> 200100 | M89: =SUM(G89:K89) -> 1000492
E90: NLTE Reserve | G90: 240000 | H90: -- | I90: -- | J90: -- | K90: --
E92: Placer TART Total Variable Funds | F92: =SUM(F69:F73) -> 803648 | G92: =SUM(G68:G73) -> 6060833 | H92: =SUM(H68:H73) -> 6280700 | I92: =SUM(I68:I73) -> 6509150 | J92: =SUM(J68:J73) -> 6746700 | K92: =SUM(K68:K73) -> 6993600 | M92: =SUM(G92:K92) -> 32590983
E93: TNT/TMA Total Variable Funds | F93: =SUM(F76:F89) -> 2181770 | G93: =SUM(G76:G90) -> 2489315 | H93: =SUM(H76:H89) -> 2301000 | I93: =SUM(I76:I89) -> 2354700 | J93: =SUM(J76:J89) -> 2410500 | K93: =SUM(K76:K89) -> 2468500 | M93: =SUM(G93:K93) -> 12024015
D95: SUMMARY OF TOTAL SOUTH SHORE TRANSIT OPERATING REVENUE
E96: Placer TART Operating Revenue | G96: =G64+G92 -> 12518633 | H96: =H64+H92 -> 12768800 | I96: =I64+I92 -> 13027850 | J96: =J64+J92 -> 13296300 | K96: =K64+K92 -> 13574400 | M96: =SUM(G96:K96) -> 65185983
E97: TNT/TMA Operating Revenue | G97: =G93 -> 2489315 | H97: =H93 -> 2301000 | I97: =I93 -> 2354700 | J97: =J93 -> 2410500 | K97: =K93 -> 2468500 | M97: =SUM(G97:K97) -> 12024015
E98: Total North Shore Operating Revenue | G98: =SUM(G96:G97) -> 15007948 | H98: =SUM(H96:H97) -> 15069800 | I98: =SUM(I96:I97) -> 15382550 | J98: =SUM(J96:J97) -> 15706800 | K98: =SUM(K96:K97) -> 16042900 | M98: =SUM(G98:K98) -> 77209998
E100: Placer TART Operating Costs (Status Quo) | G100: =G21+G26 -> 9704348.1 | H100: =H21+H26 -> 10092522 | I100: =I21+I26 -> 10496223 | J100: =J21+J26 -> 10992934 | K100: =K21+K26 -> 11418560 | M100: =SUM(G100:K100) -> 52704586
E101: TNT/TMA Operating Costs (Status Quo) | G101: =G34 -> 2329986 | H101: =H34 -> 2423185.4 | I101: =I34 -> 2520112.9 | J101: =J34 -> 2620917.4 | K101: =K34 -> 2725754.1 | M101: =SUM(G101:K101) -> 12619956
E102: TOTAL North Shore Transit Operating Costs (Status Quo) | G102: =SUM(G100:G101) -> 12034334 | H102: =SUM(H100:H101) -> 12515707 | I102: =SUM(I100:I101) -> 13016336 | J102: =SUM(J100:J101) -> 13613851 | K102: =SUM(K100:K101) -> 14144314 | M102: =SUM(G102:K102) -> 65324542
E103: Placer TART Operating Costs (w/ Service Plan) | G103: =G21+G26+G36 -> 9704348.1 | H103: =H21+H26+H36 -> 11136922 | I103: =I21+I26+I36 -> 11582423 | J103: =J21+J26+J36 -> 12122534 | K103: =K21+K26+K36 -> 12821360 | M103: =SUM(G103:K103) -> 57367586
E104: TNT/TMA Operating Costs (w/ Service Plan) | G104: =G34+G37 -> 2354986 | H104: =H34+H37 -> 2449185.4 | I104: =I34+I37 -> 2520112.9 | J104: =J34+J37 -> 2620917.4 | K104: =K34+K37 -> 2725754.1 | M104: =SUM(G104:K104) -> 12670956
E105: TOTAL North Shore Transit Operating Costs (w/ Service Plan) | G105: =SUM(G103:G104) -> 12059334 | H105: =SUM(H103:H104) -> 13586107 | I105: =SUM(I103:I104) -> 14102536 | J105: =SUM(J103:J104) -> 14743451 | K105: =SUM(K103:K104) -> 15547114 | M105: =SUM(G105:K105) -> 70038542
E107: Placer TART Operating Surplus/Deficit (Status Quo) | G107: =G96-G100 -> 2814284.9 | H107: =H96-H100 -> 2676278 | I107: =I96-I100 -> 2531627.1 | J107: =J96-J100 -> 2303366.3 | K107: =K96-K100 -> 2155840.3 | M107: =SUM(G107:K107) -> 12481397
E108: Placer TART Operating Surplus/Deficit (w/ Service Plan) | G108: =G96-G103 -> 2814284.9 | H108: =H96-H103 -> 1631878 | I108: =I96-I103 -> 1445427.1 | J108: =J96-J103 -> 1173766.3 | K108: =K96-K103 -> 753040.28 | M108: =SUM(G108:K108) -> 7818396.7
E109: TNT/TMA Operating Surplus/Deficit (Status Quo) | G109: =G97-G101 -> 159329 | H109: =H97-H101 -> -122185.44 | I109: =I97-I101 -> -165412.86 | J109: =J97-J101 -> -210417.37 | K109: =K97-K101 -> -257254.07 | M109: =SUM(G109:K109) -> -595940.74
E110: TNT/TMA Operating Surplus/Deficit (w/ Service Plan) | G110: =G97-G104 -> 134329 | H110: =H97-H104 -> -148185.44 | I110: =I97-I104 -> -165412.86 | J110: =J97-J104 -> -210417.37 | K110: =K97-K104 -> -257254.07 | M110: =SUM(G110:K110) -> -646940.74
E111: Combined North Shore Operating Surplus/Deficit (Status Quo) | G111: =G98-G102 -> 2973613.9 | H111: =H98-H102 -> 2554092.6 | I111: =I98-I102 -> 2366214.3 | J111: =J98-J102 -> 2092948.9 | K111: =K98-K102 -> 1898586.2 | M111: =SUM(G111:K111) -> 11885456
E112: Combined North Shore Operating Surplus/Deficit (w/ Service Plan) | G112: =G98-G105 -> 2948613.9 | H112: =H98-H105 -> 1483692.6 | I112: =I98-I105 -> 1280014.3 | J112: =J98-J105 -> 963348.9 | K112: =K98-K105 -> 495786.22 | M112: =SUM(G112:K112) -> 7171455.9
E116: Note 1: Assumes 1% increase annually.
E117: Note 2: Reflects assumption that total LTF allocation and STA revenue changes annually based on RTP projected population change. Assumes no change in TRPA TDA Split.
E118: Note 3: Fares shown come from Emerald Bay Shuttle.
E119: Note 4: Assumes no annual change from FY 2026-27 budget.
E120: Note 5: Represents total revenue committed for 2026 and 2027 seasons.
E126: TABLE 6: Placer TART Financial Forecast
F127: FY 25-26 (2026) | G127: FY 26-27(2027) | H127: FY 27-28 (2028) | I127: FY 28-29 (2029) | J127: FY 29-30 (2030) | K127: FY 30-31 (2031) | M127: 2026 %s
E129: Estimated Total Operating Cost (Status Quo) | G129: =G100 -> 9704348.1 | H129: =H100 -> 10092522 | I129: =I100 -> 10496223 | J129: =J100 -> 10992934 | K129: =K100 -> 11418560
E130: Estimated Total Operating Cost (w/ Service Plan) | G130: =G103 -> 9704348.1 | H130: =H103 -> 11136922 | I130: =I103 -> 11582423 | J130: =J103 -> 12122534 | K130: =K103 -> 12821360
E132: Total Revenue | G132: =G96 -> 12518633 | H132: =H96 -> 12768800 | I132: =I96 -> 13027850 | J132: =J96 -> 13296300 | K132: =K96 -> 13574400
E133: Core Reoccuring Apportioned Funds (FTA, TDA) | G133: =G64 -> 6457800 | H133: =H64 -> 6488100 | I133: =I64 -> 6518700 | J133: =J64 -> 6549600 | K133: =K64 -> 6580800 | M133: =G133/G$132 -> 0.51585505
E134: Other State/Federal Funds (LCTOP, CRP) | G134: 0 | H134: 0 | I134: 0 | J134: 0 | K134: 0 | M134: =G134/G$155 -> 0
E135: Public Local Funds (Includes TOT) | G135: =SUM(G92) -> 6060833 | H135: =SUM(H92) -> 6280700 | I135: =SUM(I92) -> 6509150 | J135: =SUM(J92) -> 6746700 | K135: =SUM(K92) -> 6993600 | M135: =G135/G$132 -> 0.48414495
E136: SB 125 | G136: 0 | H136: 0 | I136: 0 | J136: 0 | K136: 0 | M136: =G136/G$132 -> 0
...

Sheet t 8-10 Capital Plan
P1: 1.03 | Q1: Inflation
B5: EDIT THIS Table | V5: From TART Transit replacement plan (11/2024) | AA5: 24/25
D6: Table XX: Capital Plan | N6: 5-Year Costs | V6: Gas cutaway | AA6: 151892.04
H8: FY 26-27 | I8: FY 27-28 | J8: FY 28-29 | K8: FY 29-30 | L8: FY 30-31 | P8: Per Unit Costs / Notes (FY 26/27 $) | V8: Gas van (from 24/25 TART budget) | AA8: 81000
D9: Service Plan Capital Costs
E10: Fleet Expansion | H10: =SUM(H11:H16) -> 2343100 | I10: =SUM(I11:I16) -> 0 | J10: =SUM(J11:J16) -> 0 | K10: =SUM(K11:K16) -> 0 | L10: =SUM(L11:L16) -> 0 | N10: =SUM(H10:L10) -> 2343100 | P10: 1168561 | Q10: TTD 26/27 One Gillig Hybrid | V10: Fleet Expansion
E11: Eliminate 19X and Replace with US 50 Service (4 Round Trips) | H11: 0 | I11: 0 | J11: 0 | K11: 0 | L11: 0 | P11: =AA6*'T2-4 A1 TTD LL Costs'!Z129^2 -> 0 | Q11: Est. Gas Cutaway (Based on TART 2024 Purchase) | V11: 0 | W11: Eliminate 19X and Replace with US 50 Service (4 Round Trips)
E12: Seasonal Expansion of Route 28 to Spooner Mobility Hub | H12: =ROUND(V12*P10,-2) -> 2337100 | I12: 0 | J12: 0 | K12: 0 | L12: 0 | P12: =AA8*'T2-4 A1 TTD LL Costs'!Z129^2 -> 0 | Q12: Est. Gas Van (Based on TART 2024 Purchase) | V12: 2 | W12: Seasonal Expansion of Route 28 to Spooner Mobility Hub
E13: Continue to Operate the Emerald Bay Shuttle (Route 30) Beyond the Pilot Period | H13: 0 | I13: =ROUND(V13*P11*P1,-2) -> 0 | J13: 0 | K13: 0 | L13: 0 | V13: 6 | W13: Continue to Operate the Emerald Bay Shuttle (Route 30) Beyond the Pilot Period
E14: Pilot Co-mingled Paratransit/Microtransit Service to Meyers | H14: 6000 | I14: =ROUND(V14*P12,-2) -> 0 | J14: 0 | K14: 0 | L14: 0 | V14: 0 | W14: Pilot Co-mingled Paratransit/Microtransit Service to Meyers
E15: Discontinue Route 50 Deviation to LTCC | H15: 0 | I15: 0 | J15: 0 | K15: 0 | L15: 0 | V15: 0 | W15: Discontinue Route 50 Deviation to LTCC
E16: Reinstate TART Connect Service in Incline Village, NV | H16: 0 | I16: 0 | J16: 0 | K16: 0 | L16: 0 | V16: 0 | W16: Reinstate TART Connect Service in Incline Village, NV
E17: Increase Van Pools between Reno and Truckee/North Lake Tahoe | H17: 0 | I17: 0 | J17: 0 | K17: 0 | L17: 0
E18: Staffing | H18: =SUM(H19:H24) -> 0 | I18: =SUM(I19:I24) -> 64900 | J18: =SUM(J19:J24) -> 28600 | K18: =SUM(K19:K24) -> 0 | L18: =SUM(L19:L24) -> 0 | N18: =SUM(H18:L18) -> 93500 | P18: 9000 | Q18: Est. cost to hire, onboard, train new driver | V18: Staffing
E19: Eliminate 19X and Replace with US 50 Service (4 Round Trips) | H19: 0 | I19: 0 | J19: 0 | K19: 0 | L19: 0 | V19: 0 | W19: Eliminate 19X and Replace with US 50 Service (4 Round Trips)
E20: Seasonal Expansion of Route 28 to Spooner Mobility Hub | H20: 0 | I20: 0 | J20: =ROUND(V20*P18*(P1^2),-2) -> 28600 | K20: 0 | L20: 0 | V20: 3 | W20: Seasonal Expansion of Route 28 to Spooner Mobility Hub
E21: Continue to Operate the Emerald Bay Shuttle (Route 30) Beyond the Pilot Period | H21: 0 | I21: =ROUND(V21*P18*P1,-2) -> 64900 | J21: 0 | K21: 0 | L21: 0 | V21: 7 | W21: Continue to Operate the Emerald Bay Shuttle (Route 30) Beyond the Pilot Period
E22: Pilot Co-mingled Paratransit/Microtransit Service to Meyers | H22: 0 | I22: 0 | J22: 0 | K22: 0 | L22: 0 | V22: 1 | W22: Pilot Co-mingled Paratransit/Microtransit Service to Meyers
E23: Discontinue Route 50 Deviation to LTCC | H23: 0 | I23: 0 | J23: 0 | K23: 0 | L23: 0 | V23: 0 | W23: Discontinue Route 50 Deviation to LTCC
E24: Reinstate TART Connect Service in Incline Village, NV | H24: 0 | I24: 0 | J24: 0 | K24: 0 | L24: 0 | V24: 0 | W24: Reinstate TART Connect Service in Incline Village, NV
E25: Increase Van Pools between Reno and Truckee/North Lake Tahoe | H25: 0 | I25: 0 | J25: 0 | K25: 0 | L25: 0
E26: New Bus Stops | H26: =SUM(H27:H32) -> 0 | I26: =SUM(I27:I32) -> 370800 | J26: =SUM(J27:J32) -> 31800 | K26: =SUM(K27:K32) -> 0 | L26: =SUM(L27:L32) -> 0 | N26: =SUM(H26:L26) -> 402600 | P26: 15000 | Q26: Est. Cost of New Bus Stop with Sign | V26: New Bus Stops
E27: Eliminate 19X and Replace with US 50 Service (4 Round Trips) | H27: 0 | I27: =ROUND(V27*P26*P1,-2) -> 185400 | J27: 0 | K27: 0 | L27: 0 | P27: 100000 | Q27: Est. Total Cost of Bus Shelter in Tahoe | V27: 12 | W27: Eliminate 19X and Replace with US 50 Service (4 Round Trips)
E28: Seasonal Expansion of Route 28 to Spooner Mobility Hub | H28: 0 | I28: 0 | J28: =ROUND(V28*P26*(P1^2),-2) -> 31800 | K28: 0 | L28: 0 | V28: 2 | W28: Seasonal Expansion of Route 28 to Spooner Mobility Hub
E29: Continue to Operate the Emerald Bay Shuttle (Route 30) Beyond the Pilot Period | H29: 0 | I29: =V29*P26*P1 -> 185400 | J29: 0 | K29: 0 | L29: 0 | V29: 12 | W29: Continue to Operate the Emerald Bay Shuttle (Route 30) Beyond the Pilot Period
E30: Pilot Co-mingled Paratransit/Microtransit Service to Meyers | H30: =V30*P27 -> 0 | I30: 0 | J30: 0 | K30: 0 | L30: 0 | V30: 0 | W30: Pilot Co-mingled Paratransit/Microtransit Service to Meyers
E31: Discontinue Route 50 Deviation to LTCC | H31: 0 | I31: 0 | J31: 0 | K31: 0 | L31: 0 | V31: 0 | W31: Discontinue Route 50 Deviation to LTCC
E32: Reinstate TART Connect Service in Incline Village, NV | H32: 0 | I32: 0 | J32: 0 | K32: 0 | L32: 0 | V32: 0 | W32: Reinstate TART Connect Service in Incline Village, NV
E33: Increase Van Pools between Reno and Truckee/North Lake Tahoe | H33: 0 | I33: 0 | J33: 0 | K33: 0 | L33: 0
E34: Bus Pull outs and Pedestrian Crossings | H34: =SUM(H35:H40) -> 0 | I34: =SUM(I35:I40) -> 3696500 | J34: =SUM(J35:J40) -> 0 | K34: =SUM(K35:K40) -> 0 | L34: =SUM(L35:L40) -> 0 | N34: =SUM(H34:L34) -> 3696500 | P34: =ROUNDUP(T35*1.04^8,-3) -> 405000 | Q34: Est. Inclusive Cost of Bus Pull Out | T34: 2019 Lake Transit Bus Pull out est. | V34: Bus Pull outs and Pedestrian Crossings
E35: Eliminate 19X and Replace with US 50 Service (4 Round Trips) | H35: 0 | I35: 0 | J35: 0 | K35: 0 | L35: 0 | P35: 25000 | Q35: Est. Cost of RRFB | T35: 295350 | V35: 0 | W35: Eliminate 19X and Replace with US 50 Service (4 Round Trips)
E36: Seasonal Expansion of Route 28 to Spooner Mobility Hub | H36: 0 | I36: =ROUND(V36*P34,-2) -> 810000 | J36: 0 | K36: 0 | L36: 0 | V36: 2 | W36: Seasonal Expansion of Route 28 to Spooner Mobility Hub
E37: Continue to Operate the Emerald Bay Shuttle (Route 30) Beyond the Pilot Period | H37: 0 | I37: =ROUND((P34*SUM(AE38:AE59))+(P35*SUM(AF38:AF59))*1.03,-2) -> 2886500 | J37: 0 | K37: 0 | L37: 0 | W37: Continue to Operate the Emerald Bay Shuttle (Route 30) Beyond the Pilot Period | AD37: ---->>>>>> | AE37: Pull Out | AF37: RRFB
E38: Pilot Co-mingled Paratransit/Microtransit Service to Meyers | H38: =V38*P35 -> 0 | I38: 0 | J38: 0 | K38: 0 | L38: 0 | V38: 0 | W38: Pilot Co-mingled Paratransit/Microtransit Service to Meyers
E39: Discontinue Route 50 Deviation to LTCC | H39: 0 | I39: 0 | J39: 0 | K39: 0 | L39: 0 | V39: 0 | W39: Discontinue Route 50 Deviation to LTCC
E40: Reinstate TART Connect Service in Incline Village, NV | H40: 0 | I40: 0 | J40: 0 | K40: 0 | L40: 0 | V40: 0 | W40: Reinstate TART Connect Service in Incline Village, NV | AE40: 2 | AF40: 1 | AG40: Bayview
E41: Increase Van Pools between Reno and Truckee/North Lake Tahoe | H41: 0 | I41: 0 | J41: 0 | K41: 0 | L41: 0
E42: TTD Shop Street Facility Priority Improvements | H42: =SUM(H43:H45) -> 27470 | I42: =SUM(I43:I45) -> 42454 | J42: =SUM(J43:J45) -> 6494 | K42: =SUM(K43:K45) -> 45377 | L42: =SUM(L43:L45) -> 95064 | N42: =SUM(H42:L42) -> 216859 | P42: Costs directly sourced from 2023 Facility Condition Assessment Reports.
E43: Transit Repair Shop | H43: 19614 | I43: 9969 | J43: 1985 | K43: 0 | L43: 65349
E44: Tire Shop / Admin Building | H44: 1358 | I44: 23235 | J44: 1985 | K44: 13183 | L44: 20845
E45: Wash Bay | H45: 6498 | I45: 9250 | J45: 2524 | K45: 32194 | L45: 8870 | V45: Unit Numbers
D46: TOTAL CAPITAL COSTS ASSOCIATED WITH SERVICE PLAN | H46: =SUM(H42,H10,H18,H26,H34) -> 2370570 | I46: =SUM(I42,I10,I18,I26,I34) -> 4174654 | J46: =SUM(J42,J10,J18,J26,J34) -> 66894 | K46: =SUM(K42,K10,K18,K26,K34) -> 45377 | L46: =SUM(L42,L10,L18,L26,L34) -> 95064 | N46: =SUM(H46:L46) -> 6752559 | AE46: 1 | AG46: Eagle Falls
D47: Governance Recommendation Capital Costs
E48: Co-Branding Transit Services Under TART Brand | H48: =SUM(H49:H51) -> 5000 | I48: =SUM(I49:I51) -> 5000 | J48: =SUM(J49:J51) -> 448300 | K48: =SUM(K49:K51) -> 0 | L48: =SUM(L49:L51) -> 0 | N48: =SUM(H48:L48) -> 458300 | P48: Cost sourced from Appendix D of Governance Memo
E49: Vehicles | H49: 0 | I49: 0 | J49: =ROUND((P49*V49*1.03^2)+(P53*V53*1.03^2), -2) -> 415900 | K49: 0 | L49: 0 | P49: 13000 | Q49: Vehicle wrap | V49: 26 | X49: Number of TTD buses in fleet
E50: Bus Stop Signage | H50: 0 | I50: 0 | J50: =ROUND(P50*V50*1.03^2, -2) -> 27400 | K50: 0 | L50: 0 | P50: 200 | Q50: New bus stop panel | V50: 129 | X50: TTD bus stop count
E51: Other Initial Costs | H51: 5000 | I51: 5000 | J51: 5000 | K51: 0 | L51: 0
E52: Transition of Lake Link Contract to TTD | H52: =SUM(H53) -> 0 | I52: =SUM(I53) -> 57300 | J52: =SUM(J53) -> 0 | K52: =SUM(K53) -> 0 | L52: =SUM(L53) -> 0 | N52: =SUM(H52:L52) -> 57300
E53: Vehicles | H53: 0 | I53: =ROUND(P53*V53*1.03^2, -2) -> 57300 | J53: 0 | K53: 0 | L53: 0 | P53: 4500 | Q53: Vehicle wrap (lower end peer) | V53: 12 | X53: Number of LL fleet
E54: Basin Wide Trip Planning Website | H54: =SUM(H59:H61) -> 0 | I54: =P54 -> 20000 | J54: 0 | K54: 0 | L54: 0 | N54: =SUM(H54:L54) -> 20000 | P54: 20000 | Q54: Annual peer comparison fee
E55: Creation of Transit Network Manager Position | H55: =SUM(H60:H62) -> 0 | I55: =P55 -> 9000 | J55: =SUM(J60:J62) -> 0 | K55: =SUM(K60:K62) -> 0 | L55: =SUM(L60:L62) -> 0 | N55: =SUM(H55:L55) -> 9000 | P55: =P18 -> 9000 | Q55: Hiring, onboarding, training new hire
D56: TOTAL CAPITAL COSTS ASSOCIATED WITH GOVERNANCE RECOMMENDATIONS | H56: =SUM(H48,H52,H54,H55) -> 5000 | I56: =SUM(I48,I52,I54,I55) -> 91300 | J56: =SUM(J48,J52,J54,J55) -> 448300 | K56: =SUM(K48,K52,K54,K55) -> 0 | L56: =SUM(L48,L52,L54,L55) -> 0 | N56: =SUM(H56:L56) -> 544600 | AG56: Eagle Falls
AE57: 2 | AF57: 1 | AG57: DL Bliss
AE58: 2 | AG58: Meeks
AG59: Sugar Pine
B63: LINKED SUMMARY TABLE | V63: From TART Transit replacement plan (11/2024) | AA63: 24/25
D64: TABLE 8: Capital Costs Associated with Service Plan - By Expenditure Type | N64: 5-Year Costs | V64: Gas cutaway | AA64: 151892.04
E66: Expenditure Type | H66: FY 26-27 | I66: FY 27-28 | J66: FY 28-29 | K66: FY 29-30 | L66: FY 30-31 | P66: Notes | V66: Gas van (from 24/25 TART budget) | AA66: 81000
E68: =E42 -> TTD Shop Street Facility Priority Improvements | H68: =H42 -> 27470 | I68: =I42 -> 42454 | J68: =J42 -> 6494 | K68: =K42 -> 45377 | L68: =L42 -> 95064 | N68: =SUM(H68:L68) -> 216859
E69: =E10 -> Fleet Expansion | H69: =H10 -> 2343100 | I69: =I10 -> 0 | J69: =J10 -> 0 | K69: =K10 -> 0 | L69: =L10 -> 0 | N69: =SUM(H69:L69) -> 2343100
E70: =E18 -> Staffing | H70: =H18 -> 0 | I70: =I18 -> 64900 | J70: =J18 -> 28600 | K70: =K18 -> 0 | L70: =L18 -> 0 | N70: =SUM(H70:L70) -> 93500
E71: =E26 -> New Bus Stops | H71: =H26 -> 0 | I71: =I26 -> 370800 | J71: =J26 -> 31800 | K71: =K26 -> 0 | L71: =L26 -> 0 | N71: =SUM(H71:L71) -> 402600
E72: =E34 -> Bus Pull outs and Pedestrian Crossings | H72: =H34 -> 0 | I72: =I34 -> 3696500 | J72: =J34 -> 0 | K72: =K34 -> 0 | L72: =L34 -> 0 | N72: =SUM(H72:L72) -> 3696500
E73: Total Cost | H73: =SUM(H68:H72) -> 2370570 | I73: =SUM(I68:I72) -> 4174654 | J73: =SUM(J68:J72) -> 66894 | K73: =SUM(K68:K72) -> 45377 | L73: =SUM(L68:L72) -> 95064 | N73: =SUM(H73:L73) -> 6752559
B77: LINKED SUMMARY TABLE
D78: TABLE 9: Capital Costs Associated with Service Plan - By Service Recommendation | N78: 5-Year Costs
E80: Service Recommendation | H80: FY 26-27 | I80: FY 27-28 | J80: FY 28-29 | K80: FY 29-30 | L80: FY 30-31 | P80: Notes
E82: =E11 -> Eliminate 19X and Replace with US 50 Service (4 Round Trips) | H82: =SUM(H11,H19,H27,H35) -> 0 | I82: =SUM(I11,I19,I27,I35) -> 185400 | J82: =SUM(J11,J19,J27,J35) -> 0 | K82: =SUM(K11,K19,K27,K35) -> 0 | L82: =SUM(L11,L19,L27,L35) -> 0 | N82: =SUM(H82:L82) -> 185400
E83: =E12 -> Seasonal Expansion of Route 28 to Spooner Mobility Hub | H83: =SUM(H12,H20,I28,H36) -> 2337100 | I83: =SUM(I12,I20,I28,I36) -> 810000 | J83: =SUM(J12,J20,J28,J36) -> 60400 | K83: =SUM(K12,K20,K28,K36) -> 0 | L83: =SUM(L12,L20,L28,L36) -> 0 | N83: =SUM(H83:L83) -> 3207500
E84: =E13 -> Continue to Operate the Emerald Bay Shuttle (Route 30) Beyond the Pilot Period | H84: =SUM(H13,H21,H29,H37) -> 0 | I84: =SUM(I13,I21,I29,I37) -> 3136800 | J84: =SUM(J13,J21,J29,J37) -> 0 | K84: =SUM(K13,K21,K29,K37) -> 0 | L84: =SUM(L13,L21,L29,L37) -> 0 | N84: =SUM(H84:L84) -> 3136800
E85: =E14 -> Pilot Co-mingled Paratransit/Microtransit Service to Meyers | H85: =SUM(H14,H22,H30,H38) -> 6000 | I85: =SUM(I14,I22,I30,I38) -> 0 | J85: =SUM(J14,J22,J30,J38) -> 0 | K85: =SUM(K14,K22,K30,K38) -> 0 | L85: =SUM(L14,L22,L30,L38) -> 0 | N85: =SUM(H85:L85) -> 6000
E86: =E15 -> Discontinue Route 50 Deviation to LTCC | H86: =SUM(H15,H23,H31,H39) -> 0 | I86: =SUM(I15,I23,I31,I39) -> 0 | J86: =SUM(J15,J23,J31,J39) -> 0 | K86: =SUM(K15,K23,K31,K39) -> 0 | L86: =SUM(L15,L23,L31,L39) -> 0 | N86: =SUM(H86:L86) -> 0
E87: =E16 -> Reinstate TART Connect Service in Incline Village, NV | H87: =SUM(H16,H24,H32,H40) -> 0 | I87: =SUM(I16,I24,I32,I40) -> 0 | J87: =SUM(J16,J24,J32,J40) -> 0 | K87: =SUM(K16,K24,K32,K40) -> 0 | L87: =SUM(L16,L24,L32,L40) -> 0 | N87: =SUM(H87:L87) -> 0
E88: =E17 -> Increase Van Pools between Reno and Truckee/North Lake Tahoe | H88: =SUM(H17,H25,H33,H41) -> 0 | I88: =SUM(I17,I25,I33,I41) -> 0 | J88: =SUM(J17,J25,J33,J41) -> 0 | K88: =SUM(K17,K25,K33,K41) -> 0 | L88: =SUM(L17,L25,L33,L41) -> 0 | N88: =SUM(H88:L88) -> 0
E89: Total Cost | H89: =SUM(H82:H88) -> 2343100 | I89: =SUM(I82:I88) -> 4132200 | J89: =SUM(J82:J88) -> 60400 | K89: =SUM(K82:K88) -> 0 | L89: =SUM(L82:L88) -> 0 | N89: =SUM(H89:L89) -> 6535700
B93: LINKED SUMMARY TABLE | V93: From TART Transit replacement plan (11/2024) | AA93: 24/25
D94: TABLE 10: Capital Costs Associated with Governance Recommendations | N94: 5-Year Costs | V94: Gas cutaway | AA94: 151892.04
E96: Governance Recommendation | H96: FY 26-27 | I96: FY 27-28 | J96: FY 28-29 | K96: FY 29-30 | L96: FY 30-31 | P96: Notes | V96: Gas van (from 24/25 TART budget) | AA96: 81000
E98: =E48 -> Co-Branding Transit Services Under TART Brand | H98: =H48 -> 5000 | I98: =I48 -> 5000 | J98: =J48 -> 448300 | K98: =K48 -> 0 | L98: =L48 -> 0 | N98: =SUM(H98:L98) -> 458300
E99: =E52 -> Transition of Lake Link Contract to TTD | H99: =H52 -> 0 | I99: =I52 -> 57300 | J99: =J52 -> 0 | K99: =K52 -> 0 | L99: =L52 -> 0 | N99: =SUM(H99:L99) -> 57300
E100: =E54 -> Basin Wide Trip Planning Website | H100: =H54 -> 0 | I100: =I54 -> 20000 | J100: =J54 -> 0 | K100: =K54 -> 0 | L100: =L54 -> 0 | N100: =SUM(H100:L100) -> 20000
E101: =E55 -> Creation of Transit Network Manager Position | H101: =H55 -> 0 | I101: =I55 -> 9000 | J101: =J55 -> 0 | K101: =K55 -> 0 | L101: =L55 -> 0 | N101: =SUM(H101:L101) -> 9000
E102: Total Cost | H102: =SUM(H98:H101) -> 5000 | I102: =SUM(I98:I101) -> 91300 | J102: =SUM(J98:J101) -> 448300 | K102: =SUM(K98:K101) -> 0 | L102: =SUM(L98:L101) -> 0 | N102: =SUM(H102:L102) -> 544600

Sheet INPUTS>>>

Sheet VRH Rates
B3: Operating Cost Rates | C3: FY 26-27
B5: South Shore
C6: Form | D6: Per VSH | E6: Per VSM | F6: Fixed | I6: Tot. Op Cost/VSH | K6: NOTES
B7: TTD Fixed Route Bus | C7: =D27 -> TTDTTD | D7: 123.17 | E7: 1.6 | F7: 2077415.2 | I7: 214.66 | K7: Based on 24/25 actuals plus 4% inflation/yr
B8: TTD Paratransit | C8: =D27 -> TTDTTD | D8: =D7 -> 123.17 | E8: =E7 -> 1.6 | I8: =I7 -> 214.66 | K8: Based on 24/25 actuals plus 4% inflation/yr
B9: Lake Link | C9: =D29 -> SSTMAVia | D9: 65.23 | F9: 43215 | G9: 27195 | H9: =90000+1650+840 -> 92490 | I9: 68.7 | K9: SSTMA Lake Link contract costs for 2027. Plus Fixed Admin costs
B10: Route 30 | C10: =D28 -> TTDVia | I10: 147.8
B12: North Shore
B14: TART Fixed Route | C14: =D30 -> TARTTART | D14: 66.45 | E14: 1.7 | F14: 3188061.3 | I14: 185.83 | K14: Based on 24-25 actuals cost model from Existing Conditions report (+4% inflation/yr) | W14: 24-25 | X14: 26-27*
B15: TART Connect | C15: =D32 -> TARTDowntowner | D15: 46.56 | F15: 1724488 | I15: 107.23 | K15: Based on 24-25 actuals cost model from Existing Conditions report (+5% inflation/yr to reflect contract-specified escation rates) | W15: ='[32]TART cost model 24-25'!$B$44 -> 4003350 | X15: =W15*(1.05)^2 -> 4413693.4
B16: Placer TART Paratransit | C16: =D31 -> TARTTruckee | D16: 127.77784 | F16: 9338.3477 | I16: 134.52933 | K16: Based on 24-25 actuals cost model from Existing Conditions report (+4% inflation/yr)
A18: My Ride to Work | B18: Bus(TART) | I18: =284.34*(1+0.03)^2 -> 301.65631 | K18: Based on contract cost from TART/MRTW FY 24-25 (+3% inflation/yr)
B19: Van(TART) | I19: =96.85*(1+0.03)^2 -> 102.74816 | K19: Based on contract cost from TART/MRTW FY 24-25 (+3% inflation/yr)
B20: Shuttle (P&R) | C20: =D33 -> TNTTMAMRTW | I20: =195.13*(1.03) -> 200.9839 | K20: Based on Park and Ride contract cost from TNTTMA/MRTW FY 25-26 (+3% inflation/yr)
B21: Van(P&R) | I21: =128.75*1.03 -> 132.6125 | K21: Based on Park and Ride contract cost from TNTTMA/MRTW FY 25-26 (+3% inflation/yr)
B25: Agency/Operator Combinations
B27: TTD | C27: TTD | D27: =CONCATENATE(B27,C27) -> TTDTTD
B28: TTD | C28: Via | D28: =CONCATENATE(B28,C28) -> TTDVia
B29: SSTMA | C29: Via | D29: =CONCATENATE(B29,C29) -> SSTMAVia
B30: TART | C30: TART | D30: =CONCATENATE(B30,C30) -> TARTTART
B31: TART | C31: Truckee | D31: =CONCATENATE(B31,C31) -> TARTTruckee
B32: TART | C32: Downtowner | D32: =CONCATENATE(B32,C32) -> TARTDowntowner
B33: TNTTMA | C33: MRTW | D33: =CONCATENATE(B33,C33) -> TNTTMAMRTW

Sheet Fare Rates
B3: One-Way Pax Trip Fare
C5: TTD | D5: TART
B6: Local | C6: 0 | D6: 0
B7: Rural | C7: 0 | D7: 0
B8: Regional fx | C8: 0 | D8: 0
B9: Recreational | C9: 0 | D9: 0
B10: Route 30 | C10: 5

Sheet Operating Stats
D3: FY 2025-26
B6: Service/Route | C6: Agency | D6: Operator | E6: Passenger-Trips | F6: Vehicle Service Hours | G6: Vehicle Service Miles | H6: Data Year
B7: 19X | C7: TTD | D7: TTD | E7: 10747 | F7: 2250.4 | G7: 61381 | H7: 24-25
B8: 22 | C8: TTD | D8: TTD | E8: 18457 | F8: 4409.6 | G8: 121654 | H8: 24-25
B9: 28 | C9: TTD | D9: TTD | E9: 24699 | F9: 1192.7 | G9: 22330 | H9: 24-25
B10: 30 | C10: TTD | D10: Via | E10: 10700 | F10: 3500 | G10: 9850 | H10: 26-27 | I10: estimate
B11: 50 | C11: TTD | D11: TTD | E11: 170332 | F11: 9418.6 | G11: 134562 | H11: 24-25
B12: 51 | C12: TTD | D12: TTD | E12: 115 | F12: 167 | G12: 1700 | H12: 24-25
B13: 55 | C13: TTD | D13: TTD | E13: 55609 | F13: 9312.2 | G13: 111689 | H13: 24-25
B14: ADA Para | C14: TTD | D14: TTD | E14: 14556 | F14: 5429 | G14: 71677 | H14: 24-25
B15: Lake Link | C15: SSTMA | D15: Via | E15: 223047 | F15: 47002 | G15: 366322 | H15: 25-26 | I15: VSH are from contract not actual
B16: LL Z1 | C16: SSTMA | D16: Via | F16: =F15/3 -> 15667.333 | G16: =G15/3 -> 122107.33 | I16: Example
B17: LL Z2 | C17: SSTMA | D17: Via | F17: =F15/3 -> 15667.333 | G17: =G15/3 -> 122107.33 | I17: Example
B18: LL Z3 | C18: SSTMA | D18: Via | F18: =F15/3 -> 15667.333 | G18: =G15/3 -> 122107.33 | I18: Example
B19: West Shore | C19: TART | D19: TART | E19: 21205 | F19: 4237.5 | G19: 82391.1 | H19: 25-26
B20: N Shore | C20: TART | D20: TART | E20: 92011 | F20: 4983.5 | G20: 113132.1 | H20: 25-26
B21: Nevada | C21: TART | D21: TART | E21: 34977 | F21: 4219.3125 | G21: 63697 | H21: 25-26
B22: Main Line | C22: TART | D22: TART | E22: =SUM(E19:E21) -> 148193 | F22: =SUM(F19:F21) -> 13440.312 | G22: =SUM(G19:G21) -> 259220.2
B23: 89 | C23: TART | D23: TART | E23: 71136 | F23: 8331.75 | G23: 167948.7 | H23: 25-26
B24: 267 | C24: TART | D24: TART | E24: 73556 | F24: 8420.2333 | G24: 176999.3 | H24: 25-26
B25: Night | C25: TART | D25: TART | E25: 4725 | F25: 2985 | G25: 57781.2 | H25: 25-26
B26: ADA Para | C26: TART | D26: Truckee | E26: 3573 | F26: 1951.65 | G26: 34749 | H26: 25-26
B27: All | C27: TART | D27: Downtowner | E27: 157369 | F27: 27342.51 | G27: 544888.71 | H27: 25-26 | J27: =E27/F27 -> 5.7554701
B28: TC Z1 | C28: TART | D28: Downtowner | F28: =F27/3 -> 9114.17 | G28: =G27/3 -> 181629.57 | I28: Example
B29: TC Z2 | C29: TART | D29: Downtowner | F29: =F27/3 -> 9114.17 | G29: =G27/3 -> 181629.57 | I29: Example
B30: TC Z3 | C30: TART | D30: Downtowner | F30: =F27/6 -> 4557.085 | G30: =G27/6 -> 90814.785 | I30: Example
B31: TC Z4 | C31: TART | D31: Downtowner | F31: =F27/6 -> 4557.085 | G31: =G27/6 -> 90814.785 | I31: Example
B32: Park&Ride (Winter) | C32: TNTTMA | D32: MRTW | F32: 2500 | I32: Estimate
B33: Park&Ride (Summ) | C33: TNTTMA | D33: MRTW | F33: 500 | I33: Estimate
B34: NLTE | C34: TNTTMA | D34: MRTW | F34: 1200 | I34: Estimate based on budget costs for 25-26
D40: Summary Table (Linked)
D41: TTD Rural | E41: =SUM(E7:E8) -> 29204 | F41: =SUM(F7:F8) -> 6660 | G41: =SUM(G7:G8) -> 183035
D42: TTD Urban | E42: =SUM(E9,E11,E12,E13,E14) -> 265311 | F42: =SUM(F9,F11,F12,F13,F14) -> 25519.5 | G42: =SUM(G9,G11,G12,G13,G14) -> 341958
D43: TTD TOTAL | E43: =SUM(E7:E14) -> 305215 | F43: =SUM(F7:F14) -> 35679.5 | G43: =SUM(G7:G14) -> 534843
D44: LAKE LINK | E44: =E15 -> 223047 | F44: =F15 -> 47002 | G44: =G15 -> 366322
D45: TART TOTAL | E45: =SUM(E19:E26) -> 449376 | F45: =SUM(F19:F26) -> 48569.258 | G45: =SUM(G19:G26) -> 955918.6
D46: TART CONNECT | E46: =E27 -> 157369 | F46: =F27 -> 27342.51 | G46: =G27 -> 544888.71

Sheet FTA Allocation Split (26-27)
C3: FTA and TDA Funding Split Worksheet
D9: FEDERAL FUNDING APPORTIONMENT
D11: FTA Sub-Allocation (5307, 5339, 5310)
N13: INPUTS
N14: 1. NTD information
N15: 2. FTA Apportionment table
E16: TTD | F16: Revenue Miles (urban) | I16: Ridership (22/23)
F17: CA | G17: 483367 | I17: TTD | L17: 489907
F18: NV | G18: 319717 | I18: Placer-TART | L18: 613042 | V18: TOT 26 FTA
E19: Placer-TART | F19: CA | G19: 1207385 | L19: =SUM(L17:L18) -> 1102949 | V19: 4730069
F20: NV | G20: 200731
E21: Population (US Census) | I21: FY27 FTA Apportionments | K21: 5307 | L21: 5339 | M21: 5310 | O21: EXAMPLE. Based on FY 25-26, Increased by 1%
E22: TTD | F22: 31420 | G22: 2020 Census | L22: - | M22: -
E23: Placer-TART | F23: 16643 | G23: 2020 Census | I23: UZA Total | K23: ='25_26 FTA Funding Split (INFO)'!K24*1.01 -> 4296912.7 | L23: ='25_26 FTA Funding Split (INFO)'!L24*1.01 -> 405232.2 | M23: ='25_26 FTA Funding Split (INFO)'!M24*1.01 -> 75224.8
E26: Earned Share Factors
F27: Revenue Miles Factor | H27: Population Factor | J27: Ridership Factor | L27: Final
E28: TTD | F28: =G17+G18 -> 803084 | G28: =F28/F30 -> 0.36318922 | H28: =F22 -> 31420 | I28: =H28/H30 -> 0.65372532 | J28: =L17 -> 489907 | K28: =L17/(L17+L18) -> 0.4441792 | L28: =(G28+I28+K28)/3 -> 0.48703124
E29: Placer | F29: =G19+G20 -> 1408116 | G29: =F29/F30 -> 0.63681078 | H29: =F23 -> 16643 | I29: =H29/H30 -> 0.34627468 | J29: =L18 -> 613042 | K29: =L18/(L17+L18) -> 0.5558208 | L29: =(G29+I29+K29)/3 -> 0.51296876
E30: Total | F30: =SUM(F28:F29) -> 2211200 | H30: =SUM(H28:H29) -> 48063 | J30: =SUM(J28:J29) -> 1102949
E32: Allocation Totals by Operator
F33: 5307-Total | G33: 5307-Ops (75%) | H33: 5307-Cap (25%) | I33: 5339 | J33: 5310
E34: TTD | F34: =K23*L28 -> 2092730.7 | G34: =F34*0.75 -> 1569548.1 | H34: =F34-G34 -> 523182.68 | I34: =L23*L28 -> 197360.74
E35: Placer | F35: =K23*L29 -> 2204182 | G35: =F35*0.75 -> 1653136.5 | H35: =F35-G35 -> 551045.49 | I35: =L23*L29 -> 207871.46 | J35: =M23 -> 75224.8
E36: Total | F36: =SUM(F34:F35) -> 4296912.7 | G36: =SUM(G34:G35) -> 3222684.5 | H36: =SUM(H34:H35) -> 1074228.2 | I36: =SUM(I34:I35) -> 405232.2 | J36: =SUM(J34:J35) -> 75224.8

Sheet Actual Revenues
E1: 19X | F1: 22 | G1: 28 | H1: 50 | I1: 55 | J1: 51 | K1: ADA Para (TTD) | L1: 30 | M1: Lake Link (Zone 1) | N1: Lake Link (Zone 2) | O1: Lake Link (Zone 3) | P1: Mainline | Q1: Hwy 89 | R1: Hwy 267 | S1: Night | T1: ADA Para (Placer) | U1: TART Connect (Zone 1) | V1: TART Connect (Zone 2) | W1: TART Connect (Zone 3) | X1: TART Connect (Zone 4) | Y1: Park&Ride Shuttle (Winter) | Z1: Park&Ride Shuttle (Summer) | AA1: North Lake Tahoe Express | AB1: Vanpools | AC1: Total | AD1: Notes
C3: FTA 5307 (Tahoe UZA) - Formula | E3: 0 | F3: 0 | G3: 83115 | H3: 1012092.1 | I3: 397912.05 | J3: 12088.069 | K3: 459972.75 | AC3: =SUM(E3:L3) -> 1965180 | AD3: Can be used to cover 50% of operating costs (urban rtes), 80% ADA.
C4: FTA 5307 (Tahoe UZA) - CMAQ Funds | E4: 0 | F4: 0 | G4: 0 | H4: 184061 | I4: 147901 | J4: 0 | K4: 168038
C5: FTA 5307 (Tahoe UZA) - Carryover
C6: FTA 5311 NV (NDOT) | AC6: =SUM(E6:J6) -> 0 | AD6: Can be used to cover 50% of operating costs (rural rtes)
C7: FTA 5311 CA (PCTPA)
C8: FTA 5310 | AC8: =SUM(E8:J8) -> 0 | AD8: ADA
C9: FTA 5310 - Carryover
C10: TDA LTF (TRPA) | E10: 209888.04 | F10: 408846.98 | G10: 685.5266 | H10: 640648.39 | I10: 306176.9 | J10: 21031.352 | K10: 221384.49 | AC10: =SUM(E10:J10) -> 1587277.2 | AD10: TTD: 33% to rural, 66% to urban
C11: TDA LTF (PCTPA)
C12: TDA STA (TRPA) | AC12: =SUM(E12:J12) -> 0 | AD12: --
C13: TDA STA (PCTPA)
C14: State of Good Repair
C15: Low Carbon Transit Operations Program (LCTOP) - Operating | AC15: =SUM(E15:J15) -> 0
C16: Electrification Credits | E16: 577.96743 | F16: 1139.3179 | G16: 155.75774 | H16: 1553.6922 | I16: 861.86536 | J16: 109.02459 | K16: 664.67477 | AC16: =SUM(E16:J16) -> 4397.6252
C17: SB 125 (Operating) | E17: 0 | F17: 0 | G17: 0 | H17: 262920.28 | I17: 212457.41 | J17: 24622.31 | K17: 0 | AC17: =SUM(E17:L17) -> 500000
C18: Nevada State Parks | G18: 85000 | AC18: =SUM(E18:L18) -> 85000
C19: Tahoe Douglas Visitor Authority | J19: 100000 | AC19: =SUM(E19:L19) -> 100000
C20: Interest Revenue | AC20: =SUM(E20:J20) -> 0
C21: Keep Tahoe Blue (Emerald Bay Shuttle) | L21: 8322 | AC21: =SUM(E21:J21) -> 0 | AE21: Emerald Bay has already changed
C22: Carbon Reduction Program (Emerald Bay Shuttle) | L22: 271910 | AC22: =SUM(E22:J22) -> 0
C23: El Dorado County (Emerald Bay Shuttle) | L23: 331240 | AC23: =SUM(E23:J23) -> 0
C24: Placer County (Emerald Bay Shuttle) | L24: 8324 | AC24: =SUM(E24:J24) -> 0
C25: Washoe RTC | AA25: 12500
C26: Travel North Tahoe Nevada | AA26: 26417
C27: Reno Tahoe Airport Authority | AA27: 12500
C28: Placer County (Transient Occupancy Tax) | U28: =2900000*(2/6) -> 966666.67 | V28: =2900000*(2/6) -> 966666.67 | W28: =2900000*(1/6) -> 483333.33 | X28: =2900000*(1/6) -> 483333.33 | Y28: 418212 | AA28: 162594
C29: Town of Truckee | AA29: 15500
C30: Visit Truckee Tahoe | AA30: 2932
C31: North Shore Resort Partners
C32: North Shore Local Partners (Free Fares)
C33: Martis Zones of Benefit
C34: Douglas County
C35: City of South Lake Tahoe
C36: Tahoe Blue Events Center Mitigation Fee
C37: South Lake Tahoe Tourism Improvement District (SLTTID) | AC37: =SUM(E37:K37) -> 0 | AD37: Can be used to cover 50% of operating costs (urban rtes), 80% ADA.
C38: Heavenly | AC38: =SUM(E38:J38) -> 0 | AD38: Can be used to cover 50% of operating costs (rural rtes)
C39: Ceasars Entertainment | AC39: =SUM(E39:J39) -> 0 | AD39: ADA
C40: Roundhill Pines Resort | AC40: =SUM(E40:J40) -> 0 | AD40: TTD: 33% to rural, 66% to urban
C41: Advance Learning | AC41: =SUM(E41:J41) -> 0 | AD41: --
C42: Lake Tahoe Visitor's Authority | AC42: =SUM(E42:J42) -> 0
C43: Lake Tahoe Community College (LTCC) | AC43: =SUM(E43:J43) -> 0
AC44: =SUM(E44:J44) -> 0
AC45: =SUM(E45:J45) -> 0
AC46: =SUM(E46:J46) -> 0
AC47: =SUM(E47:J47) -> 0
AC48: =SUM(E48:J48) -> 0 | AE48: Emerald Bay has already changed
AC49: =SUM(E49:J49) -> 0
AC50: =SUM(E50:J50) -> 0
AC51: =SUM(E51:J51) -> 0
C53: Total | D53: T Revenue | E53: =SUM(E3:E51) -> 210466.01 | F53: =SUM(F37:F51) -> 0 | G53: =SUM(G37:G51) -> 0 | H53: =SUM(H37:H51) -> 0 | I53: =SUM(I37:I51) -> 0 | J53: =SUM(J37:J51) -> 0 | L53: =SUM(L37:L51) -> 0 | M53: =SUM(M37:M51) -> 0 | N53: =SUM(N37:N51) -> 0 | P53: =SUM(P37:P51) -> 0 | Q53: =SUM(Q37:Q51) -> 0 | R53: =SUM(R37:R51) -> 0 | U53: =SUM(U37:U51) -> 0
D54: Difference
C55: CMAQ grants coming
C56: Receive TDA end of Feb/beginning of March, so put FTA forward first
C57: FTA match with Toll credits in past, this made an impact, now need to provide more match
C58: Will start assigning TDA as match earlier. Fluid, need to look at 5 year term | P58: =+L10+L12 -> 0
C59: TDA has to be used on Nevada routes | AC59: FTA specifically says that where there are multiple recipients within a UZA, the MPO and designated recipients should determine the subarea allocation through a "fair and rational" process based on local needs.
C60: If saving a $1 on 5311 side, not really saving a$1 on 5307 side. | E60: Fiscal Cliff in 31 | P60: Fiscal Cliff in 31
C61: Historically had more Nevada 5311 than CA | E61: Cost Allocated by route based on % of miles per month | P61: Cost Allocated by route based on % of miles per month
C62: Now more people wanting NDOT 5311 | E62: Other than pilot funding, do not isolate costs. | P62: Other than pilot funding, do not isolate costs.
C63: Used to have funding from Vail and the Ridge | E63: Utlitiy costs pooled for entire system, this has been agreed to by partners | P63: Utlitiy costs pooled for entire system, this has been agreed to by partners
C64: Then got 5307 | E64: NDOT match - 20% match for admin and 40% for operating, 5% capitcal costs | P64: NDOT match - 20% match for admin and 40% for operating, 5% capitcal costs
C65: Decided (collectively) that who receives benefit of route gets urban/rural benefit
C66: If loose TDA, then money has to come from Douglas or other
C67: LCTOP alternates with TART every other year; based on ridership
C68: Don't see Douglas County, El Dorado County, SLT, Carson MPO, DART, get buy in from other authorities
C69: Hard to bridge a couple months of funding
C70: Matters when expenses hit
C72: Same level of detail for SSTMA, Placer
F75: TNTTMA | G75: TOT | L75: Private
C76: For lake Link | F76: NLTE | G76: 162594
F77: Sugar Bowl | G77: 172106
F78: Northstar | G78: 7426 | L78: 3899
F79: Palisades | G79: 238680 | L79: 119000
F81: MRTW Contract | L81: 488320
C82: TART/TART Connect
F83: NLTE | G83: =G76+#REF!+#REF!+#REF!+#REF!+#REF! -> #REF!

Sheet Revenue %s
B1: Revenue Conditions | C1: Match Requirements | D1: Revenue Sources | F1: 19X | G1: 22 | H1: 28 | I1: 50 | J1: 55 | K1: 51 | L1: ADA Para (TTD) | M1: 30 | N1: Lake Link (Zone 1) | O1: Lake Link (Zone 2) | P1: Lake Link (Zone 3) | Q1: Mainline | R1: Hwy 89 | S1: Hwy 267 | T1: Night | U1: ADA Para (Placer) | V1: TART Connect (Zone 1) | W1: TART Connect (Zone 2) | X1: TART Connect (Zone 3) | Y1: TART Connect (Zone 4) | Z1: Park&Ride Shuttle (Winter) | AA1: Park&Ride Shuttle (Summer) | AB1: North Lake Tahoe Express | AC1: Vanpools | AD1: Total | AE1: Notes
C3: 50% non-federal | D3: FTA 5307 (Tahoe UZA) - Formula | F3: 0 | G3: 0 | H3: 0.042293836 | I3: 0.51501243 | J3: 0.20248122 | K3: 0.0061511257 | L3: 0.23406139 | M3: 0 | N3: 0 | O3: 0 | P3: 0 | Q3: ='Operating Stats'!F22/'Operating Stats'!F45 -> 0.27672468 | R3: ='Operating Stats'!F23/'Operating Stats'!F45 -> 0.17154369 | S3: ='Operating Stats'!F24/'Operating Stats'!F45 -> 0.17336549 | T3: ='Operating Stats'!F25/'Operating Stats'!F45 -> 0.061458628 | U3: ='Operating Stats'!F26/'Operating Stats'!F45 -> 0.040182825 | V3: 0 | W3: 0 | X3: 0 | Y3: 0 | Z3: 0 | AA3: 0 | AB3: 0 | AC3: 0 | AD3: =SUM(F3:M3) -> 1 | AE3: Can be used to cover 50% of operating costs (urban rtes), 80% ADA.
C4: 50% non-federal | D4: FTA 5307 (Tahoe UZA) - CMAQ Funds | F4: 0 | G4: 0 | H4: 0 | I4: 0.368122 | J4: 0.295802 | K4: 0 | L4: 0.336076 | M4: 0 | N4: 0 | O4: 0 | P4: 0
C5: 50% non-federal | D5: FTA 5307 (Tahoe UZA) - Carryover | F5: 0 | G5: 0 | H5: 0 | I5: 0.368122 | J5: 0.295802 | K5: 0 | L5: 0.336076 | M5: 0 | N5: 0 | O5: 0 | P5: 0
B6: Can only be applied to rural routes (19x and 22) | C6: 50% non-federal | D6: FTA 5311 NV (NDOT) | F6: 0.33921198 | G6: 0.66078802 | H6: 0 | I6: 0 | J6: 0 | K6: 0 | L6: 0 | M6: 0 | N6: 0 | O6: 0 | P6: 0 | AD6: =SUM(F6:K6) -> 1 | AE6: Can be used to cover 50% of operating costs (rural rtes)
B7: Can only be applied to rural routes | C7: 50% non-federal | D7: FTA 5311 CA (PCTPA) | F7: 0 | G7: 0 | H7: 0 | I7: 0 | J7: 0 | K7: 0 | L7: 0 | M7: 0 | N7: 0 | O7: 0 | P7: 0
B8: Can only be applied to ADA routes | C8: 50% non-federal | D8: FTA 5310 | F8: 0 | G8: 0 | H8: 0 | I8: 0 | J8: 0 | K8: 0 | L8: 1 | M8: 0 | N8: 0 | O8: 0 | P8: 0 | AD8: =SUM(F8:K8) -> 0 | AE8: ADA
B9: Can only be applied to ADA routes | C9: 50% non-federal | D9: FTA 5310 - Carryover | F9: 0 | G9: 0 | H9: 0 | I9: 0 | J9: 0 | K9: 0 | L9: 1 | M9: 0 | N9: 0 | O9: 0 | P9: 0
B10: California funding ideally used in CA, but can be used as federal match | C10: no match requirement | D10: TDA LTF (TRPA) | F10: 0.11604605 | G10: 0.22604945 | H10: 0.00037902423 | I10: 0.35421129 | J10: 0.16928368 | K10: 0.01162813 | L10: 0.12240238 | M10: 0 | N10: 0 | O10: 0 | P10: 0 | AD10: =SUM(F10:K10) -> 0.87759762 | AE10: TTD: 33% to rural, 66% to urban
B11: California funding ideally used in CA, but can be used as federal match | C11: no match requirement | D11: TDA LTF (PCTPA) | F11: 0 | G11: 0 | H11: 0 | I11: 0 | J11: 0 | K11: 0 | L11: 0 | M11: 0 | N11: 0 | O11: 0 | P11: 0
B12: California funding ideally used in CA, but can be used as federal match | C12: no match requirement | D12: TDA STA (TRPA) | F12: 0.11604605 | G12: 0.22604945 | H12: 0.00037902423 | I12: 0.35421129 | J12: 0.16928368 | K12: 0.01162813 | L12: 0.12240238 | M12: 0 | N12: 0 | O12: 0 | P12: 0 | AD12: =SUM(F12:K12) -> 0.87759762 | AE12: --
B13: California funding ideally used in CA, but can be used as federal match | C13: no match requirement | D13: TDA STA (PCTPA) | F13: 0 | G13: 0 | H13: 0 | I13: 0 | J13: 0 | K13: 0 | L13: 0 | M13: 0 | N13: 0 | O13: 0 | P13: 0
B14: California funding ideally used in CA, but can be used as federal match | C14: no match requirement | D14: State of Good Repair | F14: 0 | G14: 0 | H14: 0 | I14: 0 | J14: 0 | K14: 0 | L14: 0 | M14: 0 | N14: 0 | O14: 0 | P14: 0
B15: California funding ideally used in CA, but can be used as federal match | C15: no match requirement | D15: Low Carbon Transit Operations Program (LCTOP) - Operating | F15: ='Operating Stats'!F7/'Operating Stats'!F43 -> 0.063072633 | G15: ='Operating Stats'!F8/'Operating Stats'!F43 -> 0.12358918 | H15: ='Operating Stats'!F9/'Operating Stats'!F43 -> 0.033428159 | I15: ='Operating Stats'!F11/'Operating Stats'!F43 -> 0.26397791 | J15: ='Operating Stats'!F13/'Operating Stats'!F43 -> 0.26099581 | K15: ='Operating Stats'!F12/'Operating Stats'!F43 -> 0.0046805589 | L15: ='Operating Stats'!F14/'Operating Stats'!F43 -> 0.1521602 | M15: 0 | N15: 0 | O15: 0 | P15: 0 | AD15: =SUM(F15:K15) -> 0.74974425
B16: not real money | C16: not real money only used as match for other sources | D16: Electrification Credits | F16: 0.11417092 | G16: 0.22505934 | H16: 0.030768177 | I16: 0.30691429 | J16: 0.17025174 | K16: 0.021536573 | L16: 0.13129897 | M16: 0 | N16: 0 | O16: 0 | P16: 0 | AD16: =SUM(F16:K16) -> 0.86870103
B17: California funding ideally used in CA, but can be used as federal match | C17: no match requirement | D17: SB 125 (Operating) | F17: 0 | G17: 0 | H17: 0 | I17: 0.52584056 | J17: 0.42491482 | K17: 0.04924462 | L17: 0 | M17: 0 | N17: 0 | O17: 0 | P17: 0 | AD17: =SUM(F17:M17) -> 1
B18: Only applied to Route 28 | C18: no match requirement | D18: Nevada State Parks | F18: 0 | G18: 0 | H18: 1 | I18: 0 | J18: 0 | K18: 0 | L18: 0 | M18: 0 | N18: 0 | O18: 0 | P18: 0 | AD18: =SUM(F18:M18) -> 1
B19: ideally applied only to NV routes | C19: no match requirement | D19: Tahoe Douglas Visitor Authority | F19: 0 | G19: 0 | H19: 0 | I19: 0 | J19: 0 | K19: 1 | L19: 0 | M19: 0 | N19: 0 | O19: 0 | P19: 0 | AD19: =SUM(F19:M19) -> 1
C20: no match requirement | D20: Interest Revenue | F20: =F15 -> 0.063072633 | G20: =G15 -> 0.12358918 | H20: =H15 -> 0.033428159 | I20: =I15 -> 0.26397791 | J20: =J15 -> 0.26099581 | K20: =K15 -> 0.0046805589 | L20: =L15 -> 0.1521602 | M20: 0 | N20: 0 | O20: 0 | P20: 0 | AD20: =SUM(F20:K20) -> 0.74974425
C21: no match requirement | D21: Keep Tahoe Blue (Emerald Bay Shuttle) | F21: 0 | G21: 0 | H21: 0 | I21: 0 | J21: 0 | K21: 0 | L21: 0 | M21: 1 | AD21: =SUM(F21:K21) -> 0 | AF21: Emerald Bay has already changed
C22: 11.47% non-federal | D22: Carbon Reduction Program (Emerald Bay Shuttle) | F22: 0 | G22: 0 | H22: 0 | I22: 0 | J22: 0 | K22: 0 | L22: 0 | M22: 1 | AD22: =SUM(F22:K22) -> 0
B23: Ideally used only in CA | C23: no match requirement | D23: El Dorado County (Emerald Bay Shuttle) | F23: 0 | G23: 0 | H23: 0 | I23: 0 | J23: 0 | K23: 0 | L23: 0 | M23: 1 | AD23: =SUM(F23:K23) -> 0
B24: Ideally used only in CA | C24: no match requirement | D24: Placer County (Emerald Bay Shuttle) | F24: 0 | G24: 0 | H24: 0 | I24: 0 | J24: 0 | K24: 0 | L24: 0 | M24: 1 | AD24: =SUM(F24:K24) -> 0
B25: Only applied to TART NV route | C25: no match requirement | D25: Washoe RTC | Q25: =1-AB25 -> 0.958 | AB25: 0.042
B26: Ideally used only in NV | C26: no match requirement | D26: Travel North Tahoe Nevada | AB26: 1
C27: no match requirement | D27: Reno Tahoe Airport Authority | AB27: 1
B28: Ideally used only in Placer County | C28: no match requirement | D28: Placer County (Transient Occupancy Tax)
C29: no match requirement | D29: Town of Truckee
C30: no match requirement | D30: Visit Truckee Tahoe | AB30: 1
C31: no match requirement | D31: North Shore Resort Partners
C32: no match requirement | D32: North Shore Local Partners (Free Fares)
C33: no match requirement | D33: Martis Zones of Benefit
B34: Ideally used only in Douglas County | C34: no match requirement | D34: Douglas County | N34: 0.5 | O34: 0.25 | P34: 0.25
B35: Ideally used only in the City of South Lake Tahoe | C35: no match requirement | D35: City of South Lake Tahoe | N35: 0.5 | O35: 0.25 | P35: 0.25
C36: no match requirement | D36: Tahoe Blue Events Center Mitigation Fee | N36: 0.5 | O36: 0.25 | P36: 0.25
C37: no match requirement | D37: South Lake Tahoe Tourism Improvement District (SLTTID) | N37: 0.5 | O37: 0.25 | P37: 0.25 | AD37: =SUM(F37:L37) -> 0 | AE37: Can be used to cover 50% of operating costs (urban rtes), 80% ADA.
C38: no match requirement | D38: Heavenly | N38: 0.5 | O38: 0.25 | P38: 0.25 | AD38: =SUM(F38:K38) -> 0 | AE38: Can be used to cover 50% of operating costs (rural rtes)
C39: no match requirement | D39: Ceasars Entertainment | N39: 0.5 | O39: 0.25 | P39: 0.25 | AD39: =SUM(F39:K39) -> 0 | AE39: ADA
C40: no match requirement | D40: Roundhill Pines Resort | N40: 0.5 | O40: 0.25 | P40: 0.25 | AD40: =SUM(F40:K40) -> 0 | AE40: TTD: 33% to rural, 66% to urban
C41: no match requirement | D41: Advance Learning | N41: 0.5 | O41: 0.25 | P41: 0.25 | AD41: =SUM(F41:K41) -> 0 | AE41: --
C42: no match requirement | D42: Lake Tahoe Visitor's Authority | N42: 0.5 | O42: 0.25 | P42: 0.25 | AD42: =SUM(F42:K42) -> 0
C43: no match requirement | D43: Lake Tahoe Community College (LTCC) | N43: 0.5 | O43: 0.25 | P43: 0.25 | AD43: =SUM(F43:K43) -> 0
AD44: =SUM(F44:K44) -> 0
AD45: =SUM(F45:K45) -> 0
AD46: =SUM(F46:K46) -> 0
AD47: =SUM(F47:K47) -> 0
AD48: =SUM(F48:K48) -> 0 | AF48: Emerald Bay has already changed
AD49: =SUM(F49:K49) -> 0
AD50: =SUM(F50:K50) -> 0
AD51: =SUM(F51:K51) -> 0
D53: Total | E53: T Revenue | F53: =SUM(F3:F51) -> 0.81162026 | G53: =SUM(G37:G51) -> 0 | H53: =SUM(H37:H51) -> 0 | I53: =SUM(I37:I51) -> 0 | J53: =SUM(J37:J51) -> 0 | K53: =SUM(K37:K51) -> 0 | M53: =SUM(M37:M51) -> 0 | N53: =SUM(N37:N51) -> 3.5 | O53: =SUM(O37:O51) -> 1.75 | Q53: =SUM(Q37:Q51) -> 0 | R53: =SUM(R37:R51) -> 0 | S53: =SUM(S37:S51) -> 0 | V53: =SUM(V37:V51) -> 0
E54: Difference
D55: CMAQ grants coming
D56: Receive TDA end of Feb/beginning of March, so put FTA forward first
D57: FTA match with Toll credits in past, this made an impact, now need to provide more match
D58: Will start assigning TDA as match earlier. Fluid, need to look at 5 year term | Q58: =+M10+M12 -> 0
D59: TDA has to be used on Nevada routes | AD59: FTA specifically says that where there are multiple recipients within a UZA, the MPO and designated recipients should determine the subarea allocation through a "fair and rational" process based on local needs.
D60: If saving a $1 on 5311 side, not really saving a$1 on 5307 side. | F60: Fiscal Cliff in 31 | Q60: Fiscal Cliff in 31
D61: Historically had more Nevada 5311 than CA | F61: Cost Allocated by route based on % of miles per month | Q61: Cost Allocated by route based on % of miles per month
D62: Now more people wanting NDOT 5311 | F62: Other than pilot funding, do not isolate costs. | Q62: Other than pilot funding, do not isolate costs.
D63: Used to have funding from Vail and the Ridge | F63: Utlitiy costs pooled for entire system, this has been agreed to by partners | Q63: Utlitiy costs pooled for entire system, this has been agreed to by partners
D64: Then got 5307 | F64: NDOT match - 20% match for admin and 40% for operating, 5% capitcal costs | Q64: NDOT match - 20% match for admin and 40% for operating, 5% capitcal costs
D65: Decided (collectively) that who receives benefit of route gets urban/rural benefit
D66: If loose TDA, then money has to come from Douglas or other
D67: LCTOP alternates with TART every other year; based on ridership
D68: Don't see Douglas County, El Dorado County, SLT, Carson MPO, DART, get buy in from other authorities
D69: Hard to bridge a couple months of funding
D70: Matters when expenses hit
D72: Same level of detail for SSTMA, Placer
G75: TNTTMA | H75: TOT | M75: Private
D76: For lake Link | G76: NLTE | H76: 162594
G77: Sugar Bowl | H77: 172106
G78: Northstar | H78: 7426 | M78: 3899
G79: Palisades | H79: 238680 | M79: 119000
G81: MRTW Contract | M81: 488320
D82: TART/TART Connect
G83: NLTE | H83: =H76+#REF!+#REF!+#REF!+#REF!+#REF! -> #REF!

Sheet Per Route Model
D1: FY 24-25 Allocated total operating cost per route (Existing Conditions Memo) | J1: 480964.47 | K1: 944472.91 | L1: 239855.47 | M1: 1832466 | N1: 1780257.5 | O1: new | P1: 1047571 | Q1: =+Q44 -> 0 | R1: new | S1: 1780257.5 | T1: 1047571 | U1: 480964.47 | V1: 944472.91 | W1: 239855.47 | Z1: 1832466
U2: Total Cost per hour including Admin Costs in a way that can be variable based on operator, how do we increase for inflation?
L3: =SUM(L10:AA10,AD10:AE10) -> 18209821 | AK3: Do we use same split between North Shore/South Shore for 5307?
L4: =SUM(J10:K10) -> 1429635.6 | AK4: This is more for a regional planning perspective not detailed enough for operations
D5: TTD | E5: Placer TART | F5: Lake Link | G5: TNTTMA | J5: 19X | K5: 22 | L5: 28 | M5: 50 | N5: 55 | O5: 51 | P5: ADA Para (TTD) | Q5: 30 | R5: Lake Link (Zone 1) | S5: Lake Link (Zone 2) | T5: Lake Link (Zone 3) | U5: Mainline | V5: Hwy 89 | W5: Hwy 267 | X5: Night | Y5: ADA Para (Placer) | Z5: TART Connect (Zone 1) | AA5: TART Connect (Zone 2) | AB5: TART Connect (Zone 3) | AC5: TART Connect (Zone 4) | AD5: Park&Ride Shuttle (Winter) | AE5: Park&Ride Shuttle (Summer) | AF5: North Lake Tahoe Express | AG5: Vanpools | AH5: Total | AI5: Notes
I6: ='Operating Stats'!C6 -> Agency | J6: ='Operating Stats'!C7 -> TTD | K6: ='Operating Stats'!C8 -> TTD | L6: ='Operating Stats'!C9 -> TTD | M6: ='Operating Stats'!C11 -> TTD | N6: ='Operating Stats'!C13 -> TTD | O6: ='Operating Stats'!C12 -> TTD | P6: ='Operating Stats'!C14 -> TTD | Q6: ='Operating Stats'!C10 -> TTD | R6: ='Operating Stats'!C16 -> SSTMA | S6: ='Operating Stats'!C17 -> SSTMA | T6: ='Operating Stats'!C18 -> SSTMA | U6: ='Operating Stats'!C22 -> TART | V6: ='Operating Stats'!C23 -> TART | W6: ='Operating Stats'!C24 -> TART | X6: ='Operating Stats'!C25 -> TART | Y6: ='Operating Stats'!C26 -> TART | Z6: ='Operating Stats'!C28 -> TART | AA6: ='Operating Stats'!C29 -> TART | AB6: ='Operating Stats'!C30 -> TART | AC6: ='Operating Stats'!C31 -> TART | AD6: ='Operating Stats'!C32 -> TNTTMA | AE6: ='Operating Stats'!C33 -> TNTTMA | AF6: ='Operating Stats'!C34 -> TNTTMA
C7: Funding Source | D7: 26-27 Budget | E7: 26-27 Budget | F7: 26-27 Budget | G7: 25-26 Budget | I7: ='Operating Stats'!D6 -> Operator | J7: ='Operating Stats'!D7 -> TTD | K7: ='Operating Stats'!D8 -> TTD | L7: ='Operating Stats'!D9 -> TTD | M7: ='Operating Stats'!D11 -> TTD | N7: ='Operating Stats'!D13 -> TTD | O7: ='Operating Stats'!D12 -> TTD | P7: ='Operating Stats'!D14 -> TTD | Q7: ='Operating Stats'!D10 -> Via | R7: ='Operating Stats'!D16 -> Via | S7: ='Operating Stats'!D17 -> Via | T7: ='Operating Stats'!D18 -> Via | U7: ='Operating Stats'!D22 -> TART | V7: ='Operating Stats'!D23 -> TART | W7: ='Operating Stats'!D24 -> TART | X7: ='Operating Stats'!D25 -> TART | Y7: ='Operating Stats'!D26 -> Truckee | Z7: ='Operating Stats'!D28 -> Downtowner | AA7: ='Operating Stats'!D29 -> Downtowner | AB7: ='Operating Stats'!D30 -> Downtowner | AC7: ='Operating Stats'!D31 -> Downtowner | AD7: ='Operating Stats'!D32 -> MRTW | AE7: ='Operating Stats'!D33 -> MRTW | AF7: ='Operating Stats'!D34 -> MRTW | AK7: TART | AL7: Lake Link | AM7: TNTTMA
I8: Agency/Op Combinations | J8: =CONCATENATE(J6,J7) -> TTDTTD | K8: =CONCATENATE(K6,K7) -> TTDTTD | L8: =CONCATENATE(L6,L7) -> TTDTTD | M8: =CONCATENATE(M6,M7) -> TTDTTD | N8: =CONCATENATE(N6,N7) -> TTDTTD | O8: =CONCATENATE(O6,O7) -> TTDTTD | P8: =CONCATENATE(P6,P7) -> TTDTTD | Q8: =CONCATENATE(Q6,Q7) -> TTDVia | ... AF8: =CONCATENATE(AF6,AF7) -> TNTTMAMRTW
I9: Cost per VSH | J9: =IF(J8='VRH Rates'!$C$7,'VRH Rates'!$I$7,IF(J8='VRH Rates'!$C$9,'VRH Rates'!$I$9,IF(J8='VRH Rates'!$C$10,'VRH Rates'!$I$10,IF(J8='VRH Rates'!$C$14,'VRH Rates'!$I$14,IF(J8='VRH Rates'!$C$15,'VRH Rates'!$I$15,IF(J8='VRH Rates'!$C$16,'VRH Rates'!$I$16,IF(J8='VRH Rates'!$C$20,'VRH Rates'!$I$20))))))) -> 214.66 | K9: =IF(K8='VRH Rates'!$C$7,'VRH Rates'!$I$7,IF(K8='VRH Rates'!$C$9,'VRH Rates'!$I$9,IF(K8='VRH Rates'!$C$10,'VRH Rates'!$I$10,IF(K8='VRH Rates'!$C$14,'VRH Rates'!$I$14,IF(K8='VRH Rates'!$C$15,'VRH Rates'!$I$15,IF(K8='VRH Rates'!$C$16,'VRH Rates'!$I$16,IF(K8='VRH Rates'!$C$20,'VRH Rates'!$I$20))))))) -> 214.66 | L9: =IF(L8='VRH Rates'!$C$7,'VRH Rates'!$I$7,IF(L8='VRH Rates'!$C$9,'VRH Rates'!$I$9,IF(L8='VRH Rates'!$C$10,'VRH Rates'!$I$10,IF(L8='VRH Rates'!$C$14,'VRH Rates'!$I$14,IF(L8='VRH Rates'!$C$15,'VRH Rates'!$I$15,IF(L8='VRH Rates'!$C$16,'VRH Rates'!$I$16,IF(L8='VRH Rates'!$C$20,'VRH Rates'!$I$20))))))) -> 214.66 | M9: =IF(M8='VRH Rates'!$C$7,'VRH Rates'!$I$7,IF(M8='VRH Rates'!$C$9,'VRH Rates'!$I$9,IF(M8='VRH Rates'!$C$10,'VRH Rates'!$I$10,IF(M8='VRH Rates'!$C$14,'VRH Rates'!$I$14,IF(M8='VRH Rates'!$C$15,'VRH Rates'!$I$15,IF(M8='VRH Rates'!$C$16,'VRH Rates'!$I$16,IF(M8='VRH Rates'!$C$20,'VRH Rates'!$I$20))))))) -> 214.66 | N9: =IF(N8='VRH Rates'!$C$7,'VRH Rates'!$I$7,IF(N8='VRH Rates'!$C$9,'VRH Rates'!$I$9,IF(N8='VRH Rates'!$C$10,'VRH Rates'!$I$10,IF(N8='VRH Rates'!$C$14,'VRH Rates'!$I$14,IF(N8='VRH Rates'!$C$15,'VRH Rates'!$I$15,IF(N8='VRH Rates'!$C$16,'VRH Rates'!$I$16,IF(N8='VRH Rates'!$C$20,'VRH Rates'!$I$20))))))) -> 214.66 | O9: =IF(O8='VRH Rates'!$C$7,'VRH Rates'!$I$7,IF(O8='VRH Rates'!$C$9,'VRH Rates'!$I$9,IF(O8='VRH Rates'!$C$10,'VRH Rates'!$I$10,IF(O8='VRH Rates'!$C$14,'VRH Rates'!$I$14,IF(O8='VRH Rates'!$C$15,'VRH Rates'!$I$15,IF(O8='VRH Rates'!$C$16,'VRH Rates'!$I$16,IF(O8='VRH Rates'!$C$20,'VRH Rates'!$I$20))))))) -> 214.66 | P9: =IF(P8='VRH Rates'!$C$7,'VRH Rates'!$I$7,IF(P8='VRH Rates'!$C$9,'VRH Rates'!$I$9,IF(P8='VRH Rates'!$C$10,'VRH Rates'!$I$10,IF(P8='VRH Rates'!$C$14,'VRH Rates'!$I$14,IF(P8='VRH Rates'!$C$15,'VRH Rates'!$I$15,IF(P8='VRH Rates'!$C$16,'VRH Rates'!$I$16,IF(P8='VRH Rates'!$C$20,'VRH Rates'!$I$20))))))) -> 214.66 | Q9: =IF(Q8='VRH Rates'!$C$7,'VRH Rates'!$I$7,IF(Q8='VRH Rates'!$C$9,'VRH Rates'!$I$9,IF(Q8='VRH Rates'!$C$10,'VRH Rates'!$I$10,IF(Q8='VRH Rates'!$C$14,'VRH Rates'!$I$14,IF(Q8='VRH Rates'!$C$15,'VRH Rates'!$I$15,IF(Q8='VRH Rates'!$C$16,'VRH Rates'!$I$16,IF(Q8='VRH Rates'!$C$20,'VRH Rates'!$I$20))))))) -> 147.8 | ... AF9: =IF(AF8='VRH Rates'!$C$7,'VRH Rates'!$I$7,IF(AF8='VRH Rates'!$C$9,'VRH Rates'!$I$9,IF(AF8='VRH Rates'!$C$10,'VRH Rates'!$I$10,IF(AF8='VRH Rates'!$C$14,'VRH Rates'!$I$14,IF(AF8='VRH Rates'!$C$15,'VRH Rates'!$I$15,IF(AF8='VRH Rates'!$C$16,'VRH Rates'!$I$16,IF(AF8='VRH Rates'!$C$20,'VRH Rates'!$I$20))))))) -> 200.9839
I10: Est Op Cost | J10: =J9*'Operating Stats'!$F7 -> 483070.86 | K10: =K9*'Operating Stats'!$F8 -> 946564.74 | L10: =L9*'Operating Stats'!$F9 -> 256024.98 | M10: =M9*'Operating Stats'!$F11 -> 2021796.7 | N10: =N9*'Operating Stats'!$F13 -> 1998956.9 | O10: =O9*'Operating Stats'!$F12 -> 35848.22 | P10: =P9*'Operating Stats'!$F14 -> 1165389.1 | Q10: =Q9*'Operating Stats'!$F10 -> 517300 | R10: =R9*'Operating Stats'!$F16 -> 1076345.8 | S10: =S9*'Operating Stats'!$F17 -> 1076345.8 | T10: =T9*'Operating Stats'!$F18 -> 1076345.8 | U10: =U9*'Operating Stats'!$F22 -> 2497613.3 | V10: =V9*'Operating Stats'!$F23 -> 1548289.1 | W10: =W9*'Operating Stats'!$F24 -> 1564732 | X10: =X9*'Operating Stats'!$F25 -> 554702.55 | Y10: =Y9*'Operating Stats'!$F26 -> 262554.16 | Z10: =Z9*'Operating Stats'!$F28 -> 977312.45 | AA10: =AA9*'Operating Stats'!$F29 -> 977312.45 | AB10: =AB9*'Operating Stats'!$F30 -> 488656.22 | AC10: =AC9*'Operating Stats'!$F31 -> 488656.22 | AD10: =AD9*'Operating Stats'!$F32 -> 502459.75 | AE10: =AE9*'Operating Stats'!$F33 -> 100491.95 | AF10: =AF9*'Operating Stats'!$F34 -> 241180.68 | AH10: =SUM(J10:AG10) -> 20857950
H11: Deficit/Surplus?
C12: FTA 5307 (Tahoe UZA) - Formula | D12: ='FTA Allocation Split (26-27)'!G34 -> 1569548.1 | E12: ='FTA Allocation Split (26-27)'!G35 -> 1653136.5 | J12: =$D$12*'Revenue %s'!F3 -> 0 | K12: =$D$12*'Revenue %s'!G3 -> 0 | L12: =$D$12*'Revenue %s'!H3 -> 66382.207 | M12: =$D$12*'Revenue %s'!I3 -> 808336.76 | N12: =$D$12*'Revenue %s'!J3 -> 317804.01 | O12: =$D$12*'Revenue %s'!K3 -> 9654.4874 | P12: =$D$12*'Revenue %s'!L3 -> 367370.59 | Q12: =$D$12*'Revenue %s'!M3 -> 0 | ... T12: =$D$12*'Revenue %s'!P3 -> 0 | U12: =$E$12*'Revenue %s'!Q3 -> 457463.66 | V12: =$E$12*'Revenue %s'!R3 -> 283585.14 | W12: =$E$12*'Revenue %s'!S3 -> 286596.82 | X12: =$E$12*'Revenue %s'!T3 -> 101599.5 | Y12: =$E$12*'Revenue %s'!U3 -> 66427.693 | Z12: =$E$12*'Revenue %s'!V3 -> 0 | AA12: =$E$12*'Revenue %s'!W3 -> 0 | AB12: =$E$12*'Revenue %s'!X3 -> 0 | AC12: =$E$12*'Revenue %s'!Y3 -> 0 | AH12: =SUM(J12:P12) -> 1569548.1 | AI12: Can be used to cover 50% of operating costs (urban rtes), 80% ADA.
C13: FTA 5307 (Tahoe UZA) - CMAQ Funds | D13: 596121 | E13: 0 | J13: =$D$13*'Revenue %s'!F4 -> 0 | K13: =$D$13*'Revenue %s'!G4 -> 0 | L13: =$D$13*'Revenue %s'!H4 -> 0 | M13: =$D$13*'Revenue %s'!I4 -> 219445.25 | N13: =$D$13*'Revenue %s'!J4 -> 176333.78 | O13: =$D$13*'Revenue %s'!K4 -> 0 | P13: =$D$13*'Revenue %s'!L4 -> 200341.96 | Q13: =$D$13*'Revenue %s'!M4 -> 0 | ... T13: =$D$13*'Revenue %s'!P4 -> 0
C14: FTA 5307 (Tahoe UZA) - Carryover | D14: 946281.95 | E14: 0 | J14: =$D$14*'Revenue %s'!F5 -> 0 | K14: =$D$14*'Revenue %s'!G5 -> 0 | L14: =$D$14*'Revenue %s'!H5 -> 0 | M14: =$D$14*'Revenue %s'!I5 -> 348347.2 | N14: =$D$14*'Revenue %s'!J5 -> 279912.09 | O14: =$D$14*'Revenue %s'!K5 -> 0 | P14: =$D$14*'Revenue %s'!L5 -> 318022.65 | Q14: =$D$14*'Revenue %s'!M5 -> 0 | ... T14: =$D$14*'Revenue %s'!P5 -> 0
C15: FTA 5311 NV (NDOT) | D15: 1798577 | E15: 0 | H15: =D15-(SUM(J15:AG15)) -> 0 | J15: =$D$15*'Revenue %s'!F6 -> 610098.87 | K15: =$D$15*'Revenue %s'!G6 -> 1188478.1 | L15: =$D$15*'Revenue %s'!H6 -> 0 | M15: =$D$15*'Revenue %s'!I6 -> 0 | N15: =$D$15*'Revenue %s'!J6 -> 0 | O15: =$D$15*'Revenue %s'!K6 -> 0 | P15: =$D$15*'Revenue %s'!L6 -> 0 | Q15: =$D$15*'Revenue %s'!M6 -> 0 | ... T15: =$D$15*'Revenue %s'!P6 -> 0 | AH15: =SUM(J15:O15) -> 1798577 | AI15: Can be used to cover 50% of operating costs (rural rtes)
C16: FTA 5311 CA (PCTPA) | E16: 290000
C17: FTA 5310 | D17: ='FTA Allocation Split (26-27)'!J34 -> 0 | E17: ='FTA Allocation Split (26-27)'!J35 -> 75224.8 | P17: =$D$17*'Revenue %s'!L8 -> 0 | AH17: =SUM(J17:O17) -> 0 | AI17: ADA
C18: FTA 5310 - Carryover | D18: 30277 | P18: =$D$18*'Revenue %s'!L9 -> 30277
C19: TDA LTF (TRPA) | D19: 615042.33 | E19: 913053 | AH19: =SUM(J19:O19) -> 0 | AI19: TTD: 33% to rural, 66% to urban
C20: TDA LTF (PCTPA) | E20: 1675000
C21: TDA STA (TRPA) | D21: 1230084.7 | E21: 510729 | AH21: =SUM(J21:O21) -> 0 | AI21: --
C22: TDA STA (PCTPA) | E22: 308898
C23: State of Good Repair | E23: 100084
C24: Low Carbon Transit Operations Program (LCTOP) - Operating | D24: 265506 | AH24: =SUM(J24:O24) -> 0
C25: Electrification Credits | D25: 8000 | AH25: =SUM(J25:O25) -> 0
C26: SB 125 (Operating) | D26: 825000 | F26: 750000 | J26: =$D$26*'Revenue %s'!F17 -> 0 | K26: =$D$26*'Revenue %s'!G17 -> 0 | L26: =$D$26*'Revenue %s'!H17 -> 0 | M26: =$D$26*'Revenue %s'!I17 -> 433818.46 | N26: =$D$26*'Revenue %s'!J17 -> 350554.73 | O26: =$D$26*'Revenue %s'!K17 -> 40626.812 | P26: =$D$26*'Revenue %s'!L17 -> 0 | Q26: =$D$26*'Revenue %s'!M17 -> 0 | ... T26: =$D$26*'Revenue %s'!P17 -> 0 | AH26: =SUM(J26:P26) -> 825000
C27: Nevada State Parks | D27: 85000 | J27: =$D$27*'Revenue %s'!F18 -> 0 | K27: =$D$27*'Revenue %s'!G18 -> 0 | L27: =$D$27*'Revenue %s'!H18 -> 85000 | M27: =$D$27*'Revenue %s'!I18 -> 0 | N27: =$D$27*'Revenue %s'!J18 -> 0 | O27: =$D$27*'Revenue %s'!K18 -> 0 | P27: =$D$27*'Revenue %s'!L18 -> 0 | Q27: =$D$27*'Revenue %s'!M18 -> 0 | ... T27: =$D$27*'Revenue %s'!P18 -> 0 | AH27: =SUM(J27:O27) -> 85000
C28: Tahoe Douglas Visitor Authority | D28: 120000 | J28: =$D$27*'Revenue %s'!F19 -> 0 | K28: =$D$27*'Revenue %s'!G19 -> 0 | L28: =$D$27*'Revenue %s'!H19 -> 0 | M28: =$D$27*'Revenue %s'!I19 -> 0 | N28: =$D$27*'Revenue %s'!J19 -> 0 | O28: =$D$27*'Revenue %s'!K19 -> 85000 | P28: =$D$27*'Revenue %s'!L19 -> 0 | Q28: =$D$27*'Revenue %s'!M19 -> 0 | ... T28: =$D$27*'Revenue %s'!P19 -> 0 | AH28: =SUM(J28:O28) -> 85000
C29: Interest Revenue | D29: 18000 | J29: =$D$29*'Revenue %s'!F20 -> 1135.3074 | K29: =$D$29*'Revenue %s'!G20 -> 2224.6052 | L29: =$D$29*'Revenue %s'!H20 -> 601.70686 | M29: =$D$29*'Revenue %s'!I20 -> 4751.6025 | N29: =$D$29*'Revenue %s'!J20 -> 4697.9246 | O29: =$D$29*'Revenue %s'!K20 -> 84.25006 | P29: =$D$29*'Revenue %s'!L20 -> 2738.8837 | Q29: =$D$29*'Revenue %s'!M20 -> 0 | ... T29: =$D$29*'Revenue %s'!P20 -> 0 | AH29: =SUM(J29:O29) -> 13495.397
C30: Keep Tahoe Blue (Emerald Bay Shuttle) | D30: 8322 | J30: =$D$30*'Revenue %s'!F21 -> 0 | K30: =$D$30*'Revenue %s'!G21 -> 0 | L30: =$D$30*'Revenue %s'!H21 -> 0 | M30: =$D$30*'Revenue %s'!I21 -> 0 | N30: =$D$30*'Revenue %s'!J21 -> 0 | O30: =$D$30*'Revenue %s'!K21 -> 0 | P30: =$D$30*'Revenue %s'!L21 -> 0 | Q30: =$D$30*'Revenue %s'!M21 -> 8322 | ... T30: =$D$30*'Revenue %s'!P21 -> 0 | AH30: =SUM(J30:O30) -> 0 | AJ30: Emerald Bay has already changed
C31: Carbon Reduction Program (Emerald Bay Shuttle) | D31: 271910 | J31: =$D$31*'Revenue %s'!F22 -> 0 | K31: =$D$31*'Revenue %s'!G22 -> 0 | L31: =$D$31*'Revenue %s'!H22 -> 0 | M31: =$D$31*'Revenue %s'!I22 -> 0 | N31: =$D$31*'Revenue %s'!J22 -> 0 | O31: =$D$31*'Revenue %s'!K22 -> 0 | P31: =$D$31*'Revenue %s'!L22 -> 0 | Q31: =$D$31*'Revenue %s'!M22 -> 271910 | ... T31: =$D$31*'Revenue %s'!P22 -> 0 | AH31: =SUM(J31:O31) -> 0
C32: El Dorado County (Emerald Bay Shuttle) | D32: 331240 | J32: =$D$32*'Revenue %s'!F23 -> 0 | K32: =$D$32*'Revenue %s'!G23 -> 0 | L32: =$D$32*'Revenue %s'!H23 -> 0 | M32: =$D$32*'Revenue %s'!I23 -> 0 | N32: =$D$32*'Revenue %s'!J23 -> 0 | O32: =$D$32*'Revenue %s'!K23 -> 0 | P32: =$D$32*'Revenue %s'!L23 -> 0 | Q32: =$D$32*'Revenue %s'!M23 -> 331240 | ... T32: =$D$32*'Revenue %s'!P23 -> 0 | AH32: =SUM(J32:O32) -> 0
C33: Placer County (Emerald Bay Shuttle) | D33: 8324 | J33: =$D$33*'Revenue %s'!F24 -> 0 | K33: =$D$33*'Revenue %s'!G24 -> 0 | L33: =$D$33*'Revenue %s'!H24 -> 0 | M33: =$D$33*'Revenue %s'!I24 -> 0 | N33: =$D$33*'Revenue %s'!J24 -> 0 | O33: =$D$33*'Revenue %s'!K24 -> 0 | P33: =$D$33*'Revenue %s'!L24 -> 0 | Q33: =$D$33*'Revenue %s'!M24 -> 8324 | ... T33: =$D$33*'Revenue %s'!P24 -> 0 | AH33: =SUM(J33:O33) -> 0
C34: Washoe RTC | E34: 296055 | G34: 12500
C35: Travel North Tahoe Nevada | G35: 26417
C36: Reno Tahoe Airport Authority | G36: 12500
C37: Placer County (Transient Occupancy Tax) | E37: =2900000+150000+1874954+277500+144946 -> 5347400 | G37: =L85+L86+L87+L88 -> 580806
C38: Town of Truckee | E38: 230478 | G38: 15500
C39: Visit Truckee Tahoe | G39: 2932
C40: North Shore Resort Partners | E40: 47900
C41: North Shore Local Partners (Free Fares) | E41: 139000
C42: Martis Zones of Benefit | E42: 0
C43: Douglas County | F43: 750000 | R43: =$F$43*'Revenue %s'!N34 -> 375000 | S43: =$F$43*'Revenue %s'!O34 -> 187500 | T43: =$F$43*'Revenue %s'!P34 -> 187500
C44: City of South Lake Tahoe | F44: 1100000 | R44: =$F$44*'Revenue %s'!N35 -> 550000 | S44: =$F$44*'Revenue %s'!O35 -> 275000 | T44: =$F$44*'Revenue %s'!P35 -> 275000
C45: Tahoe Blue Events Center Mitigation Fee | F45: 687724 | R45: =$F$45*'Revenue %s'!N36 -> 343862 | S45: =$F$45*'Revenue %s'!O36 -> 171931 | T45: =$F$45*'Revenue %s'!P36 -> 171931
C46: South Lake Tahoe Tourism Improvement District (SLTTID) | F46: 0 | R46: =$F$46*'Revenue %s'!N37 -> 0 | S46: =$F$46*'Revenue %s'!O37 -> 0 | T46: =$F$46*'Revenue %s'!P37 -> 0 | AH46: =SUM(J46:P46) -> 0 | AI46: Can be used to cover 50% of operating costs (urban rtes), 80% ADA.
C47: Heavenly | F47: 0 | R47: =$F$47*'Revenue %s'!N38 -> 0 | S47: =$F$47*'Revenue %s'!O38 -> 0 | T47: =$F$47*'Revenue %s'!P38 -> 0 | AH47: =SUM(J47:O47) -> 0 | AI47: Can be used to cover 50% of operating costs (rural rtes)
C48: Ceasars Entertainment | F48: 0 | R48: =$F$48*'Revenue %s'!N39 -> 0 | S48: =$F$48*'Revenue %s'!O39 -> 0 | T48: =$F$48*'Revenue %s'!P39 -> 0 | AH48: =SUM(J48:O48) -> 0 | AI48: ADA
C49: Roundhill Pines Resort | F49: 0 | R49: =$F$49*'Revenue %s'!N40 -> 0 | S49: =$F$49*'Revenue %s'!O40 -> 0 | T49: =$F$49*'Revenue %s'!P40 -> 0 | AH49: =SUM(J49:O49) -> 0 | AI49: TTD: 33% to rural, 66% to urban
C50: Advance Learning | F50: 0 | R50: =$F$50*'Revenue %s'!N41 -> 0 | S50: =$F$50*'Revenue %s'!O41 -> 0 | T50: =$F$50*'Revenue %s'!P41 -> 0 | AH50: =SUM(J50:O50) -> 0 | AI50: --
C51: Lake Tahoe Visitor's Authority | F51: 0 | R51: =$F$51*'Revenue %s'!N42 -> 0 | S51: =$F$51*'Revenue %s'!O42 -> 0 | T51: =$F$51*'Revenue %s'!P42 -> 0 | AH51: =SUM(J51:O51) -> 0
C52: Lake Tahoe Community College (LTCC) | F52: 0 | R52: =$F$52*'Revenue %s'!N43 -> 0 | S52: =$F$52*'Revenue %s'!O43 -> 0 | T52: =$F$52*'Revenue %s'!P43 -> 0 | AH52: =SUM(J52:O52) -> 0
AH53: =SUM(J53:O53) -> 0
AH54: =SUM(J54:O54) -> 0
AH55: =SUM(J55:O55) -> 0
AH56: =SUM(J56:O56) -> 0
AH57: =SUM(J57:O57) -> 0 | AJ57: Emerald Bay has already changed
AH58: =SUM(J58:O58) -> 0
AH59: =SUM(J59:O59) -> 0
AH60: =SUM(J60:O60) -> 0
C62: Total | D62: =SUM(D46:D60) -> 0 | I62: T Revenue | J62: =SUM(J12:J60) -> 611234.17 | K62: =SUM(K12:K60) -> 1190702.7 | L62: =SUM(L12:L60) -> 151983.91 | M62: =SUM(M12:M60) -> 1814699.3 | N62: =SUM(N12:N60) -> 1129302.5 | O62: =SUM(O12:O60) -> 135365.55 | P62: =SUM(P12:P60) -> 918751.09 | Q62: =SUM(Q12:Q60) -> 619796 | ... AG62: =SUM(AG12:AG60) -> 0
I63: Difference | J63: =J62-J10 -> 128163.31
C64: CMAQ grants coming
C65: Receive TDA end of Feb/beginning of March, so put FTA forward first
C66: FTA match with Toll credits in past, this made an impact, now need to provide more match
C67: Will start assigning TDA as match earlier. Fluid, need to look at 5 year term | U67: =+Q19+Q21 -> 0
C68: TDA has to be used on Nevada routes | AH68: FTA specifically says that where there are multiple recipients within a UZA, the MPO and designated recipients should determine the subarea allocation through a "fair and rational" process based on local needs.
C69: If saving a $1 on 5311 side, not really saving a$1 on 5307 side. | J69: Fiscal Cliff in 31 | U69: Fiscal Cliff in 31
C70: Historically had more Nevada 5311 than CA | J70: Cost Allocated by route based on % of miles per month | U70: Cost Allocated by route based on % of miles per month
C71: Now more people wanting NDOT 5311 | J71: Other than pilot funding, do not isolate costs. | U71: Other than pilot funding, do not isolate costs.
C72: Used to have funding from Vail and the Ridge | J72: Utlitiy costs pooled for entire system, this has been agreed to by partners | U72: Utlitiy costs pooled for entire system, this has been agreed to by partners
C73: Then got 5307 | J73: NDOT match - 20% match for admin and 40% for operating, 5% capitcal costs | U73: NDOT match - 20% match for admin and 40% for operating, 5% capitcal costs
C74: Decided (collectively) that who receives benefit of route gets urban/rural benefit
C75: If loose TDA, then money has to come from Douglas or other
C76: LCTOP alternates with TART every other year; based on ridership
C77: Don't see Douglas County, El Dorado County, SLT, Carson MPO, DART, get buy in from other authorities
C78: Hard to bridge a couple months of funding
C79: Matters when expenses hit
C81: Same level of detail for SSTMA, Placer
K84: TNTTMA | L84: TOT | Q84: Private
C85: For lake Link | K85: NLTE | L85: 162594
D86: Revenue sources and if any restrictions for five years | K86: Sugar Bowl | L86: 172106
D87: Expenditures by zone | K87: Northstar | L87: 7426 | Q87: 3899
D88: Douglas County and SLT are only 2 written contract | K88: Palisades | L88: 238680 | M88: =SUM(L86:L88) -> 418212 | Q88: 119000
D89: Tahoe Blue
K90: MRTW Contract | Q90: 488320
C91: TART/TART Connect | D91: Per Route costs
D92: Per Route revenues/matching | K92: NLTE | L92: =L85+G34+G35+G36+G38+G39 -> 232443

Sheet TTD FY27 budget

Sheet TART Rev
J1: REVENUE | K1: REVENUE | M1: % | V1: FY 19/20 | W1: FY20/21 | X1: FY 21/22 | Y1: FY 22/23 | Z1: FY 23/24
A2: Ledger | B2: 19 20 B | C2: 20 21 B | D2: 21 22 B | E2: 22 23 B | F2: 23-24 B | G2: 24-25 B | H2: 25-26 B | I2: 26-27B | J2: Funding Source | K2: Explanation | L2: Change | M2: Change | O2: 45010 - Free Fare Contributions | R2: 45010 - Resort Winter Contributions | U2: 49060 - TOT Funds for Operating Costs | W2: 1.025 | Y2: 1.035 | Z2: 1.035
A3: 40150 | B3: 771000 | C3: 836900 | D3: 675900 | E3: 848448 | F3: 672403 | G3: 645022 | H3: 623819 | I3: 913053 | J3: TRPA LTF | K3: Estimated based on 23-24 allocation | L3: =D3-C3 -> -161000 | M3: =L3/C3 -> -0.19237663 | O3: Airport District | P3: 0 | R3: Homewood | S3: 2100 | U3: Base Transit Service Operated by TART | V3: 200000 | W3: =V3 -> 200000 | X3: 150000 | Y3: 150000 | Z3: 150000
A4: 40150 | B4: 1125000 | C4: 1300000 | D4: 1125000 | E4: 1300000 | F4: 1767187 | G4: 1305180 | H4: 1400000 | I4: 1675000 | J4: PCTPA LTF West Slope Contr. Hwy 89/267 | K4: Estimated based on 23-24 allocation | L4: =D4-C4 -> -175000 | M4: =L4/C4 -> -0.13461538 | O4: Palisades | P4: 61500 | R4: Village @ Palisades | S4: 3600 | U4: Summer Transit Services Operated by TART * | V4: 193500 | W4: =ROUND(V4*W$2,-2) -> 198300 | X4: 204700 | Y4: =ROUND(X4*Y2, -2) -> 211900 | Z4: =ROUND(Y4*Z2, -2) -> 219300
A5: 42010 | I5: 0 | J5: Interest Revenue | L5: =D5-C5 -> 0 | M5: 0 | O5: Village @ Palisades | P5: 12500 | R5: Northstar | S5: 30100 | U5: Shoulder Season Nite Rider | V5: 239500 | W5: =ROUND(V5*W$2,-2) -> 245500 | X5: 253500 | Y5: =ROUND(X5*Y2, -2) -> 262400 | Z5: =ROUND(Y5*Z2, -2) -> 271600
A6: 43210 | C6: 142000 | D6: 546000 | G6: 4900000 | I6: 0 | J6: FTA Grant - Construction | L6: =D6-C6 -> 404000 | M6: =L6/C6 -> 2.8450704 | O6: Everline | P6: 2300 | R6: Everline | S6: 10000 | U6: Winter Service 30 minutes | V6: 101400 | W6: =ROUND(V6*W$2,-2) -> 103900 | X6: 107300 | Y6: =ROUND(X6*Y2, -2) -> 111100 | Z6: =ROUND(Y6*Z2, -2) -> 115000
A7: 43210 | G7: 450000 | H7: 450000 | I7: =450000-160000 -> 290000 | J7: FTA 5311 | L7: =D7-C7 -> 0 | M7: 0 | O7: Northstar | P7: 65000 | R7: Palisades | S7: 10600 | U7: Northstar Added 6AM run | V7: 10200 | W7: =ROUND(V7*W$2,-2) -> 10500 | X7: 10800 | Y7: =ROUND(X7*Y2, -2) -> 11200 | Z7: =ROUND(Y7*Z2, -2) -> 11600
G8: 157836 | I8: 189578 | J8: FTA 5339 | K8: ADA Capital
A9: 43220 | B9: 355000 | C9: 422000 | D9: 422000 | E9: 422000 | I9: 0 | J9: Fed Op Assist - 5311 TRPA | K9: Estimated based on 22-23 allocation | L9: =D9-C9 -> 0 | M9: =L9/C9 -> 0 | O9: Homewood | P9: 11900 | R9: Alpine Meadows | S9: 3600 | U9: Squaw AM & PM Peak Service | V9: 37100 | W9: =ROUND(V9*W$2,-2) -> 38000 | X9: 39200 | Y9: =ROUND(X9*Y2, -2) -> 40600 | Z9: =ROUND(Y9*Z2, -2) -> 42000
A10: 43220 | B10: 960000 | C10: 1037300 | D10: 1169600 | E10: 865418 | F10: 865500 | G10: 1543653 | H10: 2500000 | I10: 2660000 | J10: FTA 5307 TRPA UZA Funds | K10: Estimated based on 22-23 allocation | L10: =D10-C10 -> 132300 | M10: =L10/C10 -> 0.12754266 | U10: Winter Night Service | V10: 392500 | W10: =ROUND(V10*W$2,-2) -> 402300 | X10: 415400 | Y10: =ROUND(X10*Y2, -2) -> 429900 | Z10: =ROUND(Y10*Z2, -2) -> 444900
A11: 43220 | D11: 232300 | J11: CARES Act Operating Funding 5307 | L11: =D11-C11 -> 232300 | M11: =L11/D11 -> 1 | O11: Welk Resorts | U11: Summer Night Service | V11: 207800 | W11: =ROUND(V11*W$2,-2) -> 213000 | X11: 219900 | Y11: =ROUND(X11*Y2, -2) -> 227600 | Z11: =ROUND(Y11*Z2, -2) -> 235600
A12: 43210 | C12: 729300 | D12: 405800 | J12: CARES Act Capital Funding 5307 | K12: CARES Funding - Capital Purchase | L12: =D12-C12 -> -323500 | M12: =L12/C12 -> -0.44357603 | O12: Town of Truckee | P12: 21000 | Q12: Included in ops cost | U12: Northstar AM & PM Peak Service | V12: 39400 | W12: =ROUND(V12*W$2,-2) -> 40400 | X12: 41700 | Y12: =ROUND(X12*Y2, -2) -> 43200 | Z12: =ROUND(Y12*Z2, -2) -> 44700
A13: 43220 | C13: 340000 | D13: 477800 | J13: CARES Act Operating Funding 5311 | K13: Round 2 - 5311 CARES Funding allocation 477,471 | L13: =D13-C13 -> 137800 | M13: =L13/C13 -> 0.40529412 | O13: Other | U13: Year-Round 30 Minute Service | V13: 200800 | W13: =ROUND(V13*W$2,-2) -> 205800 | X13: 212500 | Y13: =ROUND(X13*Y2, -2) -> 219900 | Z13: =ROUND(Y13*Z2, -2) -> 227600
A14: 45010 | B14: 572700 | C14: 572700 | D14: 459800 | E14: =485044+185000 -> 670044 | F14: 585000 | G14: =610118+500000 -> 1110118 | H14: 1110118 | I14: =510729+308898 -> 819627 | J14: STA | K14: TRPA $610,118 PCTPA $500000 | L14: =D14-C14 -> -112900 | M14: =L14/C14 -> -0.19713637 | O14: TOT | P14: 277500 | U14: Winter 30 Minute Service TC & Squaw | V14: 81700 | W14: =ROUND(V14*W$2,-2) -> 83700 | X14: 86400 | Y14: =ROUND(X14*Y2, -2) -> 89400 | Z14: =ROUND(Y14*Z2, -2) -> 92500
A15: 45010 | C15: 223000 | D15: 223000 | E15: =185329+79891 -> 265220 | F15: 81000 | G15: 79511 | H15: 102929 | I15: 100084 | J15: SB1 - State of Good Repair | K15: Use 26-27 for PM | L15: =D15-C15 -> 0 | M15: =L15/C15 -> 0 | U15: Winter 30 Minute Service Cr.Bay & Northstar | V15: 115500 | W15: =ROUND(V15*W$2,-2) -> 118400 | X15: 122200 | Y15: =ROUND(X15*Y2, -2) -> 126500 | Z15: =ROUND(Y15*Z2, -2) -> 130900
A16: 45010 | C16: 0 | D16: 0 | J16: LCTOP | L16: =D16-C16 -> 0 | M16: 0 | U16: Fill Time Gaps between Afternoon & Evening Svc | V16: 11000 | W16: =ROUND(V16*W$2,-2) -> 11300 | X16: 11700 | Y16: =ROUND(X16*Y2, -2) -> 12100 | Z16: =ROUND(Y16*Z2, -2) -> 12500
A17: 45010 | J17: Proposition 1B | L17: =D17-C17 -> 0 | M17: 0 | U17: Free to the Rider Fare Reimburement | X17: 250000 | Y17: 230000 | Z17: 230000
A18: 45010 | H18: 3966642 | I18: =891367+3926487.44 -> 4817854.4 | J18: Other State Funding | K18: SB125 buses $891,367 (contingency not in PO) SB125 Tech & EV Improvements $3,926,217.44 | L18: =D18-C18 -> 0 | M18: 0 | U18: Other - Town of Truckee Night Service | V18: 68706.4 | W18: 118146.4 | X18: 122000 | Y18: =ROUND(X18*Y2, -2) -> 126300 | Z18: =ROUND(Y18*Z2, -2) -> 130700
A19: 45010 | B19: 214800 | C19: 189300 | D19: 0 | E19: =233079 -> 233079 | F19: =262855 -> 262855 | G19: =284793 -> 284793 | H19: 288746 | I19: 296055 | J19: RTC - Incline Village Fixed Route | K19: RTC Contribution to TART & TART Connect Connect Est @ $1.5 million | L19: =D19-C19 -> -189300 | M19: =L19/C19 -> -1 | U19: TOTAL | V19: =SUM(V4:V18) -> 1699106.4 | W19: =SUM(W4:W18) -> 1789246.4 | X19: =SUM(X3:X18) -> 2247300 | Y19: =SUM(Y3:Y18) -> 2292100 | Z19: =SUM(Z3:Z18) -> 2358900
A20: 45010 | B20: 60000 | C20: =S22 -> 60000 | D20: 60000 | E20: 60000 | F20: 60000 | G20: 60000 | H20: 60000 | I20: 47900 | J20: Resort Partner (Previous TMA Pass-thru) | K20: Contributions to Winter Ops Cost | L20: =D20-C20 -> 0 | M20: =L20/C20 -> 0
A21: 45010 | B21: 0 | D21: 0 | E21: 837572 | F21: 1000000 | G21: 1500000 | H21: 1296823 | I21: 1300000 | J21: Incline/Crystal Bay Funding - TART Connect | K21: Contributions to fund free fares | L21: =D21-C21 -> 0 | M21: =L21/C21 -> #DIV/0!
A22: 45010 | B22: 182300 | C22: 181200 | D22: 182300 | E22: 182300 | F22: 182300 | G22: 186049 | H22: =193402+63000 -> 256402 | I22: 230478 | J22: Truckee Contract | K22: Truckee contribution for hwy 89 & 267 (Add $63K for 267 in 25-26) | L22: =D22-C22 -> 1100 | M22: =L22/C22 -> 0.0060706402 | O22: TOTAL | P22: =SUM(P3:P21) -> 451700 | R22: TOTAL | S22: =SUM(S3:S21) -> 60000
A23: 45010 | B23: 62000 | C23: 63000 | D23: 62300 | E23: 62300 | F23: 62300 | G23: 63000 | H23: 0 | I23: 0 | J23: Tahoe Truckee Airport Distr. | K23: Hwy 267 Contribution | L23: =D23-C23 -> -700 | M23: =L23/C23 -> -0.011111111
A24: 45010 | B24: 1000 | C24: 1000 | D24: 0 | J24: RTC ADA Contribution | L24: =D24-C24 -> -1000 | M24: =L24/C24 -> -1 | O24: Revised Total | P24: =P4+P5+P7+P14 -> 416500 | U24: Add in Free Fares | W24: 172900
A25: 46320 | B25: =475700-B30 -> 268200 | C25: =523000-D30 -> 294800 | D25: =523000-D30 -> 294800 | E25: 287200 | F25: 287200 | G25: =425887.21-250000 -> 175887.21 | H25: 148500 | I25: 139000 | J25: Farebox/Free Fare Contributions | K25: Replace by Free Fare Contributions | L25: =D25-C25 -> 0 | M25: =L25/C25 -> 0 | U25: Grand Total TOT Funding | W25: =W22+W24 -> 172900
A26: 49060 | J26: Other General Reimbursement | L26: =D26-C26 -> 0 | M26: 0
A27: 49060 | G27: 2800000 | H27: 2899000 | I27: 2900000 | J27: TART Connect TOT Funding | L27: =D27-C27 -> 0 | M27: 0 | U27: * Note
A28: 49060 | B28: 200000 | C28: =V3 -> 200000 | D28: 200000 | E28: 150000 | F28: 150000 | G28: 150000 | H28: 150000 | I28: 150000 | J28: TOT for Base Service | K28: To cover TART Shortfall | L28: =D28-C28 -> 0 | M28: =L28/C28 -> 0 | U28: Summer Transit Serivce By Route | V28: Daily VRH | W28: % VRH
A29: 49060 | B29: 1630400 | C29: 1671100 | D29: 1721200 | E29: 1785800 | F29: 1848200 | G29: 1912900 | H29: 1879200 | I29: 1874954 | J29: TOT Funds for Transit Programs | K29: Added TART Services | L29: =D29-C29 -> 50100 | M29: =L29/C29 -> 0.029980253 | U29: 30 Minute Northshore | V29: 10.5 | W29: =V29/V$34 -> 0.32792005
A30: 49060 | B30: 207500 | C30: 172900 | D30: 228200 | E30: 230000 | F30: 230000 | G30: 250000 | H30: 277500 | I30: 277500 | J30: TOT Funds for Free Fares | K30: Contribution to fund free fares | L30: =D30-C30 -> 55300 | M30: =L30/C30 -> 0.31983806 | U30: Hwy 89 Route @ 11.58 hours per day | V30: 11.58 | W30: =V30/V$34 -> 0.36164897
A31: 49060 | B31: 68706 | C31: 118146.4 | D31: 121700 | E31: 126300 | F31: 130700 | G31: 135300 | H31: 140700 | I31: 144946 | J31: TOT Funds for Truckee Night Service & Fares
A32: 49060 | C32: 210000 | J32: Tahoe Traffic Mitigation Fees | K32: Traffic mitigation fees | L32: =D32-C32 -> -210000 | M32: =L32/C32 -> -1 | U32: Hwy 267 Route @ 8.82 hours per day | V32: 8.82 | W32: =V32/V$34 -> 0.27545284
A33: 49080 | B33: 50000 | C33: 50000 | D33: 50000 | E33: 50000 | F33: 50000 | G33: 50000 | H33: 50000 | I33: 0 | J33: Operating Transfers In | K33: Martis ZOB revenue | L33: =D33-C33 -> 0 | M33: =L33/C33 -> 0 | U33: Added 6:05pm SV to Hyatt 7:12pm run | V33: 1.12 | W33: =V33/V$34 -> 0.034978139
A34: TOTAL | B34: =SUM(B3:B33) -> 6728606 | C34: =SUM(C3:C33) -> 8814646.4 | D34: =SUM(D3:D33) -> 8657700 | E34: =SUM(E3:E33) -> 8375681 | F34: =SUM(F3:F33) -> 8234645 | G34: =SUM(G3:G33) -> 17759249 | H34: =SUM(H3:H33) -> 17600379 | I34: =SUM(I3:I32) -> 18826029 | L34: =C34-B34 -> 2086040.4 | M34: =L34/B34 -> 0.31002564 | U34: TOTAL | V34: =SUM(V29:V33) -> 32.02
B35: Operating | C35: =C34-C32-C15-C6 -> 8239646.4 | D35: =D34-D15-D6 -> 7888700 | E35: =E34-E15-E6 -> 8110461 | F35: =F34-F15 -> 8153645 | G35: =G34-G15-G8-G6 -> 12621902 | H35: =H3+H4+H7+H10+H14+H15+H19+H20+985285+H25+H27+H28+H29+H30+H31 -> 13015797 | U35: Using Summer Stats 15.xlsx as basis of Summer Service Costs
C36: Operating | D36: Operating | E36: Operating | F36: Operating | G36: Operating | H36: Operating
H37: =H35-H27-985285 -> 9131512 | J37: =SUM(I27:I31) -> 5347400
H38: Operating - fixed route only | J38: =I27/$J$37 -> 0.54231963
D39: Operating | E39: Operating | J39: =I28/$J$37 -> 0.028051015
A40: Placer County Local Transp Funds | J40: =I29/$J$37 -> 0.35062909
A41: Placer County T.O.T. | J41: =I30/$J$37 -> 0.051894379
A42: Federal Transit Administration | J42: =I31/$J$37 -> 0.027105883
A43: State Transit Assistance
A44: SB1 State of Good Repair
A45: Washoe RTC
A46: Town of Truckee
A47: Truckee Tahoe Airport District
A48: Developer Zone of Benefit
A49: Squaw Valley
A50: Northstar
A51: Resort at Squaw Creek
A52: Homewood
A53: Fare Revenue Contributions - Private
A54: Fare Revenue Contributions - TOT
H89: -1890557

Sheet TNTTMA $
C4: TNT TMA
C6: NLTE | G6: Administration | M6: Regional Transit Marketing | S6: Summary
E7: 25-26 | F7: 2026-27 B | I7: 24-25 Actual | J7: 25-26 B | K7: 26-27 B | O7: 24-25 Actual | P7: 25-26 B | Q7: 26-27 B | T7: 24-25 Actual | U7: 25-26 B | V7: =Q7 -> 26-27 B
B8: Revenue | C8: Source | E8: Amount | G8: Revenue | H8: Source | I8: Amount | M8: Revenue | N8: Source | O8: Amount | T8: Amount
C9: TOT | E9: 152612 | F9: 162595 | H9: Membership | I9: 105495 | J9: 120694 | K9: 125267 | N9: Placer County (TOT) | O9: 59375 | P9: 174720 | Q9: 181709 | S9: Placer County (Transient Occupancy Tax) | T9: =SUM(D9,D29,I29,O9) -> 484909 | U9: =SUM(E9,E29,J29,P9) -> 676730 | V9: =SUM(F9,F29,K29,Q9) -> 1290060
C10: Travel North Tahoe NV | E10: 30390 | F10: 26421 | H10: Program Management | I10: 92534 | J10: 95650 | K10: 111252 | N10: Town of Truckee | O10: 10988 | P10: 21264 | Q10: 22115 | S10: North Tahoe Community Alliance | T10: =SUM(D30) -> 50471 | U10: =SUM(E30) -> 487173 | V10: =SUM(F30) -> 0
C11: Washoe County | E11: 25000 | F11: 12500 | H11: Marketing Management | I11: 78406 | J11: 81543 | K11: 84808 | N11: RCMF | O11: 20000 | P11: 20000 | Q11: 20000 | S11: Washoe County | T11: =SUM(E11) -> 25000 | U11: =SUM(E11) -> 25000 | V11: =SUM(F11) -> 12500
C12: Reno-Tahoe Airport Authority | F12: 12500 | H12: Other | I12: 6132 | J12: 5832 | K12: 4032 | N12: TNTNV | O12: 20000 | P12: 10000 | S12: Nevada County | T12: =D31 -> 0 | U12: =E31 -> 0 | V12: =F31 -> 16339
C13: Town of Truckee | E13: 15500 | F13: 15500 | S13: Town of Truckee | T13: =SUM(E13,O10) -> 26488 | U13: =SUM(E13,P10) -> 36764 | V13: =SUM(F13,Q10) -> 37615
C14: Additional Truckee | F14: 2927 | S14: Other Truckee | U14: =E14 -> 0 | V14: =F14 -> 2927
C15: Farebox | E15: 445263 | F15: 377656 | S15: Reno-Tahoe Airport Authority | T15: =SUM(E12) -> 0 | U15: =SUM(E12) -> 0 | V15: =SUM(F12) -> 12500
C16: Reserve | F16: 240000 | S16: Northstar Resort | T16: =D32 -> 2652 | U16: =E32 -> 21413 | V16: =F32 -> 3862
B17: Expenses | G17: Expenses | M17: Expenses | S17: Palisades Tahoe | T17: =D33 -> 119014 | U17: =E33 -> 119304 | V17: =F33 -> 124076
C18: Operations Contract | E18: 266331 | F18: 596396 | H18: Personnel | I18: 179385 | J18: 220447 | K18: 272563 | N18: Marketing Management | O18: 20510 | P18: 70186 | Q18: 72997 | S18: Travel North Tahoe Nevada | T18: =SUM(E10,O12) -> 50390 | U18: =SUM(E10,P12) -> 40390 | V18: =SUM(F10,Q12) -> 26421
C19: Admin/Fixed | E19: =10529+66600+1914 -> 79043 | F19: =34253+25000+11811+25800+1000 -> 97864 | H19: Services and Supplies | I19: 67094 | J19: 55842 | K19: 49307 | N19: Marketing Activities | O19: =52480+17277+25049+674+625+5550 -> 101655 | P19: =65405+26005+50888+8500+5000 -> 155798 | Q19: =105531+12818+23637+8840 -> 150826 | S19: RCMF | T19: =O11 -> 20000 | U19: =P11 -> 20000 | V19: =Q11 -> 20000
S20: Fare Revenue (NLTE) | T20: =E15 -> 445263 | U20: =E15 -> 445263 | V20: =F15 -> 377656
C21: Total Revenue | E21: =SUM(E9:E15) -> 668765 | F21: =SUM(F9:F16) -> 850099 | H21: Total Revenue | I21: =SUM(I9:I15) -> 282567 | J21: =SUM(J9:J15) -> 303719 | K21: =SUM(K9:K15) -> 325359 | N21: Total Revenue | O21: =SUM(O9:O15) -> 110363 | P21: =SUM(P9:P15) -> 225984 | Q21: =SUM(Q9:Q15) -> 223824 | S21: Membership | T21: =I9 -> 105495 | U21: =J9 -> 120694 | V21: =K9 -> 125267
C22: Total Expenses | E22: =SUM(E18:E19) -> 345374 | F22: =SUM(F18:F19) -> 694260 | H22: Total Expenses | I22: =SUM(I18:I19) -> 246479 | J22: =SUM(J18:J19) -> 276289 | K22: =SUM(K18:K19) -> 321870 | N22: Total Expenses | O22: =SUM(O18:O19) -> 122165 | P22: =SUM(P18:P19) -> 225984 | Q22: =SUM(Q18:Q19) -> 223823 | S22: Management Revenues | T22: =SUM(I10:I12) -> 177072 | U22: =SUM(J10:J12) -> 183025 | V22: =SUM(K10:K12) -> 200092
T23: =SUM(T9:T22) -> 1506754 | U23: =SUM(U9:U22) -> 2175756 | V23: =SUM(V9:V22) -> 2249315
V25: =SUM(F21,F42,K21,K42,Q21) -> 2489315
C26: Park and Ride Shuttles | H26: Van Pool | V26: =SUM(F22,F43,K22,K43,Q22) -> 2329986
D27: 24-25 Actual | E27: 25-26 B | F27: 26-27 B | I27: 24-25 Actual | J27: 25-26 B | K27: 26-27 B
B28: Revenue | C28: Source | D28: Amount | G28: Revenue | H28: Source | I28: Amount
C29: Placer County (TOT) | D29: 267385 | E29: =90762+12118+25700 -> 128580 | F29: 749956 | H29: Placer County (TOT) | I29: 158149 | J29: 220818 | K29: 195800
C30: NTCA | D30: 50471 | E30: =431733+55440 -> 487173
C31: Nevada County | F31: 16339
C32: Northstar | D32: 2652 | E32: =3713+17700 -> 21413 | F32: 3862
C33: Palisades | D33: 119014 | E33: 119304 | F33: 124076
B35: Expenses | G35: Expenses
C36: Operations | D36: =6915+215014+92000+6062 -> 319991 | E36: =8000+357984+11140+157106 -> 534230 | F36: =7130+372303+11586+163390+94092+12320+18700 -> 679521 | H36: Operations Contract | I36: 140800 | J36: 192000 | K36: 177600
C37: TNT TMA Admin | D37: 48078 | E37: 52715 | F37: 66799 | H37: Admin | I37: =1125+12788 -> 13913 | J37: 13900 | K37: 10200
C38: Facility Attendent, Rental, Snow, Toilet | D38: =4188+4800+48300+7490+2587+1216+1216 -> 69797 | E38: =12000+5000+63406+7000+7000+35400 -> 129806 | F38: =8000+5500+69000+7282+4200+2150 -> 96132 | H38: Marketing | I38: 3436 | J38: 14918 | K38: 8000
C39: Marketing | D39: =3183+591+591+591 -> 4956 | E39: =3000+5000+5000+5000+17000+4719 -> 39719 | F39: =3120+6310+6310+6079+3000+16310+2000+8652 -> 51781
C42: Total Revenue | D42: =SUM(D29:D34) -> 439522 | E42: =SUM(E29:E34) -> 756470 | F42: =SUM(F29:F34) -> 894233 | H42: Total Revenue | I42: =SUM(I29:I34) -> 158149 | J42: =SUM(J29:J34) -> 220818 | K42: =SUM(K29:K34) -> 195800
C43: Total Expenses | D43: =SUM(D36:D40) -> 442822 | E43: =SUM(E36:E40) -> 756470 | F43: =SUM(F36:F40) -> 894233 | H43: Total Expenses | I43: =SUM(I36:I39) -> 158149 | J43: =SUM(J36:J39) -> 220818 | K43: =SUM(K36:K39) -> 195800
I45: Per van cost | J45: =J36/16 -> 12000
H46: Expansion of 2 vans/ year | I46: Per year cost | J46: =J45*2 -> 24000

Sheet 25_26 FTA Funding Split (INFO)
C3: Base FTA Funding Split Worksheet
C4: FTA and TDA Funding Split Worksheet
C5: FY 25-26
D10: FEDERAL FUNDING APPORTIONMENT
D12: FTA Sub-Allocation (5307, 5339, 5310)
N15: 1. NTD information
N16: 2. FTA Apportionment table
E17: TTD | F17: Revenue Miles (urban) | I17: Ridership (22/23)
F18: CA | G18: 483367 | I18: TTD | L18: 489907
F19: NV | G19: 319717 | I19: Placer-TART | L19: 613042 | V19: TOT 26 FTA
E20: Placer-TART | F20: CA | G20: 1207385 | L20: =SUM(L18:L19) -> 1102949 | V20: 4730069
F21: NV | G21: 200731
E22: Population (US Census) | I22: FY26 FTA Apportionments | K22: 5307 | L22: 5339 | M22: 5310
E23: TTD | F23: 31420 | G23: 2020 Census | L23: - | M23: -
E24: Placer-TART | F24: 16643 | G24: 2020 Census | I24: UZA Total | K24: 4254369 | L24: 401220 | M24: 74480
E27: Earned Share Factors
F28: Revenue Miles Factor | H28: Population Factor | J28: Ridership Factor | L28: Final
E29: TTD | F29: =G18+G19 -> 803084 | G29: =F29/F31 -> 0.36318922 | H29: =F23 -> 31420 | I29: =H29/H31 -> 0.65372532 | J29: =L18 -> 489907 | K29: =L18/(L18+L19) -> 0.4441792 | L29: =(G29+I29+K29)/3 -> 0.48703124
E30: Placer | F30: =G20+G21 -> 1408116 | G30: =F30/F31 -> 0.63681078 | H30: =F24 -> 16643 | I30: =H30/H31 -> 0.34627468 | J30: =L19 -> 613042 | K30: =L19/(L18+L19) -> 0.5558208 | L30: =(G30+I30+K30)/3 -> 0.51296876
E31: Total | F31: =SUM(F29:F30) -> 2211200 | H31: =SUM(H29:H30) -> 48063 | J31: =SUM(J29:J30) -> 1102949
E33: Allocation Totals by Operator
F34: 5307-Total | G34: 5307-Ops (75%) | H34: 5307-Cap (25%) | I34: 5339 | J34: 5310
E35: TTD | F35: =K24*L29 -> 2072010.6 | G35: =F35*0.75 -> 1554008 | H35: =F35-G35 -> 518002.66 | I35: =L24*L29 -> 195406.68
E36: Placer | F36: =K24*L30 -> 2182358.4 | G36: =F36*0.75 -> 1636768.8 | H36: =F36-G36 -> 545589.59 | I36: =L24*L30 -> 205813.32 | J36: =M24 -> 74480
E37: Total | F37: =SUM(F35:F36) -> 4254369 | G37: =SUM(G35:G36) -> 3190776.8 | H37: =SUM(H35:H36) -> 1063592.2 | I37: =SUM(I35:I36) -> 401220 | J37: =SUM(J35:J36) -> 74480

Sheet Left over from Raymond Model>>>

Sheet SRTP - COMP Factors
A1: DRAFT SRTP used as a source of information
S8: Cost per Hr.
S9: Comps | T9: # of Vehicles
S10: =6131022/28294 -> 216.68983 | T10: 12 | U10: TTD
S11: =6532640/66679 -> 97.971475 | T11: 27 | U11: Vail, Co
S12: =5187138/52795 -> 98.250554 | T12: 37 | U12: Mammoth, Ca
S13: =5603319/57175 -> 98.002956 | T13: 28 | U13: Jackson Hole, Wy
S14: =3558126/40400 -> 88.072426 | T14: 32 | U14: Sun Valley, Id
S15: =4672736/41060 -> 113.80263 | T15: 22 | U15: Steamboat Springs, Co
S16: =11491801/72927 -> 157.57951 | T16: 21 | U16: Park City, Ut
S17: =9677785/55759 -> 173.56454 | T17: 31 | U17: Summit County, Co
S18: =11504947/79931 -> 143.93598 | T18: 22 | U18: Eagle County, Co
S19: =11400000/74899 -> 152.20497 | T19: 33 | U19: Whistler
S21: =46190159/246091 -> 187.69544 | T21: 98 | U21: Aspen
S22: =AVERAGE(S11:S21) -> 131.10805 | T22: Average
R23: 0.34 | S23: =S22*R23 -> 44.576736 | T23: COLA to Tahoe
S24: =SUM(S22:S23) -> 175.68478 | T24: Target Hourly Rate
A25: National and regional comps support the use of $175 per VRH for fixed route services as a target | S25: CA+CO | T25: CO Only
A26: Regional comps suggest a targeted cost of $96-$183 per VRH for fixed route services | S26: =(S11+S12+S13+S15+S16+S17+S18+S19)/8 -> 129.41408 | T26: =(S11+S12+S15+S17+S18+S21)/6 -> 135.8701
R27: 0.289 | S27: =S26*R27 -> 37.400668 | T27: =T26*R27 -> 39.26646
S28: =S26+S27 -> 166.81475 | T28: =T26+T27 -> 175.13656

Sheet Regional COMPs

Sheet TTD 2022 NTD DATA
R22: FY27 | S22: FY28
R23: Vehicle | S23: Vehicle
R24: Revenue | S24: Revenue
R25: Miles | S25: Miles
R28: =(208928/7)*3 -> 89540.571 | S28: =208928/7*4 -> 119387.43 | T28: VRM JPA
R29: =423821-R28 -> 334280.43 | S29: =423821-S28 -> 304433.57 | T29: VRM TTD
R30: =R29+R28 -> 423821 | S30: =S29+S28 -> 423821
R31: 0.75 | S31: 0.75
R32: =(269576-22739)*0.75 -> 185127.75 | T32: Px
R33: =R28/12 -> 7461.7143 | S33: =S28/12 -> 9948.9524 | T33: VRH JPA

Sheet Operating Assistance
B1: FY27 JPA ASSUMPTIONS USING - FTA FY 2020 SECTION 5307 OPERATING ASSISTANCE SPECIAL RULE OPERATOR CAPS FOR URBANIZED AREAS OVER 200,000 IN POPULATION
B2: The total available for operating assistance is based on FY 2018 NTD Data and the Section 5307 funding shown in FTA Apportionment Table #3.
B4: NOTES:
B5: 1. Agencies that are included in this table AND that are eligible for grants under the Section 5307 Urbanized Area Formula Program are eligible to receive operating assistance under the provisions of 5307(a)(2)(A), subject to local allocation, up to the amounts specified in column "H" in Fiscal Year 2020.
B6: 2. Beginning in FY17, agencies may alternatively use program funds up to the amount shown in column "I" for operating assistance under 5307(a)(2)(B), provided that this amount is no greater than 50 or 75 percent of the total amount allocated to them for eligible projects through the local planning process, consistent with the eligible percent factor shown in column "G".
B7: 3. This list does NOT indicate an agency's eligibility or entitlement for funding and does not represent an allocation of funding under the Urbanized Area Formula Program or any other FTA program.
B8: 4. Public agencies that operate fixed route bus service and demand response service, excluding complementary ADA service, are permitted to use this provision in their Urbanized Area Formula Program grants.
B9: 5. Certain transit operators that reported to NTD in a consolidated (multi-agency) report are included based on a vehicle revenue hour share proportional to the number of vehicles reported in maximum service.
B10: 6. Transit operators may receive a cap for each urbanized area in which they operate and report transit service.
B11: 7. Agencies that contract for public transportation service from a private operator, and which otherwise qualify for an operating cap under this provision, have been credited with the vehicle revenue hours reported by the private provider as attributable to the public agency.
B13: Urbanized Area of Service Provided | C13: Public Transportation System Operator | D13: Vehicles Operated in Peak Fixed Route and Demand Response Service | E13: Apportionment to Urbanized Area | F13: Percent of Apportionment Attributable to Operator based on Vehicle Revenue Hours | G13: Eligible Percent Factor Category | H13: FY 2020 Maximum Amount of Section 5307 Operating Assistance Allowed | I13: FY 2020 Maximum Amount of Section 5307 Operating Assistance Allowed 5307(a)(2)(B)
A14: FY18 | B14: Lake Tahoe Region, CA-NV | C14: Placer County Department of Public Works and Facilities | D14: 20 | E14: 2891532 | F14: 0.34623809 | G14: 0.75 | H14: 750868.89 | I14: 825955.78
A15: FY18 | B15: Lake Tahoe Region, CA-NV | C15: Tahoe Transportation District | D15: 29 | E15: 2891532 | F15: 0.65376191 | G15: 0.75 | H15: 1417780.1 | I15: 1559558.1
A16: FY19 | B16: Lake Tahoe Region, CA-NV | C16: Placer County Department of Public Works and Facilities | D16: 21 | E16: 2944091 | F16: 0.39535193 | G16: 0.75 | H16: 872964.04 | I16: 960260.45
A17: FY19 | B17: Lake Tahoe Region, CA-NV | C17: Tahoe Transportation District | D17: 21 | E17: 2944091 | F17: 0.60464807 | G17: 0.75 | H17: 1335104.2 | I17: 1468614.6
A18: FY20 | B18: Lake Tahoe, CA-NV | C18: County of Placer | D18: 21 | E18: 3057188 | F18: 0.40196644 | G18: 0.75 | H18: 921665.22 | I18: 1013831.7
A19: FY20 | B19: Lake Tahoe, CA-NV | C19: Tahoe Transportation District | D19: 19 | E19: 3057188 | F19: 0.59803356 | G19: 0.75 | H19: 1371225.8 | I19: 1508348.4
A20: FY21 | B20: Lake Tahoe Region, CA-NV | C20: County of Placer | D20: 21 | E20: 2964270 | F20: 0.47846577 | G20: 0.75 | H20: 1063726.3 | I20: 1170098.9
A21: FY21 | B21: Lake Tahoe Region, CA-NV | C21: Tahoe Transportation District | D21: 15 | E21: 2964270 | F21: 0.52153423 | G21: 0.75 | H21: 1159476.2 | I21: 1275423.8
A22: FY22 | B22: Lake Tahoe, CA-NV | C22: County of Placer | D22: 21 | E22: 3805886 | F22: 0.47846577 | G22: 0.75 | H22: 1365739.6 | I22: 1502313.6
A23: FY22 | B23: Lake Tahoe, CA-NV | C23: Tahoe Transportation District | D23: 15 | E23: 3805886 | F23: 0.52153423 | G23: 0.75 | H23: 1488674.9 | I23: 1637542.4
A24: FY23 | B24: Lake Tahoe Region, CA-NV | C24: County of Placer | D24: 21 | E24: 3845305 | F24: 0.47846577 | G24: 0.75 | H24: 1379885.1 | I24: 1517873.6
A25: FY23 | B25: Lake Tahoe Region, CA-NV | C25: Tahoe Transportation District | D25: 15 | E25: 3845305 | F25: 0.52153423 | G25: 0.75 | H25: 1504093.6 | I25: 1654503
A26: FY24 | B26: Lake Tahoe Region, CA-NV | C26: County of Placer | D26: 21 | E26: 3902214 | F26: =D26/(D26+D27) -> 0.53846154 | G26: 0.75 | H26: =E26*F26 -> 2101192.2 | I26: 2205277
A27: FY24 | B27: Lake Tahoe Region, CA-NV | C27: Tahoe Transportation District | D27: 18 | E27: 3902214 | F27: =D27/(D26+D27) -> 0.46153846 | G27: 0.75 | H27: =E27*F27 -> 1801021.8 | I27: 1014049
A28: FY27 | B28: Lake Tahoe Region, CA-NV | C28: Tahoe Transportation District | D28: 4 | E28: 2682000 | F28: =D28/(D27+D28) -> 0.18181818 | G28: 0.75 | H28: =E28*F28 -> 487636.36
A29: FY27 | B29: Lake Tahoe Region, CA-NV | C29: JPA | D29: 14 | E29: 2682000 | F29: =D29/(D28+D29) -> 0.77777778 | G29: 0.75 | H29: =E29*F29 -> 2086000

Sheet Avg Pass, Mile Per Hr
B2: Projected Passengers Per Revenue Hour
B3: Micro Meyers | C3: 7
B4: Micro Urban | C4: 7
B5: Fixed Route | C5: 20
B6: Recreation | C6: 7
B8: Estimated Miles Per Vehicle Revenue Hour
B9: Microtransit | C9: 12.8
B10: Fx | C10: 14
