Workbook
Name _NST01: #N/A
Name FINAL: #N/A
Name TABLE1: #N/A

Sheet For Slides
A1: HILL COUNTRY TRANSIT DISTRICT
A2: FY2024 Proposed Budget (1/1/24 - 12/31/24)
A3: Presented to Board of Directors 11/20/23
C6: In Service | D6: In Service
B7: Commuter Bus Allocation Based on Census 2020 Population by City | S7: Commuter Bus Allocation Based on Census 2020 Population by City
C8: Vehicles | D8: Vehicles | F8: Cost Estimate | G8: Population | J8: Hours | T8: Cost Estimate | U8: Population | W8: Allocated Cost | X8: Hours
B9: TEMPLE | C9: 9 | D9: 12 | G9: 82073 | H9: =G9/G14 -> 0.24921128 | I9: =H9*$F$14 -> 209935.58 | J9: =F155 -> 39832 | K9: =J9/J14 -> 0.33765089 | L9: =J9/(J9+J10) -> 0.80293501 | S9: TEMPLE | U9: 82073 | V9: =U9/U14 -> 0.24921128 | W9: =V9*$F$14 -> 209935.58 | X9: =$F$30*V9 -> 2332.6176
B10: BELTON | C10: 2 | D10: 3 | G10: 23054 | H10: =G10/G14 -> 0.07000252 | I10: =H10*$F$14 -> 58970.123 | J10: =F134 -> 9776 | K10: =J10/J14 -> 0.082869931 | L10: =J10/(J9+J10) -> 0.19706499 | S10: BELTON | U10: 23054 | V10: =U10/U14 -> 0.07000252 | W10: =V10*$F$14 -> 58970.123 | X10: =$F$30*V10 -> 655.22359
B11: KILLEEN | C11: 11 | D11: 15 | G11: 153143 | H11: =G11/G14 -> 0.4650124 | I11: =H11*$F$14 -> 391726.45 | J11: =F112 -> 49192 | K11: =J11/J14 -> 0.41699444 | L11: =J11/(J11+J12+J13) -> 0.71960211 | S11: KILLEEN | U11: 153143 | V11: =U11/U14 -> 0.4650124 | W11: =V11*$F$14 -> 391726.45 | X11: =$F$30*V11 -> 4352.5161
B12: COPPERAS COVE | C12: 2 | D12: 3 | G12: 37964 | H12: =G12/G14 -> 0.11527612 | I12: =H12*$F$14 -> 97108.604 | J12: =F70 -> 9600 | K12: =J12/J14 -> 0.081378001 | L12: =J12/(J11+J12+J13) -> 0.140433 | S12: COPPERAS COVE | U12: 37964 | V12: =U12/U14 -> 0.11527612 | W12: =V12*$F$14 -> 97108.604 | X12: =$F$30*V12 -> 1078.9845
B13: HARKER HEIGHTS | C13: 2 | D13: 3 | G13: 33097 | H13: =G13/G14 -> 0.10049768 | I13: =H13*$F$14 -> 84659.242 | J13: =F91 -> 9568 | K13: =J13/J14 -> 0.081106741 | L13: =J13/(J11+J12+J13) -> 0.13996489 | S13: HARKER HEIGHTS | U13: 33097 | V13: =U13/U14 -> 0.10049768 | W13: =V13*$F$14 -> 84659.242 | X13: =$F$30*V13 -> 940.65824
C14: =SUM(C9:C13) -> 26 | D14: =SUM(D9:D13) -> 36 | F14: =12*260*3*90 -> 842400 | G14: =SUM(G9:G13) -> 329331 | H14: =SUM(H9:H13) -> 1 | I14: =SUM(I9:I13) -> 842400 | J14: =SUM(J9:J13) -> 117968 | K14: =SUM(K9:K13) -> 1 | T14: =12*260*3*90 -> 842400 | U14: =SUM(U9:U13) -> 329331 | V14: =SUM(V9:V13) -> 1 | W14: =SUM(W9:W13) -> 842400 | X14: =SUM(X9:X13) -> 9360
B16: Average Fare | C16: 1
B18: FY24 Budget Targets
B19: As of 6/6/2023
B20: Fully Allocated Expenses | C20: Avg. Daily | D20: Avg. Fleet During | F20: Annual Vehicle Revenue Hours | I20: Annual Passengers | L20: Proposed | P20: FY23
B21: Microtransit On-demand All Urban Zones | C21: Service Hours | D21: Service Hours | G21: Contingency | H21: Contingency | L21: FY24 | P21: Budget
B22: All Zones - Avg. Wait Times 30min Peak | C22: 260 Weekdays | F22: Budget | G22: +10% | H22: +20% | I22: Low | J22: Med | K22: High | L22: Budget | M22: +10% | N22: +20% | O22: Diff Lo/Hi
B23: 7am - 11am + 3pm - 7pm | C23: 8 | D23: =D14 -> 36 | F23: =(C23*D23*260) -> 74880 | G23: =F23*1.1 -> 82368 | H23: =F23*1.2 -> 89856 | I23: =F23*5 -> 374400 | J23: =F23*5.5 -> 411840 | K23: =F23*6 -> 449280 | L23: =F23*65 -> 4867200 | M23: =G23*65 -> 5353920 | N23: =H23*65 -> 5840640 | R23: =L63+L84+L105+L127+L148 -> 4867200
B24: All Zones - Avg. Wait Times 40min Off Peak | C24: 260 Weekdays
B25: 11am - 3pm + 7pm - 9pm | C25: 6 | D25: =C14 -> 26 | F25: =(C25*D25*260) -> 40560 | G25: =F25*1.1 -> 44616 | H25: =F25*1.2 -> 48672 | I25: =F25*3 -> 121680 | J25: =F25*4 -> 162240 | K25: =F25*5 -> 202800 | L25: =F25*65 -> 2636400 | M25: =G25*65 -> 2900040 | N25: =H25*65 -> 3163680 | R25: =L65+L86+L107+L129+L150 -> 2636400
B26: All Zones - Avg. Wait Times 30min Off Peak | C26: 52 Weekend Days
B27: TNC Service Provider | L27: =L67+L88+L109+L131+L151 -> 670453 | R27: =L67+L88+L109+L131+L151 -> 670453
B28: Medicaid Trips (50 daily) | C28: 8 | D28: 6 | F28: =F68+F89+F110+F132+F153 -> 2528 | G28: =F28*1.1 -> 2780.8 | H28: =F28*1.2 -> 3033.6 | I28: =F28*1.5 -> 3792 | J28: =G28*1.5 -> 4171.2 | K28: =H28*1.5 -> 4550.4 | L28: =F28*65 -> 164320 | M28: =G28*65 -> 180752 | N28: =H28*65 -> 197184 | R28: =L68+L89+L110+L132+L153 -> 164320
B29: Total Microtransit On-demand | F29: =SUM(F23:F28) -> 117968 | G29: =SUM(G23:G28) -> 129764.8 | H29: =SUM(H23:H28) -> 141561.6 | I29: =SUM(I23:I28) -> 499872 | J29: =SUM(J23:J28) -> 578251.2 | K29: =SUM(K23:K28) -> 656630.4 | L29: =SUM(L23:L28) -> 8338373 | M29: =SUM(M23:M28) -> 8434712 | N29: =SUM(N23:N28) -> 9201504
B30: Commuter Bus - Stops in Temple, Belton, Nolanville, Harker Heights, Killeen, Copperas Cove | C30: 12 | D30: 3 | F30: =(C30*D30*260) -> 9360 | G30: =F30*1.1 -> 10296 | H30: =F30*1.2 -> 11232 | I30: =10*5*2*290 -> 29000 | J30: =10*7*2*290 -> 40600 | K30: =10*8*2*290 -> 46400 | L30: =F30*90 -> 842400 | M30: =12*259*86*6 -> 1603728 | N30: =12*259*86*6 -> 1603728
B31: Rural | D31: 20 | F31: 32958.05 | J31: 70000 | L31: 2641604 | M31: 2592992 | N31: 2592992
B32: Fort Cavazos (No Fare) | F32: 56548 | J32: 169644 | L32: =4241400-(F32*10) -> 3675920 | S32: County | T32: State & Fed Funding Allocation | U32: NEMT Revenue | V32: Local Funding Contributions | W32: FY24 Budget Target | X32: FY24 County Funding Commitment
B33: Total Projected Expense | F33: =F29+F30+F31+F32 -> 216834.05 | G33: =G29+G30+G31+G32 -> 140060.8 | H33: =H29+H30+H31+H32 -> 152793.6 | I33: =I29+I30+I31+I32 -> 528872 | J33: =J29+J30+J31+J32 -> 858495.2 | K33: =K29+K30+K31+K32 -> 703030.4 | L33: =L29+L30+L31+L32 -> 15498297 | M33: =SUM(M29:M31) -> 12631432 | N33: =SUM(N29:N31) -> 13398224 | O33: =N33-L33 -> -2100073 | P33: =5149835+2883500+3001770 -> 11035105
B34: Projected Revenue
B35: Federal Grant Revenue | L35: =(L48+L51+L54)*-1 -> -6164398 | M35: =-(2970479+1673250+1253517) -> -5897246 | N35: =-(2970479+1673250+1253517) -> -5897246 | P35: =-(2970479+1673250+1253517) -> -5897246 | S35: Bell County | T35: 60476.325 | U35: 9383 | V35: 134383 | W35: 100793 | X35: 125000 | Z35: =ROUND(W35,0) -> 100793
B36: Federal Grant Carbon Reduction Grant | L36: -500000 | S36: Coryell County | T36: 197197.34 | U36: 30595 | V36: 104111 | W36: 301309 | X36: 50000 | Z36: =ROUND(W36,0) -> 301309
B37: State Revenue | L37: =(L49+L52+L55)*-1 -> -1525568 | M37: =-(415133+519759+601585) -> -1536477 | N37: =-(415133+519759+601585) -> -1536477 | P37: =-(415133+519759+601585) -> -1536477 | S37: Hamilton County | T37: 174565.1 | U37: 0 | V37: 0 | W37: 174565 | X37: 0 | Z37: =ROUND(W37,0) -> 174565
B38: Urban Medicaid Revenue | L38: -1113000 | M38: -1400000 | N38: -1400000 | P38: =-917223-634691-404368 -> -1956282 | S38: Lampasas County | T38: 179759.38 | U38: 27890 | V38: 119839 | W38: 299598 | X38: 68433 | Z38: =ROUND(W38,0) -> 299598
B39: Fare Revenue | L39: =((J29+J30+J31)*C16)*-1 -> -688851.2 | S39: Llano County | T39: 303680.2 | U39: 47116 | V39: 202451 | W39: 506131 | X39: 155335 | Z39: =ROUND(W39,0) -> 506131
B40: Killeen Local | L40: =L117*-1 -> -650000 | S40: Mason County | T40: 88117.345 | U40: 13671 | V40: 58744 | W40: 146862 | X40: 45073 | Z40: =ROUND(W40,0) -> 146862
B41: Temple Local | L41: =L162*-1 -> -308936.66 | S41: Milam County | T41: 601053.05 | U41: 93254 | V41: 215287 | W41: 816341 | X41: 75000 | Z41: =ROUND(W41,0) -> 816341
B42: Belton Local | L42: =L141*-1 -> -55372.768 | S42: Mills County | T42: 116500.41 | U42: 0 | V42: 0 | W42: 116500 | X42: 0 | Z42: =ROUND(W42,0) -> 116500
B43: Copperas Cove Local | L43: =L77*-1 -> -94462.808 | S43: San Saba | T43: 133752.85 | U43: 20752 | V43: 45752 | W43: 179505 | X43: 25000 | Z43: =ROUND(W43,0) -> 179505
B44: Harker Heights Local | L44: =L98*-1 -> -64999.85 | T44: =SUM(T35:T43) -> 1855102 | U44: =SUM(U35:U43) -> 242661 | V44: =SUM(V35:V43) -> 880567 | W44: =SUM(W35:W43) -> 2641604 | X44: =SUM(X35:X43) -> 543841 | Z44: =SUM(Z35:Z43) -> 2641604
B45: Rural Local ($242,661 Medicaid + $543,841 Counties) | L45: =(242661+543841)*-1 -> -786502
B46: Fort Cavazos | L46: =4241400*-1 -> -4241400 | S46: Total Revenues
B47: Total Revenue All Sources | L47: =SUM(L34:L46) -> -16193491 | M47: =SUM(M35:M38) -> -8833723 | N47: =SUM(N35:N38) -> -8833723 | P47: =SUM(P35:P38) -> -9390005 | S47: Federal Grant Revenue | T47: =-L35-L36 -> 6664398 | U47: =ROUND(T47/$T$55,2) -> 0.41
B48: Killeen UZA Federal Revenue Allocation | L48: 2970472 | S48: State Grant Revenue | T48: =-L37 -> 1525568 | U48: =ROUNDUP(T48/$T$55,2) -> 0.1
B49: Killeen State UZA Allocation | L49: =379929 -> 379929 | S49: Urban Medicaid Revenue | T49: =-L38 -> 1113000 | U49: =ROUND(T49/$T$55,2) -> 0.07
B50: Total Killeen | L50: =SUM(L48:L49) -> 3350401 | S50: Fare Revenue | T50: =-L39 -> 688851.2 | U50: =ROUND(T50/$T$55,2) -> 0.04
B51: Temple UZA Federal UZA Revenue Allocation | L51: 1940409 | P51: 1673250 | S51: Urban Local | T51: =-L40-L41-L42-L43-L44 -> 1173772.1 | U51: =ROUND(T51/$T$55,2) -> 0.07
B52: Temple State FY24 UZA Revenue Allocation + 5311 Grant Revenue | L52: =362108+158000 -> 520108 | P52: 519759 | S52: Rural Medicaid Revenue | T52: 242661 | U52: =ROUNDUP(T52/$T$55,2) -> 0.02
B53: Total Temple | L53: =SUM(L51:L52) -> 2460517 | S53: Rural Local | T53: 543841 | U53: =ROUND(T53/$T$55,2) -> 0.03
B54: Rural Federal Allocation | L54: 1253517 | S54: Fort Cavazos | T54: =-L46 -> 4241400 | U54: =ROUND(T54/$T$55,2) -> 0.26
B55: Rural State Allocation | L55: 625531 | S55: Total | T55: =SUM(T47:T54) -> 16193491
B56: Total Rural | L56: =SUM(L54:L55) -> 1879048 | P56: =L56+L53+L50 -> 7689966 | R56: =P56-L33 -> -7808331
B58: Estimates for Microtransit On-demand Copperas Cove Zones
C60: Avg. Daily | D60: Avg. Fleet During | F60: Annual Vehicle Revenue Hours | I60: Annual Passengers | L60: Proposed
C61: Service Hours | D61: Service Hours | G61: Contingency | H61: Contingency | L61: FY24
B62: All Zones - Avg. Wait Times 30min Peak | C62: 260 Weekdays | F62: Budget | G62: +10% | H62: +20% | I62: Low | J62: Med | K62: High | L62: Budget | M62: +10% | N62: +20% | O62: Diff Lo/Hi
B63: 7am - 11am + 3pm - 7pm | C63: 8 | D63: 3 | F63: =(C63*D63*260) -> 6240 | G63: =F63*1.1 -> 6864 | H63: =F63*1.2 -> 7488 | I63: =F63*5 -> 31200 | J63: =F63*5.5 -> 34320 | K63: =F63*6 -> 37440 | L63: =F63*65 -> 405600 | M63: =G63*65 -> 446160 | N63: =H63*65 -> 486720
B64: All Zones - Avg. Wait Times 40min Off Peak | C64: 260 Weekdays
B65: 11am - 3pm + 7pm - 9pm | C65: 6 | D65: 2 | F65: =(C65*D65*260) -> 3120 | G65: =F65*1.1 -> 3432 | H65: =F65*1.2 -> 3744 | I65: =F65*3 -> 9360 | J65: =F65*4 -> 12480 | K65: =F65*5 -> 15600 | L65: =F65*65 -> 202800 | M65: =G65*65 -> 223080 | N65: =H65*65 -> 243360
B66: All Zones - Avg. Wait Times 30min Off Peak | C66: 52 Weekend Days
B67: TNC Service Provider | J67: =L67/10 -> 3000 | L67: 30000
B68: Medicaid Trips | C68: 8 | D68: 0.5 | F68: =(C68*D68*60) -> 240 | G68: =F68*1.1 -> 264 | H68: =F68*1.2 -> 288 | I68: =F68*1.5 -> 360 | J68: =G68*1.5 -> 396 | K68: =H68*1.5 -> 432 | L68: =F68*65 -> 15600 | M68: =G68*65 -> 17160 | N68: =H68*65 -> 18720
B69: Commuter Bus Allocation | I69: =I30*$H$12 -> 3343.0075 | J69: =J30*$H$12 -> 4680.2105 | K69: =K30*$H$12 -> 5348.812 | L69: =I12 -> 97108.604 | M69: =L69*1.1 -> 106819.46 | N69: =L69*1.2 -> 116530.32
B70: Total | F70: =SUM(F63:F68) -> 9600 | G70: =SUM(G63:G68) -> 10560 | H70: =SUM(H63:H68) -> 11520 | I70: =SUM(I63:I69) -> 44263.007 | J70: =SUM(J63:J69) -> 54876.21 | K70: =SUM(K63:K69) -> 58820.812 | L70: =SUM(L63:L69) -> 751108.6 | M70: =SUM(M63:M69) -> 793219.46 | N70: =SUM(N63:N69) -> 865330.32 | O70: =N70-L70 -> 114221.72
B71: Projected Revenue | L71: =J70*C16 -> 54876.21 | P71: =L71+L74+L75 -> 198804.5
B72: =B36 -> Federal Grant Carbon Reduction Grant | C72: Based on hours in each city | L72: =(L36*K12)*-1 -> 40689
B73: Federal Revenue | L73: =L48*L12 -> 417152.3 | P73: =L73+L72 -> 457841.3
B74: State Revenue | L74: =L49*L12 -> 53354.57 | P74: =P73/2 -> 228920.65
B75: NEMT Revenue | L75: =(L38*K12)*-1 -> 90573.715 | P75: =P74-P71 -> 30116.155
B76: Total Revenue Sources | L76: =SUM(L71:L75) -> 656645.8
B77: Net Required Subsidy | L77: =L70-L76 -> 94462.808 | P77: =P75 -> 30116.155
B79: Estimates for Microtransit On-demand Harker Heights
C81: Avg. Daily | D81: Avg. Fleet During | F81: Annual Vehicle Revenue Hours | I81: Annual Passengers | L81: Proposed
C82: Service Hours | D82: Service Hours | G82: Contingency | H82: Contingency | L82: FY24
B83: All Zones - Avg. Wait Times 30min Peak | C83: 260 Weekdays | F83: Budget | G83: +10% | H83: +20% | I83: Low | J83: Med | K83: High | L83: Budget | M83: +10% | N83: +20% | O83: Diff Lo/Hi
B84: 7am - 11am + 3pm - 7pm | C84: 8 | D84: 3 | F84: =(C84*D84*260) -> 6240 | G84: =F84*1.1 -> 6864 | H84: =F84*1.2 -> 7488 | I84: =F84*5 -> 31200 | J84: =F84*5.5 -> 34320 | K84: =F84*6 -> 37440 | L84: =F84*65 -> 405600 | M84: =G84*65 -> 446160 | N84: =H84*65 -> 486720
B85: All Zones - Avg. Wait Times 40min Off Peak | C85: 260 Weekdays
B86: 11am - 3pm + 7pm - 9pm | C86: 6 | D86: 2 | F86: =(C86*D86*260) -> 3120 | G86: =F86*1.2 -> 3744 | H86: =F86*1.3 -> 4056 | I86: =F86*3 -> 9360 | J86: =F86*4 -> 12480 | K86: =F86*5 -> 15600 | L86: =F86*65 -> 202800 | M86: =G86*65 -> 243360 | N86: =H86*65 -> 263640
B87: All Zones - Avg. Wait Times 30min Off Peak | C87: 52 Weekend Days
B88: TNC Service Provider | J88: =L88/10 -> 1045.3 | L88: 10453
B89: Medicaid Trips | C89: 8 | D89: 0.5 | F89: =(C89*D89*52) -> 208 | G89: =F89*1.1 -> 228.8 | H89: =F89*1.2 -> 249.6 | I89: =F89*1.5 -> 312 | J89: =G89*1.5 -> 343.2 | K89: =H89*1.5 -> 374.4 | L89: =F89*65 -> 13520 | M89: =G89*65 -> 14872 | N89: =H89*65 -> 16224
B90: Commuter Bus Allocation | I90: =I30*$H$13 -> 2914.4326 | J90: =J30*$H$13 -> 4080.2056 | K90: =K30*$H$13 -> 4663.0921 | L90: =I13 -> 84659.242 | M90: =L90*1.1 -> 93125.166 | N90: =L90*1.2 -> 101591.09
B91: Total | F91: =SUM(F84:F89) -> 9568 | G91: =SUM(G84:G89) -> 10836.8 | H91: =SUM(H84:H89) -> 11793.6 | I91: =SUM(I84:I90) -> 43786.433 | J91: =SUM(J84:J90) -> 52268.706 | K91: =SUM(K84:K90) -> 58077.492 | L91: =SUM(L84:L90) -> 717032.24 | M91: =SUM(M84:M90) -> 797517.17 | N91: =SUM(N84:N90) -> 868175.09 | O91: =N91-L91 -> 151142.85
B92: Projected Revenue | L92: =J91*C16 -> 52268.706 | P92: =L92+L95+L96 -> 195717.23
B93: =B36 -> Federal Grant Carbon Reduction Grant | C93: Based on hours in each city | L93: =(L36*K13)*-1 -> 40553.37
B94: Federal Revenue | L94: =L48*L13 -> 415761.79 | P94: =L94+L93 -> 456315.16
B95: State Revenue | L95: =L49*L13 -> 53176.721 | P95: =P94/2 -> 228157.58
B96: NEMT Revenue | L96: =(L38*K13)*-1 -> 90271.803 | P96: =P95-P92 -> 32440.352
B97: Total Revenue Sources | L97: =SUM(L92:L96) -> 652032.39
B98: Net Required Subsidy | L98: =L91-L97 -> 64999.85 | P98: =P96 -> 32440.352
B100: Estimates for Microtransit On-demand Killeen
C102: Avg. Daily | D102: Avg. Fleet During | F102: Annual Vehicle Revenue Hours | I102: Annual Passengers | L102: Proposed
C103: Service Hours | D103: Service Hours | G103: Contingency | H103: Contingency | L103: FY24
B104: All Zones - Avg. Wait Times 30min Peak | C104: 260 Weekdays | F104: Budget | G104: +10% | H104: +20% | I104: Low | J104: Med | K104: High | L104: Budget | M104: +10% | N104: +20% | O104: Diff Lo/Hi
B105: 7am - 11am + 3pm - 7pm | C105: 8 | D105: =D11 -> 15 | F105: =(C105*D105*260) -> 31200 | G105: =F105*1.1 -> 34320 | H105: =F105*1.2 -> 37440 | I105: =F105*5 -> 156000 | J105: =F105*5.5 -> 171600 | K105: =F105*6 -> 187200 | L105: =F105*65 -> 2028000 | M105: =G105*65 -> 2230800 | N105: =H105*65 -> 2433600 | R105: =G11 -> 153143 | S105: =R105/R108 -> 0.68305204 | T105: Killeen
B106: All Zones - Avg. Wait Times 40min Off Peak | C106: 260 Weekdays | R106: =G12 -> 37964 | S106: =R106/R108 -> 0.16932793 | T106: Cove
B107: 11am - 3pm + 7pm - 9pm | C107: 6 | D107: =C11 -> 11 | F107: =(C107*D107*260) -> 17160 | G107: =F107*1.2 -> 20592 | H107: =F107*1.3 -> 22308 | I107: =F107*3 -> 51480 | J107: =F107*4 -> 68640 | K107: =F107*5 -> 85800 | L107: =F107*65 -> 1115400 | M107: =G107*65 -> 1338480 | N107: =H107*65 -> 1450020 | R107: =G13 -> 33097 | S107: =R107/R108 -> 0.14762002 | T107: Heights
B108: All Zones - Avg. Wait Times 30min Off Peak | C108: 52 Weekend Days | R108: =SUM(R105:R107) -> 224204
B109: TNC Service Provider | J109: =L109/10 -> 35000 | L109: 350000
B110: Medicaid Trips | C110: 8 | D110: 2 | F110: =(C110*D110*52) -> 832 | G110: =F110*1.1 -> 915.2 | H110: =F110*1.2 -> 998.4 | I110: =F110*1.5 -> 1248 | J110: =G110*1.5 -> 1372.8 | K110: =H110*1.5 -> 1497.6 | L110: =F110*65 -> 54080 | M110: =G110*65 -> 59488 | N110: =H110*65 -> 64896
...

Sheet ASSUMPTIONS
A1: MAJOR ASSUMPTIONS
A2: WORKING DRAFT
A4: 1 | B4: This workbook provides examples and a working draft 5-year financial model as an attempt to tie operating decisions to return on investment
A5: 2 | B5: It is intended to facilitate further discussions and collaberative input regarding sources and uses of funding streams
A6: 3 | B6: All information presented is for illustrative purposes - No recommendation or decisions are to be made from this draft model without further validation
A7: 4 | B7: Certain categorizations have been made to illustrate how funding may be apportioned in the future
A8: 5 | B8: Validation and collaboration is needed to refine all data
A9: 6 | B9: Proposed date for transition of operations = October 1, 2026
A10: 7 | B10: The model uses 2.5% annual escalation for most expenses
A11: 8 | B11: It is important for the user of this the workbook is not complete as key cost share, service type, and revenue share assumptions need to be defined and agreed upon
A12: 9 | B12: The workbook is designed to allow for incremental progress and adjustments as various options are executed to improve the accurace of the workbook
A13: 10 | B13: Three tabs to focus on: Operating Tab, FY27 Financial Forecast, FTA FY27 Financial Forecast Sub Allocation Example

Sheet SRTP - COMP Factors
A1: DRAFT SRTP used as a source of information
S8: Cost per Hr.
S9: Comps | T9: # of Vehicles
S10: =6131022/28294 -> 216.68983 | T10: 12 | U10: TTD
S11: =6532640/66679 -> 97.971475 | T11: 27 | U11: Vail, Co
S12: =5187138/52795 -> 98.250554 | T12: 37 | U12: Mammoth, Ca
S13: =5603319/57175 -> 98.002956 | T13: 28 | U13: Jackson Hole, Wy
S14: =3558126/40400 -> 88.072426 | T14: 32 | U14: Sun Valley, Id
S15: =4672736/41060 -> 113.80263 | T15: 22 | U15: Steamboat Springs, Co
S16: =11491801/72927 -> 157.57951 | T16: 21 | U16: Park City, Ut
S17: =9677785/55759 -> 173.56454 | T17: 31 | U17: Summit County, Co
S18: =11504947/79931 -> 143.93598 | T18: 22 | U18: Eagle County, Co
S19: =11400000/74899 -> 152.20497 | T19: 33 | U19: Whistler
S21: =46190159/246091 -> 187.69544 | T21: 98 | U21: Aspen
S22: =AVERAGE(S11:S21) -> 131.10805 | T22: Average
R23: 0.34 | S23: =S22*R23 -> 44.576736 | T23: COLA to Tahoe
S24: =SUM(S22:S23) -> 175.68478 | T24: Target Hourly Rate
A25: National and regional comps support the use of $175 per VRH for fixed route services as a target | S25: CA+CO | T25: CO Only
A26: Regional comps suggest a targeted cost of $96-$183 per VRH for fixed route services | S26: =(S11+S12+S13+S15+S16+S17+S18+S19)/8 -> 129.41408 | T26: =(S11+S12+S15+S17+S18+S21)/6 -> 135.8701
R27: 0.289 | S27: =S26*R27 -> 37.400668 | T27: =T26*R27 -> 39.26646
S28: =S26+S27 -> 166.81475 | T28: =T26+T27 -> 175.13656

Sheet Regional COMPs

Sheet Fare Assumptions
C3: Fare
B4: Local | C4: 0
B5: Rural | C5: 5
B6: Regional fx | C6: 7
B7: Recreational | C7: 15

Sheet VRH Rates
B3: VRH Rates
B5: Microtransit | D5: 85
B6: Fixed Route Bus | D6: 175
B7: Commuter | D7: =D6 -> 175

Sheet Avg Pass, Mile Per Hr
B2: Projected Passengers Per Revenue Hour
B3: Micro Meyers | C3: 7
B4: Micro Urban | C4: 7
B5: Fixed Route | C5: 20
B6: Recreation | C6: 7
B8: Estimated Miles Per Vehicle Revenue Hour
B9: Microtransit | C9: 12.8
B10: Fx | C10: 14

Sheet Operating 
A1: LAKE LINK ZONES 1-5
A2: SERVICE HOURS OFF-PEAK SEASON [OCT, NOVEMBER] | B2: 6am | C2: 7am | D2: 8am | E2: 9am | F2: 10am | G2: 11am | H2: 12pm | I2: 1pm | J2: 2pm | K2: 3pm | L2: 4pm | M2: 5pm | N2: 6pm | O2: 7pm | P2: 8pm | Q2: 9pm | R2: 10pm | S2: 11pm | AB2: LAKE LINK - 12 MONTH ROLLING STATISTICS
A3: hr | C3: 1 | D3: 2 | E3: 3 | F3: 4 | G3: 5 | H3: 6 | I3: 7 | J3: 8 | K3: 9 | L3: 10 | M3: 11 | N3: 12 | O3: 13 | P3: 14 | Q3: 15 | R3: 17 | S3: 18 | AC3: 45170 | AD3: 45200 | AE3: 45231 | AF3: 45261 | AG3: 45292 | AH3: 45323 | AI3: 45352 | AJ3: 45383 | AK3: 45413 | AL3: 45444 | AM3: 45474 | AN3: 45505 | AO3: Total
A4: TIME | B4: 0.25 | C4: 0.29166667 | D4: 0.33333333 | E4: 0.375 | F4: 0.41666667 | G4: 0.45833333 | H4: 0.5 | I4: 0.54166667 | J4: 0.58333333 | K4: 0.625 | L4: 0.66666667 | M4: 0.70833333 | N4: 0.75 | O4: 0.79166667 | P4: 0.83333333 | Q4: 0.875 | R4: 0.91666667 | S4: 0.95833333 | AB4: Passengers | AC4: 15390 | AD4: 12235 | AE4: 11359 | AF4: 19738 | AG4: 24392 | AH4: 25301 | AI4: 23546 | AJ4: 18830 | AK4: 19932 | AL4: 24029 | AM4: 25365 | AN4: 24121 | AO4: 244238
A5: Vehicles | C5: 9 | D5: 10 | E5: 10 | F5: 10 | G5: 8 | H5: 8 | I5: 8 | J5: 9 | K5: 9 | L5: 10 | M5: 10 | N5: 10 | O5: 10 | P5: 9 | Q5: 9 | R5: 8 | U5: Weeks | V5: VRH | W5: Expenses | X5: VRM | Y5: Passengers | Z5: Fares | AB5: Vehicle Revenue Hours | AC5: 1929 | AD5: 1430 | AE5: 1315 | AF5: 1924 | AG5: 2463 | AH5: 2572 | AI5: 2619 | AJ5: 2062 | AK5: 2047 | AL5: 2507 | AM5: 2655 | AN5: 2585 | AO5: 26108
A6: Nonpeak days Sunday - Thursday | C6: 5 | D6: 5 | E6: 5 | F6: 5 | G6: 5 | H6: 5 | I6: 5 | J6: 5 | K6: 5 | L6: 5 | M6: 5 | N6: 5 | O6: 5 | P6: 5 | U6: 8 | AB6: Total Vehicle Hours | AC6: 2088 | AD6: 1529 | AE6: 1412 | AF6: 2056 | AG6: 2630 | AH6: 2753 | AI6: 2822 | AJ6: 2230 | AK6: 2221 | AL6: 2717 | AM6: 2880 | AN6: 2825 | AO6: 28163
A7: Peak Days Friday-Saturday | C7: 2 | D7: 2 | E7: 2 | F7: 2 | G7: 2 | H7: 2 | I7: 2 | J7: 2 | K7: 2 | L7: 2 | M7: 2 | N7: 2 | O7: 2 | P7: 2 | Q7: 2 | R7: 2 | AB7: Vehicle Revenue Miles | AC7: 23772 | AD7: 18326 | AE7: 17325 | AF7: 23657 | AG7: 29638 | AH7: 31591 | AI7: 35502 | AJ7: 28463 | AK7: 27637 | AL7: 32486 | AM7: 33127 | AN7: 33199 | AO7: 334723
A8: Service Days | C8: =C7+C6 -> 7 | D8: =D7+D6 -> 7 | E8: =E7+E6 -> 7 | F8: =F7+F6 -> 7 | G8: =G7+G6 -> 7 | H8: =H7+H6 -> 7 | I8: =I7+I6 -> 7 | J8: =J7+J6 -> 7 | ... R8: =R7+R6 -> 2 | AB8: Total Vehicle Miles | AC8: 25004 | AD8: 19081 | AE8: 18119 | AF8: 24593 | AG8: 30803 | AH8: 32863 | AI8: 33785 | AJ8: 29681 | AK8: 28887 | AL8: 33981 | AM8: 34744 | AN8: 34825 | AO8: 346366
A9: SERVICE BY HOUR | U9: Weekly Hours | AB9: Passenger Miles | AC9: 24785 | AD9: 19110 | AE9: 17402 | AF9: 29440 | AG9: 38011 | AH9: 41594 | AI9: 38682 | AJ9: 33069 | AK9: 37284 | AL9: 47653 | AM9: 48929 | AN9: 46932 | AO9: 422891
A10: Nonpeak days Sunday - Thursday | C10: =C5*C6 -> 45 | D10: =D5*D6 -> 50 | E10: =E5*E6 -> 50 | F10: =F5*F6 -> 50 | G10: =G5*G6 -> 40 | H10: =H5*H6 -> 40 | I10: =I5*I6 -> 40 | J10: =J5*J6 -> 45 | ... R10: =R5*R6 -> 0 | U10: =SUM(B10:T10) -> 650
A11: Peak Days Friday-Saturday | C11: =C5*C7 -> 18 | D11: =D5*D7 -> 20 | E11: =E5*E7 -> 20 | F11: =F5*F7 -> 20 | G11: =G5*G7 -> 16 | H11: =H5*H7 -> 16 | I11: =I5*I7 -> 16 | J11: =J5*J7 -> 18 | ... R11: =R5*R7 -> 16 | U11: =SUM(B11:T11) -> 294 | AB11: Passengers | AC11: 0.063012308 | AD11: 0.05009458 | AE11: 0.046507914 | AF11: 0.080814615 | AG11: 0.099869799 | AH11: 0.10359158 | AI11: 0.096405965 | AJ11: 0.07709693 | AK11: 0.081608922 | AL11: 0.098383544 | AM11: 0.10385362 | AN11: 0.098760226 | AO11: 1
A12: Total Service Hours - by hour of the day | C12: =SUM(C10:C11) -> 63 | D12: =SUM(D10:D11) -> 70 | E12: =SUM(E10:E11) -> 70 | F12: =SUM(F10:F11) -> 70 | G12: =SUM(G10:G11) -> 56 | H12: =SUM(H10:H11) -> 56 | I12: =SUM(I10:I11) -> 56 | J12: =SUM(J10:J11) -> 63 | ... R12: =SUM(R10:R11) -> 16 | U12: =SUM(U10:U11) -> 944 | V12: =U12*U6 -> 7552 | W12: =V12*'VRH Rates'!D5 -> 641920 | X12: =V12*$AC$24 -> 96947.235 | Y12: =V12*'Avg Pass, Mile Per Hr'!C4 -> 52864 | Z12: =Y12*'Fare Assumptions'!C4 -> 0 | AB12: Vehicle Revenue Hours | AC12: 0.073885399 | AD12: 0.054772484 | AE12: 0.050367703 | AF12: 0.073693887 | AG12: 0.0943389 | AH12: 0.098513865 | AI12: 0.10031408 | AJ12: 0.078979623 | AK12: 0.078405087 | AL12: 0.096024207 | AM12: 0.10169297 | AN12: 0.099011797 | AO12: 1
AB13: Total Vehicle Hours | AC13: 0.074139829 | AD13: 0.054291091 | AE13: 0.050136704 | AF13: 0.073003586 | AG13: 0.093384938 | AH13: 0.09775237 | AI13: 0.10020239 | AJ13: 0.079181905 | AK13: 0.078862337 | AL13: 0.096474097 | AM13: 0.10226183 | AN13: 0.10030892 | AO13: 1
A14: SERVICE HOURS PEAK SEASON [JAN, FEB, MAR, JUN, JUL, AUG] | AB14: Vehicle Revenue Miles | AC14: 0.071019918 | AD14: 0.054749748 | AE14: 0.051759216 | AF14: 0.07067635 | AG14: 0.088544856 | AH14: 0.094379532 | AI14: 0.10606382 | AJ14: 0.085034491 | AK14: 0.082566779 | AL14: 0.097053384 | AM14: 0.098968401 | AN14: 0.099183504 | AO14: 1
A15: Vehicles | C15: 11 | D15: 11 | E15: 11 | F15: 10 | G15: 10 | H15: 10 | I15: 9 | J15: 9 | K15: 9 | L15: 11 | M15: 11 | N15: 11 | O15: 11 | P15: 9 | Q15: 9 | R15: 8 | U15: Weeks | V15: VRH | W15: Expenses | X15: VRM | Y15: Passengers | Z15: Fares | AB15: Total Vehicle Miles | AC15: 0.072189534 | AD15: 0.055089125 | AE15: 0.052311717 | AF15: 0.071002928 | AG15: 0.088931939 | AH15: 0.094879405 | AI15: 0.097541329 | AJ15: 0.085692591 | AK15: 0.083400218 | AL15: 0.098107205 | AM15: 0.10031008 | AN15: 0.10054393 | AO15: 1
A16: Nonpeak days Sunday - Thursday | C16: 5 | D16: 5 | E16: 5 | F16: 5 | G16: 5 | H16: 5 | I16: 5 | J16: 5 | K16: 5 | L16: 5 | M16: 5 | N16: 5 | O16: 5 | P16: 5 | U16: 27 | AB16: Passenger Miles | AC16: 0.058608483 | AD16: 0.045188949 | AE16: 0.041150084 | AF16: 0.069616048 | AG16: 0.089883682 | AH16: 0.098356314 | AI16: 0.091470379 | AJ16: 0.078197455 | AK16: 0.088164562 | AL16: 0.11268388 | AM16: 0.11570121 | AN16: 0.11097895 | AO16: 1
A17: Peak Days Friday-Saturday | C17: 2 | D17: 2 | E17: 2 | F17: 2 | G17: 2 | H17: 2 | I17: 2 | J17: 2 | K17: 2 | L17: 2 | M17: 2 | N17: 2 | O17: 2 | P17: 2 | Q17: 2 | R17: 2
A18: Service Days | C18: =C17+C16 -> 7 | D18: =D17+D16 -> 7 | E18: =E17+E16 -> 7 | F18: =F17+F16 -> 7 | G18: =G17+G16 -> 7 | H18: =H17+H16 -> 7 | I18: =I17+I16 -> 7 | J18: =J17+J16 -> 7 | ... R18: =R17+R16 -> 2
A19: SERVICE BY HOUR | U19: Weekly Hours
A20: Nonpeak days Sunday - Thursday | C20: =C15*C16 -> 55 | D20: =D15*D16 -> 55 | E20: =E15*E16 -> 55 | F20: =F15*F16 -> 50 | G20: =G15*G16 -> 50 | H20: =H15*H16 -> 50 | I20: =I15*I16 -> 45 | J20: =J15*J16 -> 45 | ... R20: =R15*R16 -> 0 | U20: =SUM(B20:T20) -> 715
A21: Peak Days Friday-Saturday | C21: =C15*C17 -> 22 | D21: =D15*D17 -> 22 | E21: =E15*E17 -> 22 | F21: =F15*F17 -> 20 | G21: =G15*G17 -> 20 | H21: =H15*H17 -> 20 | I21: =I15*I17 -> 18 | J21: =J15*J17 -> 18 | ... R21: =R15*R17 -> 16 | U21: =SUM(B21:T21) -> 320
A22: Total Service Hours - by hour of the day | C22: =SUM(C20:C21) -> 77 | D22: =SUM(D20:D21) -> 77 | E22: =SUM(E20:E21) -> 77 | F22: =SUM(F20:F21) -> 70 | G22: =SUM(G20:G21) -> 70 | H22: =SUM(H20:H21) -> 70 | I22: =SUM(I20:I21) -> 63 | J22: =SUM(J20:J21) -> 63 | ... R22: =SUM(R20:R21) -> 16 | U22: =SUM(U20:U21) -> 1035 | V22: =U22*U16 -> 27945 | W22: =V22*'VRH Rates'!D5 -> 2375325 | X22: =V22*'Avg Pass, Mile Per Hr'!C9 -> 357696 | Y22: =V22*'Avg Pass, Mile Per Hr'!C4 -> 195615 | Z22: =Y22*'Fare Assumptions'!C4 -> 0
AB23: Miles per RH | AC23: =AC7/AC5 -> 12.323484 | AD23: =AD7/AD5 -> 12.815385 | AE23: =AE7/AE5 -> 13.174905 | AF23: =AF7/AF5 -> 12.295738 | AG23: =AG7/AG5 -> 12.033293 | AH23: =AH7/AH5 -> 12.282659 | AI23: =AI7/AI5 -> 13.555556 | AJ23: =AJ7/AJ5 -> 13.803589 | ... AO23: =AO7/AO5 -> 12.820706 | AP23: =AVERAGE(AC23:AO23) -> 12.837293
A24: SERVICE HOURS OFF-PEAK SEASON [SEP, DEC, APR, MAY] | AB24: Average Miles Per Rev Hour | AC24: =AVERAGE(AC23:AP23) -> 12.837293
A25: Vehicles | C25: 11 | D25: 10 | E25: 10 | F25: 9 | G25: 9 | H25: 8 | I25: 8 | J25: 8 | K25: 8 | L25: 11 | M25: 11 | N25: 11 | O25: 10 | P25: 9 | Q25: 9 | R25: 8 | U25: Weeks | V25: VRH | W25: Expenses | X25: VRM | Y25: Passengers | Z25: Fares
A26: Nonpeak days Sunday - Thursday | C26: 5 | D26: 5 | E26: 5 | F26: 5 | G26: 5 | H26: 5 | I26: 5 | J26: 5 | K26: 5 | L26: 5 | M26: 5 | N26: 5 | O26: 5 | P26: 5 | U26: 17
A27: Peak Days Friday-Saturday | C27: 2 | D27: 2 | E27: 2 | F27: 2 | G27: 2 | H27: 2 | I27: 2 | J27: 2 | K27: 2 | L27: 2 | M27: 2 | N27: 2 | O27: 2 | P27: 2 | Q27: 2 | R27: 2
A28: Service Days | C28: =C27+C26 -> 7 | D28: =D27+D26 -> 7 | E28: =E27+E26 -> 7 | F28: =F27+F26 -> 7 | G28: =G27+G26 -> 7 | H28: =H27+H26 -> 7 | I28: =I27+I26 -> 7 | J28: =J27+J26 -> 7 | ... R28: =R27+R26 -> 2
A29: SERVICE BY HOUR | U29: Weekly Hours
A30: Nonpeak days Sunday - Thursday | C30: =C25*C26 -> 55 | D30: =D25*D26 -> 50 | E30: =E25*E26 -> 50 | F30: =F25*F26 -> 45 | G30: =G25*G26 -> 45 | H30: =H25*H26 -> 40 | I30: =I25*I26 -> 40 | J30: =J25*J26 -> 40 | ... R30: =R25*R26 -> 0 | U30: =SUM(B30:T30) -> 665
A31: Peak Days Friday-Saturday | C31: =C25*C27 -> 22 | D31: =D25*D27 -> 20 | E31: =E25*E27 -> 20 | F31: =F25*F27 -> 18 | G31: =G25*G27 -> 18 | H31: =H25*H27 -> 16 | I31: =I25*I27 -> 16 | J31: =J25*J27 -> 16 | ... R31: =R25*R27 -> 16 | U31: =SUM(B31:T31) -> 300
A32: Total Service Hours - by hour of the day | C32: =SUM(C30:C31) -> 77 | D32: =SUM(D30:D31) -> 70 | E32: =SUM(E30:E31) -> 70 | F32: =SUM(F30:F31) -> 63 | G32: =SUM(G30:G31) -> 63 | H32: =SUM(H30:H31) -> 56 | I32: =SUM(I30:I31) -> 56 | J32: =SUM(J30:J31) -> 56 | ... R32: =SUM(R30:R31) -> 16 | U32: =SUM(U30:U31) -> 965 | V32: =U32*U26 -> 16405 | W32: =V32*'VRH Rates'!D5 -> 1394425 | X32: =V32*'Avg Pass, Mile Per Hr'!C9 -> 209984 | Y32: =V32*'Avg Pass, Mile Per Hr'!C4 -> 114835 | Z32: =Y32*'Fare Assumptions'!C4 -> 0
U33: Zone 1 -5 TOTAL | V33: =V32+V22+V12 -> 51902 | W33: =W32+W22+W12 -> 4411670 | X33: =X32+X22+X12 -> 664627.23 | Y33: =Y32+Y22+Y12 -> 363314 | Z33: =Z32+Z22+Z12 -> 0
A34: SERVICE OPTIONS
A35: ZONE 6 SERVICE HOURS ROUTE 55 Replacement | B35: 6am | C35: 7am | D35: 8am | E35: 9am | F35: 10am | G35: 11am | H35: 12pm | I35: 1pm | J35: 2pm | K35: 3pm | L35: 4pm | M35: 5pm | N35: 6pm | O35: 7pm | P35: 8pm | Q35: 9pm | R35: 10pm | S35: 11pm | U35: ZONE 6 SERVICE HOURS ROUTE 55 Replacement
C36: 1 | D36: 2 | E36: 3 | F36: 4 | G36: 5 | H36: 6 | I36: 7 | J36: 8 | K36: 9 | L36: 10 | M36: 11 | N36: 12 | O36: 13 | P36: 14 | Q36: 15 | R36: 17 | S36: 18 | U36: Weeks | V36: VRH | W36: Expenses | X36: VRM | Y36: Passengers | Z36: Fares
A37: TIME | B37: 0.25 | C37: 0.29166667 | D37: 0.33333333 | E37: 0.375 | F37: 0.41666667 | G37: 0.45833333 | H37: 0.5 | I37: 0.54166667 | J37: 0.58333333 | K37: 0.625 | L37: 0.66666667 | M37: 0.70833333 | N37: 0.75 | O37: 0.79166667 | P37: 0.83333333 | Q37: 0.875 | R37: 0.91666667 | S37: 0.95833333 | U37: 52
A38: Vehicles | C38: 2 | D38: 2 | E38: 2 | F38: 2 | G38: 2 | H38: 2 | I38: 2 | J38: 2 | K38: 2 | L38: 2 | M38: 2 | N38: 2 | O38: 2 | P38: 2
A39: Weekdays Only | C39: 5 | D39: 5 | E39: 5 | F39: 5 | G39: 5 | H39: 5 | I39: 5 | J39: 5 | K39: 5 | L39: 5 | M39: 5 | N39: 5 | O39: 5 | P39: 5
A41: Total Service Hours - by hour of the day | C41: =C38*C39 -> 10 | D41: =D38*D39 -> 10 | E41: =E38*E39 -> 10 | F41: =F38*F39 -> 10 | G41: =G38*G39 -> 10 | H41: =H38*H39 -> 10 | I41: =I38*I39 -> 10 | J41: =J38*J39 -> 10 | ... P41: =P38*P39 -> 10 | U41: Weekly Hours
U42: =SUM(C41:Q41) -> 140 | V42: =U42*U37 -> 7280 | W42: =V42*'VRH Rates'!D5 -> 618800 | X42: =V42*'Avg Pass, Mile Per Hr'!C9 -> 93184 | Y42: =V42*'Avg Pass, Mile Per Hr'!C4 -> 50960 | Z42: =Y42*'Fare Assumptions'!C4 -> 0
A48: ZONE 7 EMERALD BAY | B48: 6am | C48: 7am | D48: 8am | E48: 9am | F48: 10am | G48: 11am | H48: 12pm | I48: 1pm | J48: 2pm | K48: 3pm | L48: 4pm | M48: 5pm | N48: 6pm | O48: 7pm | P48: 8pm | Q48: 9pm | R48: 10pm | S48: 11pm | U48: ZONE 7 EMERALD BAY
A49: SERVICE HOURS [JUN, JUL, AUG] | U49: Weeks | V49: VRH | W49: Expenses | X49: VRM | Y49: Passengers | Z49: Fares
C50: 1 | D50: 2 | E50: 3 | F50: 4 | G50: 5 | H50: 6 | I50: 7 | J50: 8 | K50: 9 | L50: 10 | M50: 11 | N50: 12 | O50: 13 | P50: 14 | Q50: 15 | R50: 17 | S50: 18 | U50: 12
A51: Vehicles | C51: 4 | D51: 4 | E51: 4 | F51: 4 | G51: 4 | H51: 4 | I51: 4 | J51: 4 | K51: 4 | L51: 4 | M51: 4 | N51: 4 | O51: 4 | P51: 4 | Q51: 4 | R51: 4
A52: Nonpeak days | C52: 5 | D52: 5 | E52: 5 | F52: 5 | G52: 5 | H52: 5 | I52: 5 | J52: 5 | K52: 5 | L52: 5 | M52: 5 | N52: 5 | O52: 5 | P52: 5
A53: Peak Days | C53: 2 | D53: 2 | E53: 2 | F53: 2 | G53: 2 | H53: 2 | I53: 2 | J53: 2 | K53: 2 | L53: 2 | M53: 2 | N53: 2 | O53: 2 | P53: 2 | Q53: 2 | R53: 2 | U53: Weekly Hours
A54: Service Days | C54: =C53+C52 -> 7 | D54: =D53+D52 -> 7 | E54: =E53+E52 -> 7 | F54: =F53+F52 -> 7 | G54: =G53+G52 -> 7 | H54: =H53+H52 -> 7 | I54: =I53+I52 -> 7 | J54: =J53+J52 -> 7 | ... P54: =P53+P52 -> 7 | U54: =SUM(B56:T56) -> 280
A55: SERVICE BY HOUR | U55: =SUM(B57:T57) -> 128
A56: Nonpeak hrs | C56: =C51*C52 -> 20 | D56: =D51*D52 -> 20 | E56: =E51*E52 -> 20 | F56: =F51*F52 -> 20 | G56: =G51*G52 -> 20 | H56: =H51*H52 -> 20 | I56: =I51*I52 -> 20 | J56: =J51*J52 -> 20 | ... P56: =P51*P52 -> 20 | U56: =SUM(U54:U55) -> 408 | V56: =U56*U50 -> 4896 | W56: =V56*'VRH Rates'!D5 -> 416160 | X56: =V56*'Avg Pass, Mile Per Hr'!C9 -> 62668.8 | Y56: =V56*'Avg Pass, Mile Per Hr'!C6 -> 34272 | Z56: =Y56*'Fare Assumptions'!C7 -> 514080
A57: Peak hrs | C57: =C51*C53 -> 8 | D57: =D51*D53 -> 8 | E57: =E51*E53 -> 8 | F57: =F51*F53 -> 8 | G57: =G51*G53 -> 8 | H57: =H51*H53 -> 8 | I57: =I51*I53 -> 8 | J57: =J51*J53 -> 8 | ... R57: =R51*R53 -> 8
A58: Total Service Hours - by hour of the day | C58: =SUM(C56:C57) -> 28 | D58: =SUM(D56:D57) -> 28 | E58: =SUM(E56:E57) -> 28 | F58: =SUM(F56:F57) -> 28 | G58: =SUM(G56:G57) -> 28 | H58: =SUM(H56:H57) -> 28 | I58: =SUM(I56:I57) -> 28 | J58: =SUM(J56:J57) -> 28 | ... R58: =SUM(R56:R57) -> 8
AH59: 225 | AI59: 175 | AJ59: =AI59-AH59 -> -50
A60: Zone 8 Meyers | U60: Zone 8 Meyers | AH60: =28294*AH59 -> 6366150 | AI60: =28294*175 -> 4951450 | AJ60: =AI60-AH60 -> -1414700
A61: SERVICE HOURS OFF-PEAK SEASON [OCT, NOVEMBER] | B61: 6am | C61: 7am | D61: 8am | E61: 9am | F61: 10am | G61: 11am | H61: 12pm | I61: 1pm | J61: 2pm | K61: 3pm | L61: 4pm | M61: 5pm | N61: 6pm | O61: 7pm | P61: 8pm | Q61: 9pm | R61: 10pm | S61: 11pm | U61: Weeks | V61: VRH | W61: Expenses | X61: VRM | Y61: Passengers | Z61: Fares
C62: 1 | D62: 2 | E62: 3 | F62: 4 | G62: 5 | H62: 6 | I62: 7 | J62: 8 | K62: 9 | L62: 10 | M62: 11 | N62: 12 | O62: 13 | P62: 14 | Q62: 15 | R62: 17 | S62: 18 | U62: 8
A63: Vehicles | C63: 2 | D63: 2 | E63: 2 | F63: 2 | G63: 1 | H63: 1 | I63: 1 | J63: 1 | K63: 1 | L63: 2 | M63: 2 | N63: 2 | O63: 12 | P63: 1
A64: Nonpeak days | C64: 5 | D64: 5 | E64: 5 | F64: 5 | G64: 5 | H64: 5 | I64: 5 | J64: 5 | K64: 5 | L64: 5 | M64: 5 | N64: 5 | O64: 5 | P64: 5
A65: Peak Days | C65: 2 | D65: 2 | E65: 2 | F65: 2 | G65: 2 | H65: 2 | I65: 2 | J65: 2 | K65: 2 | L65: 2 | M65: 2 | N65: 2 | O65: 2 | P65: 2 | Q65: 2 | R65: 2 | U65: Weekly Hours
A66: Service Days | C66: =C65+C64 -> 7 | D66: =D65+D64 -> 7 | E66: =E65+E64 -> 7 | F66: =F65+F64 -> 7 | G66: =G65+G64 -> 7 | H66: =H65+H64 -> 7 | I66: =I65+I64 -> 7 | J66: =J65+J64 -> 7 | ... R66: =R65+R64 -> 2 | U66: =SUM(B68:T68) -> 160 | AH66: 240 | AI66: 175 | AJ66: =AI66-AH66 -> -65
A67: SERVICE BY HOUR | U67: =SUM(B69:T69) -> 64 | AH67: =28294*AH66 -> 6790560 | AI67: =28294*175 -> 4951450 | AJ67: =AI67-AH67 -> -1839110
A68: Nonpeak days | C68: =C63*C64 -> 10 | D68: =D63*D64 -> 10 | E68: =E63*E64 -> 10 | F68: =F63*F64 -> 10 | G68: =G63*G64 -> 5 | H68: =H63*H64 -> 5 | I68: =I63*I64 -> 5 | J68: =J63*J64 -> 5 | ... R68: =R63*R64 -> 0 | U68: =SUM(U66:U67) -> 224 | V68: =U68*U62 -> 1792 | W68: =V68*'VRH Rates'!D5 -> 152320 | X68: =V68*'Avg Pass, Mile Per Hr'!C9 -> 22937.6 | Y68: =V68*'Avg Pass, Mile Per Hr'!C3 -> 12544 | Z68: =Y68*'Fare Assumptions'!C5 -> 62720
A69: Peak Days | C69: =C63*C65 -> 4 | D69: =D63*D65 -> 4 | E69: =E63*E65 -> 4 | F69: =F63*F65 -> 4 | G69: =G63*G65 -> 2 | H69: =H63*H65 -> 2 | I69: =I63*I65 -> 2 | J69: =J63*J65 -> 2 | ... R69: =R63*R65 -> 0
A70: Total Service Hours - by hour of the day | C70: =SUM(C68:C69) -> 14 | D70: =SUM(D68:D69) -> 14 | E70: =SUM(E68:E69) -> 14 | F70: =SUM(F68:F69) -> 14 | G70: =SUM(G68:G69) -> 7 | H70: =SUM(H68:H69) -> 7 | I70: =SUM(I68:I69) -> 7 | J70: =SUM(J68:J69) -> 7 | ... R70: =SUM(R68:R69) -> 0
U71: Weeks | V71: VRH | W71: Expenses | X71: VRM | Y71: Passengers | Z71: Fares
A72: SERVICE HOURS PEAK SEASON [JAN, FEB, MAR, JUN, JUL, AUG] | U72: 27
A73: Vehicles | C73: 2 | D73: 2 | E73: 2 | F73: 2 | G73: 2 | H73: 2 | I73: 2 | J73: 2 | K73: 2 | L73: 2 | M73: 2 | N73: 2 | O73: 2 | P73: 1 | Q73: 1 | R73: 1 | AH73: 260 | AI73: 175 | AJ73: =AI73-AH73 -> -85
A74: Nonpeak days | C74: 5 | D74: 5 | E74: 5 | F74: 5 | G74: 5 | H74: 5 | I74: 5 | J74: 5 | K74: 5 | L74: 5 | M74: 5 | N74: 5 | O74: 5 | P74: 5 | AH74: =28294*AH73 -> 7356440 | AI74: =28294*175 -> 4951450 | AJ74: =AI74-AH74 -> -2404990
A75: Peak Days | C75: 2 | D75: 2 | E75: 2 | F75: 2 | G75: 2 | H75: 2 | I75: 2 | J75: 2 | K75: 2 | L75: 2 | M75: 2 | N75: 2 | O75: 2 | P75: 2 | Q75: 2 | R75: 2 | U75: Weekly Hours
A76: Service Days | C76: =C75+C74 -> 7 | D76: =D75+D74 -> 7 | E76: =E75+E74 -> 7 | F76: =F75+F74 -> 7 | G76: =G75+G74 -> 7 | H76: =H75+H74 -> 7 | I76: =I75+I74 -> 7 | J76: =J75+J74 -> 7 | ... R76: =R75+R74 -> 2 | U76: =SUM(B78:T78) -> 135
A77: SERVICE BY HOUR | U77: =SUM(B79:T79) -> 58
A78: Nonpeak days | C78: =C73*C74 -> 10 | D78: =D73*D74 -> 10 | E78: =E73*E74 -> 10 | F78: =F73*F74 -> 10 | G78: =G73*G74 -> 10 | H78: =H73*H74 -> 10 | I78: =I73*I74 -> 10 | J78: =J73*J74 -> 10 | ... R78: =R73*R74 -> 0 | U78: =SUM(U76:U77) -> 193 | V78: =U78*U72 -> 5211 | W78: =V78*'VRH Rates'!D5 -> 442935 | X78: =V78*'Avg Pass, Mile Per Hr'!C9 -> 66700.8 | Y78: =V78*'Avg Pass, Mile Per Hr'!C3 -> 36477 | Z78: =Y78*'Fare Assumptions'!C5 -> 182385
A79: Peak Days | C79: =C73*C75 -> 4 | D79: =D73*D75 -> 4 | E79: =E73*E75 -> 4 | F79: =F73*F75 -> 4 | G79: =G73*G75 -> 4 | H79: =H73*H75 -> 4 | I79: =I73*I75 -> 4 | J79: =J73*J75 -> 4 | ... R79: =R73*R75 -> 2
A80: Total Service Hours - by hour of the day | C80: =SUM(C78:C79) -> 14 | D80: =SUM(D78:D79) -> 14 | E80: =SUM(E78:E79) -> 14 | F80: =SUM(F78:F79) -> 14 | G80: =SUM(G78:G79) -> 14 | H80: =SUM(H78:H79) -> 14 | I80: =SUM(I78:I79) -> 14 | J80: =SUM(J78:J79) -> 14 | ... R80: =SUM(R78:R79) -> 2
U81: Weeks | V81: VRH | W81: Expenses | X81: VRM | Y81: Passengers | Z81: Fares
A82: SERVICE HOURS OFF-PEAK SEASON [SEP, DEC, APR, MAY] | U82: 17
A83: Vehicles | C83: 2 | D83: 2 | E83: 2 | F83: 2 | G83: 2 | H83: 2 | I83: 2 | J83: 1 | K83: 1 | L83: 1 | M83: 2 | N83: 2 | O83: 2 | P83: 1 | Q83: 1 | R83: 1
A84: Nonpeak days | C84: 5 | D84: 5 | E84: 5 | F84: 5 | G84: 5 | H84: 5 | I84: 5 | J84: 5 | K84: 5 | L84: 5 | M84: 5 | N84: 5 | O84: 5 | P84: 5
A85: Peak Days | C85: 2 | D85: 2 | E85: 2 | F85: 2 | G85: 2 | H85: 2 | I85: 2 | J85: 2 | K85: 2 | L85: 2 | M85: 2 | N85: 2 | O85: 2 | P85: 2 | Q85: 2 | R85: 2 | U85: Weekly Hours
A86: Service Days | C86: =C85+C84 -> 7 | D86: =D85+D84 -> 7 | E86: =E85+E84 -> 7 | F86: =F85+F84 -> 7 | G86: =G85+G84 -> 7 | H86: =H85+H84 -> 7 | I86: =I85+I84 -> 7 | J86: =J85+J84 -> 7 | ... R86: =R85+R84 -> 2 | U86: =SUM(B88:T88) -> 120
A87: SERVICE BY HOUR | U87: =SUM(B89:T89) -> 52
A88: Nonpeak days | C88: =C83*C84 -> 10 | D88: =D83*D84 -> 10 | E88: =E83*E84 -> 10 | F88: =F83*F84 -> 10 | G88: =G83*G84 -> 10 | H88: =H83*H84 -> 10 | I88: =I83*I84 -> 10 | J88: =J83*J84 -> 5 | ... R88: =R83*R84 -> 0 | U88: =SUM(U86:U87) -> 172 | V88: =U88*U82 -> 2924 | W88: =V88*'VRH Rates'!D5 -> 248540 | X88: =V88*'Avg Pass, Mile Per Hr'!C9 -> 37427.2 | Y88: =V88*'Avg Pass, Mile Per Hr'!C3 -> 20468 | Z88: =Y88*'Fare Assumptions'!C5 -> 102340
A89: Peak Days | C89: =C83*C85 -> 4 | D89: =D83*D85 -> 4 | E89: =E83*E85 -> 4 | F89: =F83*F85 -> 4 | G89: =G83*G85 -> 4 | H89: =H83*H85 -> 4 | I89: =I83*I85 -> 4 | J89: =J83*J85 -> 2 | ... R89: =R83*R85 -> 2
A90: Total Service Hours - by hour of the day | C90: =SUM(C88:C89) -> 14 | D90: =SUM(D88:D89) -> 14 | E90: =SUM(E88:E89) -> 14 | F90: =SUM(F88:F89) -> 14 | G90: =SUM(G88:G89) -> 14 | H90: =SUM(H88:H89) -> 14 | I90: =SUM(I88:I89) -> 14 | J90: =SUM(J88:J89) -> 7 | ... R90: =SUM(R88:R89) -> 2 | U90: Meyers | V90: =V88+V78+V68 -> 9927 | W90: =W88+W78+W68 -> 843795 | X90: =X88+X78+X68 -> 127065.6 | Y90: =Y88+Y78+Y68 -> 69489 | Z90: =Z88+Z78+Z68 -> 347445
U91: Total | V91: =V90+V56+V42+V33 -> 74005 | W91: =W90+W56+W42+W33 -> 6290425 | X91: =X90+X56+X42+X33 -> 947545.63 | Y91: =Y90+Y56+Y42+Y33 -> 518035 | Z91: =Z90+Z56+Z42+Z33 -> 861525
U92: Fixed Route and Vanpool
A93: Route 50 - Y to Kingsbury | U93: fx 50 | V93: 16420 | W93: =V93*'VRH Rates'!D6 -> 2873500 | X93: =V93*'Avg Pass, Mile Per Hr'!C10 -> 229880 | Y93: =V93*'Avg Pass, Mile Per Hr'!C5 -> 328400 | Z93: =V93*'Avg Pass, Mile Per Hr'!C5 -> 328400
A94: Fixed Route 19/22 Interlined | U94: fx19/22 Interlined | V94: 6786 | W94: =V94*'VRH Rates'!D6 -> 1187550 | X94: =V94*'Avg Pass, Mile Per Hr'!C10 -> 95004 | Y94: 27906 | Z94: =Y94*'Fare Assumptions'!C6 -> 195342
A95: Fixed Route 28 East Shore Express | U95: fx 28 East Shore Express | V95: 2553 | W95: =V95*'VRH Rates'!D6 -> 446775 | X95: =V95*'Avg Pass, Mile Per Hr'!C10 -> 35742 | Y95: 25795 | Z95: =Y95*'Fare Assumptions'!C6 -> 180565
U96: Total | W96: =W95+W94+W93+W91 -> 10798250 | X96: =X95+X94+X93+X91 -> 1308171.6 | Y96: =Y95+Y94+Y93+Y91 -> 900136 | Z96: =Z95+Z94+Z93+Z91 -> 1565832
U97: Vanpool (VP) | W97: ='FY27 Financial Forecast'!I71 -> 432000 | X97: =(30*30*2)*254 -> 457200 | Y97: 25000
U98: Grand Total | W98: =W96+W97 -> 11230250
U99: Route 50 + Micro | V99: =V91+V93 -> 90425 | W99: =W91+W93 -> 9163925 | X99: =X91+X93 -> 1177425.6 | Y99: =Y91+Y93 -> 846435 | Z99: =Z91+Z93 -> 1189925
U100: Routes 19,22,28 + VP | V100: =V94+V95 -> 9339 | W100: =W94+W95+W97 -> 2066325 | X100: =X94+X95+X97 -> 587946 | Y100: =Y94+Y95+Y97 -> 78701 | Z100: =Z94+Z95+Z97 -> 375907
U101: Total all Modes | V101: =V99+V100 -> 99764 | W101: =W99+W100 -> 11230250 | X101: =X99+X100 -> 1765371.6 | Y101: =Y99+Y100 -> 925136 | Z101: =Z99+Z100 -> 1565832

Sheet Zone 1-5 Peak Vehicles
B3: PEAK VEHICLE DEMAND
E4: Early AM
B5: SERVICE HOURS OFF-PEAK SEASON [OCT, NOVEMBER] | C5: Peak | D5: Off-Peak | E5: Off-Peak
B6: Zone 1 | C6: 2 | D6: 1.5 | E6: 1
B7: Zone 2 | C7: 3 | D7: 3 | E7: 3
B8: Zone 3 | C8: 1 | D8: 1 | E8: 2
B9: Zone 4 | C9: 1 | D9: 1
B10: Zone 5 | C10: 2 | D10: 1.5 | E10: 1
B11: ADA Overflow | C11: 1 | D11: 1 | E11: 1
B12: Total | C12: =SUM(C6:C11) -> 10 | D12: =SUM(D6:D11) -> 9 | E12: =SUM(E6:E11) -> 8
E14: Early AM
B15: SERVICE HOURS PEAK SEASON [JAN, FEB, MAR, JUN, JUL, AUG] | C15: Peak | D15: Off-Peak | E15: Off-Peak
B16: Zone 1 | C16: 2 | D16: 2 | E16: 1
B17: Zone 2 | C17: 4 | D17: 3 | E17: 3
B18: Zone 3 | C18: 1 | D18: 1 | E18: 2
B19: Zone 4 | C19: 1 | D19: 1
B20: Zone 5 | C20: 2 | D20: 2 | E20: 1
B21: ADA Overflow | C21: 1 | D21: 1 | E21: 1
B22: Total | C22: =SUM(C16:C21) -> 11 | D22: =SUM(D16:D21) -> 10 | E22: =SUM(E16:E21) -> 8
B24: SERVICE HOURS OFF-PEAK SEASON [SEP, DEC, APR, MAY] | C24: Peak | D24: Off-Peak | E24: Off-Peak
B25: Zone 1 | C25: 2 | D25: 2 | E25: 1
B26: Zone 2 | C26: 4 | D26: 3 | E26: 3
B27: Zone 3 | C27: 1 | D27: 1 | E27: 2
B28: Zone 4 | C28: 1 | D28: 1
B29: Zone 5 | C29: 2 | D29: 2 | E29: 1
B30: ADA Overflow | C30: 1 | D30: 1 | E30: 1
B31: Total | C31: =SUM(C25:C30) -> 11 | D31: =SUM(D25:D30) -> 10 | E31: =SUM(E25:E30) -> 8

Sheet FY27 Financial Forecast
C1: DRAFT
C2: EXAMPLE 5 YEAR FINANCIAL MODEL - Operating
C3: Revenue & Expense Assumptions (10/1/26 - 09/30/31) | P3: need to address local match for route 19/22, 28 Urban UZA vs Rural
A6: 34 | C6: Revenue Sources | I6: FY2027 | J6: FY2028 | K6: FY2029 | L6: FY2023 | M6: FY2031 | N6: Total
A7: 35 | C7: Caltrans Congestion Mitigation Air Quality (CMAQ) | I7: =500000*0.7 -> 350000 | J7: =500000*0.7 -> 350000 | K7: =500000*0.7 -> 350000 | L7: =500000*0.7 -> 350000 | M7: =500000*0.7 -> 350000 | N7: =SUM(I7:M7) -> 1750000
A8: 37 | C8: Federal Transit Administration Allocations
A9: 41 | C9: FTA 5307 Block Grant | I9: ='FTA FY27 Sub Allocation Exampl '!J32 -> 1322921 | J9: =I9*1.01 -> 1336150.2 | K9: =J9*1.01 -> 1349511.7 | L9: =K9*1.01 -> 1363006.8 | M9: =L9*1.01 -> 1376636.9 | N9: =SUM(I9:M9) -> 6748226.5
A10: 42 | C10: FTA 5311 Allocation (For Portion of Rural El Dorado County) covered by JPA - Funidng Source may need to come from El Dorado County Transit??? | I10: 0 | J10: 0 | K10: 0 | L10: 0 | M10: 0 | N10: =SUM(I10:M10) -> 0
A11: 43 | C11: FTA 5310 Elderly & Disabilities | N11: =SUM(I11:M11) -> 0
A12: 44 | C12: California Transportation Development Act (TDA)
A13: 45 | C13: SGR Growth Projected at 1.5% annually (state of good repair) | N13: =SUM(I13:M13) -> 0
C14: LTF (JPA Full Amount?) (Growth Projected at 1.5% annually) | I14: 1338438 | J14: =I14*1.015 -> 1358514.6 | K14: =J14*1.015 -> 1378892.3 | L14: =K14*1.015 -> 1399575.7 | M14: =L14*1.015 -> 1420569.3 | N14: =SUM(I14:M14) -> 6895989.8
C15: STA (Growth Projected at 1.5% annually) | I15: =1363577*('FTA FY27 Sub Allocation Exampl '!I22) -> 900611.55 | J15: =I15*1.015 -> 914120.72 | K15: =J15*1.015 -> 927832.54 | L15: =K15*1.015 -> 941750.02 | M15: =L15*1.015 -> 955876.27 | N15: =SUM(I15:M15) -> 4640191.1
C16: Surface Transportation Block Grant (STBG) ??? | N16: =SUM(I16:M16) -> 0
C17: City of South Lake Tahoe | I17: 1150000 | J17: 1150000 | K17: 1200000 | L17: 1400000 | M17: 1560000 | N17: =SUM(I17:M17) -> 6460000
C18: El Dorado County | I18: 400000 | J18: 400000 | K18: 400000 | L18: 400000 | M18: 400000 | N18: =SUM(I18:M18) -> 2000000
C19: SSTMA Funding Partners: Event Center, Douglas County, LTVA, TDVA, Others
C20: Event Center | I20: 350000 | J20: 350000 | K20: 350000 | L20: 350000 | M20: 350000 | N20: =SUM(I20:M20) -> 1750000
C21: Douglas County | I21: 600000 | J21: 600000 | K21: 600000 | L21: 600000 | M21: 600000 | N21: =SUM(I21:M21) -> 3000000
C22: LTVA | I22: 50000 | J22: 50000 | K22: 50000 | L22: 50000 | M22: 50000 | N22: =SUM(I22:M22) -> 250000
C23: Other Partners | I23: 100000 | J23: 100000 | K23: 100000 | L23: 100000 | M23: 100000 | N23: =SUM(I23:M23) -> 500000
C24: Parking Revenue
C25: TBID/TOT, Other | J25: 1700000 | K25: 2100000 | L25: 2100000 | M25: 2200000 | N25: =SUM(I25:M25) -> 8100000
C26: CAT 7/10 FHWY | N26: =SUM(I26:M26) -> 0
C27: California SB125 (California) South Shore Transit Operations Support (must be a TDA Operator)* | I27: =1768000 -> 1768000 | J27: =400000-106820 -> 293180 | N27: =SUM(I27:M27) -> 2061180
C28: *$13M allocated $4M for south shore operations $2.1 unallocated
C29: Emerald Bay Fares = $15 per ride, each way | I29: ='Operating '!Z56 -> 514080 | J29: =I29 -> 514080 | K29: =J29 -> 514080 | L29: =K29 -> 514080 | M29: =L29 -> 514080 | N29: =SUM(I29:M29) -> 2570400
C30: Meyers Fare = $5.00 Downtowner+Uber | I30: ='Operating '!Z90 -> 347445 | J30: =I30 -> 347445 | K30: =J30 -> 347445 | L30: =K30 -> 347445 | M30: =L30 -> 347445 | N30: =SUM(I30:M30) -> 1737225
C32: Total Revenue All Sources | I32: =SUM(I7:I31) -> 9191495.5 | J32: =SUM(J7:J31) -> 9463490.5 | K32: =SUM(K7:K31) -> 9667761.5 | L32: =SUM(L7:L31) -> 9915857.5 | M32: =SUM(M7:M31) -> 10224607 | N32: =SUM(I32:M32) -> 48463212
C33: Total Lake Link Operating Expenses by year | I33: ='Operating '!W33 -> 4411670 | J33: =I33*1.025 -> 4521961.8 | K33: =J33*1.025 -> 4635010.8 | L33: =K33*1.025 -> 4750886.1 | M33: =L33*1.025 -> 4869658.2 | N33: =SUM(I33:M33) -> 23189187
C34: Total Fx Bus Operting Expenses by year | I34: ='Operating '!W93 -> 2873500 | J34: =I34*1.025 -> 2945337.5 | K34: =J34*1.025 -> 3018970.9 | L34: =K34*1.025 -> 3094445.2 | M34: =L34*1.025 -> 3171806.3 | N34: =SUM(I34:M34) -> 15104060
C35: Total Projected Operating Expenses (Lake Link + fx bus) | I35: =SUM(I33:I34) -> 7285170 | J35: =SUM(J33:J34) -> 7467299.2 | K35: =SUM(K33:K34) -> 7653981.7 | L35: =SUM(L33:L34) -> 7845331.3 | M35: =SUM(M33:M34) -> 8041464.6 | N35: =SUM(I35:M35) -> 38293247
C36: Zone 6 LTCC to Stateline Service | I36: ='Operating '!W42 -> 618800 | J36: =I36*1.025 -> 634270 | K36: =J36*1.025 -> 650126.75 | L36: =K36*1.025 -> 666379.92 | M36: =L36*1.025 -> 683039.42 | N36: =SUM(I36:M36) -> 3252616.1
C37: Total Projected Operating Expenses (w/Zone 6) | I37: =I35+I36 -> 7903970 | J37: =J35+J36 -> 8101569.2 | K37: =K35+K36 -> 8304108.5 | L37: =L35+L36 -> 8511711.2 | M37: =M35+M36 -> 8724504 | N37: =N35+N36 -> 41545863
C38: South Lake Tahoe Portions of Route 19 | J38: =I38*1.025 -> 0 | K38: =J38*1.025 -> 0 | L38: =K38*1.025 -> 0 | M38: =L38*1.025 -> 0 | N38: =M38*1.025 -> 0
C39: Total Projected Operating Expenses (w/Routee 19) | I39: =I37+I38 -> 7903970 | J39: =J37+J38 -> 8101569.2 | K39: =K37+K38 -> 8304108.5 | L39: =L37+L38 -> 8511711.2 | M39: =M37+M38 -> 8724504 | N39: =N37+N38 -> 41545863
C40: South Lake Tahoe Portions of Route 22 | J40: =I40*1.025 -> 0 | K40: =J40*1.025 -> 0 | L40: =K40*1.025 -> 0 | M40: =L40*1.025 -> 0 | N40: =M40*1.025 -> 0
C41: Total Projected Operating Expenses (w/Route 22) | I41: =I39+I40 -> 7903970 | J41: =J39+J40 -> 8101569.2 | K41: =K39+K40 -> 8304108.5 | L41: =L39+L40 -> 8511711.2 | M41: =M39+M40 -> 8724504 | N41: =N39+N40 -> 41545863
C42: South Lake Tahoe Portions of Route 28 Eeast Shore Express | J42: =I42*1.025 -> 0 | K42: =J42*1.025 -> 0 | L42: =K42*1.025 -> 0 | M42: =L42*1.025 -> 0 | N42: =M42*1.025 -> 0
C43: Total Projected Operating Expenses (w/Route 28) | I43: =I41+I42 -> 7903970 | J43: =J41+J42 -> 8101569.2 | K43: =K41+K42 -> 8304108.5 | L43: =L41+L42 -> 8511711.2 | M43: =M41+M42 -> 8724504 | N43: =N41+N42 -> 41545863
C44: Zone 7 Emerald Bay Reservation Service Expense | I44: ='Operating '!W56 -> 416160 | J44: =I44*1.025 -> 426564 | K44: =J44*1.025 -> 437228.1 | L44: =K44*1.025 -> 448158.8 | M44: =L44*1.025 -> 459362.77 | N44: =SUM(I44:M44) -> 2187473.7
C45: Total Projected Operating Expenses (w/Zone 7) | I45: =I43+I44 -> 8320130 | J45: =J43+J44 -> 8528133.2 | K45: =K43+K44 -> 8741336.6 | L45: =L43+L44 -> 8959870 | M45: =M37+M44 -> 9183866.7 | N45: =N37+N44 -> 43733337
C46: Zone 8 Meyers Service w/uber | I46: ='Operating '!W90 -> 843795 | J46: =I46*1.025 -> 864889.87 | K46: =J46*1.025 -> 886512.12 | L46: =K46*1.025 -> 908674.92 | M46: =L46*1.025 -> 931391.8 | N46: =SUM(I46:M46) -> 4435263.7
C47: Total Projected Operating Expenses (w/Zone8) | I47: =I45+I46 -> 9163925 | J47: =J45+J46 -> 9393023.1 | K47: =K45+K46 -> 9627848.7 | L47: =L45+L46 -> 9868544.9 | M47: =M45+M46 -> 10115259 | N47: =N45+N46 -> 48168600
C48: unallocated funds/shorfall | I48: =I32-I47 -> 27570.52 | J48: =J32-J47 -> 70467.348 | K48: =K32-K47 -> 39912.801 | L48: =L32-L47 -> 47312.573 | M48: =M32-M47 -> 109348.9 | N48: =N32-N47 -> 294612.15
C49: ROUTES 19/22, 28
C50: Revenue Sources
C51: Caltrans Congestion Mitigation Air Quality (CMAQ) | I51: 150000 | J51: 150000 | K51: 150000 | L51: 150000 | M51: 150000 | N51: =SUM(I51:M51) -> 750000
C52: Federal Transit Administration Allocations
C53: FTA 5307 Allocation - Federal Apportionment Allocation to Route 28 | I53: ='FTA FY27 Sub Allocation Exampl '!J31 -> 594355.8 | J53: =I53*1.01 -> 600299.36 | K53: =J53*1.01 -> 606302.35 | L53: =K53*1.01 -> 612365.37 | M53: =L53*1.01 -> 618489.03 | N53: =SUM(I53:M53) -> 3031811.9
C54: FTA 5311 Allocation (For Portion of Rural El Dorado County) covered by JPA - Funidng Source may need to come from El Dorado County Transit??? | I54: 0 | J54: 0 | K54: 0 | L54: 0 | M54: 0 | N54: =SUM(I54:M54) -> 0
C55: FTA 5311 Allocation - Federal Apportionment through NDOT Route 19 & 22 | I55: =1196991/2 -> 598495.5 | J55: =I55*1.01 -> 604480.45 | K55: =J55*1.01 -> 610525.26 | L55: =K55*1.01 -> 616630.51 | M55: =L55*1.01 -> 622796.82 | N55: =SUM(I55:M55) -> 3052928.5
C56: FTA 5310 | N56: =SUM(I56:M56) -> 0
C57: Nevada State Funding
C58: TART/Washoe Portion of Route 28 - State or local match needed | N58: =SUM(I58:M58) -> 0
C59: Douglas County/DART ((Portion of Route 22) - State or local match needed | J59: =I59*1.025 -> 0 | K59: =J59*1.025 -> 0 | L59: =K59*1.025 -> 0 | M59: =L59*1.025 -> 0 | N59: =SUM(I59:M59) -> 0
C61: Carson City (Portion of Route 19x) - State or local match needed | J61: =I61*1.025 -> 0 | K61: =J61*1.025 -> 0 | L61: =K61*1.025 -> 0 | M61: =L61*1.025 -> 0 | N61: =SUM(I61:M61) -> 0
C62: Parking Revenue
C63: Nevada Department of Conservation & National Resources | I63: 85000 | J63: 85000 | K63: 85000 | L63: 85000 | M63: 85000 | N63: =SUM(I63:M63) -> 425000
C64: State of Nevada Funded - Vanpool | I64: =30*1200*12 -> 432000 | J64: =30*1300*12 -> 468000 | K64: =30*1400*12 -> 504000 | L64: =30*1500*12 -> 540000 | M64: =30*1600*12 -> 576000 | N64: =SUM(I64:M64) -> 2520000 | R64: =30*5*254*2 -> 76200
C65: Route 19X Interlined Fare = Proposed $7 oneway fare (local) $ 15 Regional? | I65: ='Operating '!Z94/2 -> 97671 | J65: =I65 -> 97671 | K65: =J65 -> 97671 | L65: =K65*1.05 -> 102554.55 | M65: =L65 -> 102554.55 | N65: =SUM(I65:M65) -> 498122.1
C66: Route 22 Interlined Fare = Proposed $7 oneway fare (local) $ 15 Regional? | I66: ='Operating '!Z94/2 -> 97671 | J66: =I66 -> 97671 | K66: =J66 -> 97671 | L66: =K66*1.05 -> 102554.55 | M66: =L66 -> 102554.55 | N66: =SUM(I66:M66) -> 498122.1
C67: Route 28 = $7 oneway Fare | I67: ='Operating '!Z95 -> 180565 | J67: =I67 -> 180565 | K67: =J67 -> 180565 | L67: =K67*1.05 -> 189593.25 | M67: =L67 -> 189593.25 | N67: =SUM(I67:M67) -> 920881.5
C68: Revenue Sources | I68: =SUM(I51:I67) -> 2235758.3 | J68: =SUM(J51:J67) -> 2283686.8 | K68: =SUM(K51:K67) -> 2331734.6 | L68: =SUM(L51:L67) -> 2398698.2 | M68: =SUM(M51:M67) -> 2446988.2 | N68: =SUM(I68:M68) -> 11696866
C69: Route 19 | I69: ='Operating '!W94/2 -> 593775 | J69: =I69*1.025 -> 608619.38 | K69: =J69*1.025 -> 623834.86 | L69: =K69*1.025 -> 639430.73 | M69: =L69*1.025 -> 655416.5 | N69: =SUM(I69:M69) -> 3121076.5
C70: Route 22 | I70: ='Operating '!W94/2 -> 593775 | J70: =I70*1.025 -> 608619.38 | K70: =J70*1.025 -> 623834.86 | L70: =K70*1.025 -> 639430.73 | M70: =L70*1.025 -> 655416.5 | N70: =SUM(I70:M70) -> 3121076.5
C71: Vanpools = Alternate to Route 19 & 22 cost shown in addition to fixed routs 19/22 for modeling | I71: =I64 -> 432000 | J71: =J64 -> 468000 | K71: =K64 -> 504000 | L71: =L64 -> 540000 | M71: =M64 -> 576000 | N71: =SUM(I71:M71) -> 2520000
C72: Route 28 | I72: ='Operating '!W95 -> 446775 | J72: =I72*1.025 -> 457944.37 | K72: =J72*1.025 -> 469392.98 | L72: =K72*1.025 -> 481127.81 | M72: =L72*1.025 -> 493156 | N72: =SUM(I72:M72) -> 2348396.2
C73: Projected Operating Expenses | I73: =SUM(I69:I72) -> 2066325 | J73: =SUM(J69:J72) -> 2143183.1 | K73: =SUM(K69:K72) -> 2221062.7 | L73: =SUM(L69:L72) -> 2299989.3 | M73: =SUM(M69:M72) -> 2379989 | N73: =SUM(N69:N70) -> 6242152.9
C74: Unallocated funds | I74: =I68-I73 -> 169433.3 | J74: =J68-J73 -> 140503.69 | K74: =K68-K73 -> 110671.91 | L74: =L68-L73 -> 98708.964 | M74: =M68-M73 -> 66999.191 | N74: =N68-N73 -> 5454713.2
C75: Unallocated 5311 FTA Allocation Available for drawdown with state or local match | I75: =I53 -> 594355.8 | J75: =I75*1.01 -> 600299.36 | K75: =J75*1.01 -> 606302.35 | L75: =K75*1.01 -> 612365.37 | M75: =L75*1.01 -> 618489.03 | N75: =SUM(I75:M75) -> 3031811.9
C77: Grand Total Revenue | I77: =I68+I32 -> 11427254 | J77: =J68+J32 -> 11747177 | K77: =K68+K32 -> 11999496 | L77: =L68+L32 -> 12314556 | M77: =M68+M32 -> 12671596 | N77: =SUM(I77:M77) -> 60160079
C78: Grand Total Expenses | I78: =I73+I47 -> 11230250 | J78: =J73+J47 -> 11536206 | K78: =K73+K47 -> 11848911 | L78: =L73+L47 -> 12168534 | M78: =M73+M47 -> 12495248 | N78: =SUM(I78:M78) -> 59279149
C79: Unallocated | I79: =I77-I78 -> 197003.82 | J79: =J77-J78 -> 210971.03 | K79: =K77-K78 -> 150584.71 | L79: =L77-L78 -> 146021.54 | M79: =M77-M78 -> 176348.09 | N79: =N77-N78 -> 880929.19
C81: Federal
C85: Caltrans Transportation Development Credits from Tolls (CAPx)
C86: FTA 5339 (Prior Years) Allocable to California & Nevada Service Area Operated by JPA
C87: FTA 5339 Future Years
C89: FTA 5307 CAPITAL, can be used for Opex
C91: Total Capital
C92: Possible Transportation Toll Credits = 20%
C94: Total Projected FY27 Capital Funding | I94: =I91+I92 -> 0 | J94: =J91+J92 -> 0 | K94: =K91+K92 -> 0 | L94: =L91+L92 -> 0 | M94: =M91+M92 -> 0 | N94: =SUM(I94:M94) -> 0
I95: =I92+I93 -> 0 | J95: =J92+J93 -> 0 | K95: =K92+K93 -> 0 | L95: =L92+L93 -> 0 | M95: =M92+M93 -> 0 | N95: =SUM(I95:M95) -> 0
C96: Allocation of Prior Years Federal 5307 Attributal to South Shore Services | I96: ??? | J96: ??? | K96: ??? | L96: ??? | M96: ??? | N96: ???
C97: Allocation of Prior Years Federal 5310 Attributal to South Shore Services | I97: ??? | J97: ??? | K97: ??? | L97: ??? | M97: ??? | N97: ???
C98: Allocation of Prior Years Federal Descreationary Funding | I98: ??? | J98: ??? | K98: ??? | L98: ??? | M98: ??? | N98: ???
C99: Allocation of Prior Years Federal Comptetitive Grant Funding | I99: ??? | J99: ??? | K99: ??? | L99: ??? | M99: ??? | N99: ???
C100: Bus & Bus Failicities
C101: Zero Emissions
C102: Other

Sheet FTA FY27 Sub Allocation Exampl 
B2: FEDERAL FUNDING APPORTIONMENT DISCUSSIONS AND "EXAMPLE" DATA
B4: FTA Sub-Allocation (5307, 5339, 5310)
F5: https://www.transit.dot.gov/funding/apportionments/current-apportionments
K7: 1. Updated with current NTD information
C8: EXAMPLE Using Proposed 2027 Forecasted Regional Model | K8: 2. Updated Allocation amounts from the FTA Apportionment table
C9: TTD | D9: Revenue Miles (urban) | G9: Ridership
D10: fx +micro | E10: ='Operating '!X99 -> 1177425.6 | F10: =E10/D22 -> 0.66695624 | I10: ='Operating '!Y101 -> 925136 | J10: =I10/I12 -> 0.60659246 | K10: Miles + Ridership
D11: 19/22+28+VP | E11: ='Operating '!X100 -> 587946 | F11: =E11/D22 -> 0.33304376 | G11: Placer-TART | I11: 600000 | J11: =I11/I12 -> 0.39340754
C12: Placer-TART | D12: Revenue Miles (urban) | I12: =SUM(I10:I11) -> 1525136
D13: CA | E13: 596889
D14: NV | E14: 85857 | G14: FY24 FTA Allocation 5307 | I14: 5339 | J14: 5310
C15: Population (US Census) | G15: CA | H15: 2682893 | I15: - | K15: =H15/H17 -> 0.68753098
C16: TTD | D16: 31420 | E16: 2020 Census | G16: NV | H16: 1219321 | I16: - | J16: - | K16: =H16/H17 -> 0.31246902
C17: Placer-TART | D17: 16643 | E17: 2020 Census | G17: TOTAL | H17: =SUM(H15:H16) -> 3902214 | I17: 345232 | J17: 64333
C20: Earned Share Factors
D21: Revenue Miles Factor | F21: Population Factor | H21: Ridership Factor | I21: Forecasted % in 2027
C22: TTD | D22: =E10+E11 -> 1765371.6 | E22: =D22/D24 -> 0.72111389 | F22: =D16 -> 31420 | G22: =F22/F24 -> 0.65372532 | H22: =I10/(I10+I11) -> 0.60659246 | I22: =(E22+G22+H22)/3 -> 0.66047722
C23: Placer | D23: =E13+E14 -> 682746 | E23: =D23/D24 -> 0.27888611 | F23: =D17 -> 16643 | G23: =F23/F24 -> 0.34627468 | H23: =I11/(I10+I11) -> 0.39340754 | I23: =(E23+G23+H23)/3 -> 0.33952278
C24: Total | D24: =SUM(D22:D23) -> 2448117.6 | F24: =SUM(F22:F23) -> 48063
C26: 2024 Base + Earned Allocations | H26: "EXAMPLE" Totals by Operator (Earned + Base)
D27: 5307-Base | E27: 5307-Earned | I27: 5307-Total | J27: 5307-Ops (75%) | K27: 5307-Cap (25%) | L27: 5339 | M27: 5310
C28: TTD | D28: 1300000 | E28: =(H17-D30)*I22 -> 1256369 | H28: TTD | I28: =D28+E28 -> 2556369 | J28: =I28*0.75 -> 1917276.8 | K28: =I28*0.25 -> 639092.26 | L28: =I17*I22 -> 228017.87 | M28: 64333
C29: Placer | D29: 700000 | E29: =(H17-D30)*I23 -> 645844.98 | G29: EXAMPLE | H29: Placer | I29: =D29+E29 -> 1345845 | J29: =I29*0.75 -> 1009383.7 | K29: =I29*0.25 -> 336461.24 | L29: =I17*I23 -> 117214.13 | M29: 0
C30: Total | D30: =SUM(D28:D29) -> 2000000 | E30: =SUM(E28:E29) -> 1902214 | G30: *Split | H30: Total | I30: =SUM(I28:I29) -> 3902214 | J30: =SUM(J28:J29) -> 2926660.5 | K30: =SUM(K28:K29) -> 975553.5 | L30: =SUM(L28:L29) -> 345232 | M30: =SUM(M28:M29) -> 64333
E31: =SUM(D30:E30) -> 3902214 | G31: 0.31 | H31: fx 19/22, 28ESxp | I31: =I28*G31 -> 792474.4 | J31: =J28*G31 -> 594355.8 | K31: =K28*G31 -> 198118.6 | L31: =L28*G31 -> 70685.541 | M31: =M28*G31 -> 19943.23
G32: 0.69 | H32: Micro + 50fx | I32: =I28*G32 -> 1763894.6 | J32: =J28*G32 -> 1322921 | K32: =K28*G32 -> 440973.66 | L32: =L28*G32 -> 157332.33 | M32: =M28*G32 -> 44389.77
H33: FY2024 | I33: =SUM(I31:I32) -> 2556369 | J33: =SUM(J31:J32) -> 1917276.8 | K33: =SUM(K31:K32) -> 639092.26 | L33: =SUM(L31:L32) -> 228017.87 | M33: =SUM(M31:M32) -> 64333
G34: *Split should use similar formula focused on area currently served by TTD in California and Nevada

Sheet rt 19,22,28 Cost Share
B2: Determine equitable cost and revenue split for services connnecting multiple regional destination cities based on benefits to each jursidication. What is the ROI?
B3: Determine best service type: Commuter bus, Urban Commuter Bus, Cutaway, Light Duty Van, Vanpool
B4: Determine best operator to deliver the service and develop IGSA bewteen stakeholers directly benefiting from the service
D6: Potential Operator = JAC/Douglas County
D7: Estimated Operating Expense | H7: ='FY27 Financial Forecast'!I69 -> 593775
B8: Route 19 | D8: Carson /JAC | H8: Douglas County | L8: JPA/City of South Lake Tahoe
D9: Miles | E9: Hours | F9: Stops | G9: Ridership | H9: Miles | I9: Hours | J9: Stops | K9: Ridership | L9: Miles | M9: Hours | N9: Stops | O9: Ridership
D10: 0.4 | E10: 0.45 | F10: 0.45 | G10: 0.4 | H10: 0.4 | I10: 0.45 | J10: 0.45 | K10: 0.2 | L10: 0.2 | M10: 0.1 | N10: 0.1 | O10: 0.4
D11: =SUM(D10:G10)/4 -> 0.425 | H11: =SUM(H10:K10)/4 -> 0.375 | L11: =SUM(L10:O10)/4 -> 0.2
D12: =H7*D11 -> 252354.38 | H12: =H7*H11 -> 222665.62 | L12: =H7*L11 -> 118755
C13: Federal 5311 | D13: =D12/2 -> 126177.19 | H13: =H12/2 -> 111332.81
C14: State/Local | D14: =D12/2 -> 126177.19 | H14: =H12/2 -> 111332.81 | L14: =L12 -> 118755
C15: Share | G15: =D12 -> 252354.38 | K15: =H12 -> 222665.62 | O15: =L12 -> 118755
D18: Potential Operator JAC/Douglas County
D19: Estimated Operating Expense | H19: ='FY27 Financial Forecast'!I70 -> 593775
B20: Route 22 | D20: Carson /JAC | H20: Douglas County | L20: JPA/City of South Lake Tahoe
D21: Miles | E21: Hours | F21: Stops | G21: Ridership | H21: Miles | I21: Hours | J21: Stops | K21: Ridership | L21: Miles | M21: Hours | N21: Stops | O21: Ridership
D22: 0.4 | E22: 0.45 | F22: 0.45 | G22: 0.4 | H22: 0.4 | I22: 0.45 | J22: 0.45 | K22: 0.2 | L22: 0.2 | M22: 0.1 | N22: 0.1 | O22: 0.4
D23: =SUM(D22:G22)/4 -> 0.425 | H23: =SUM(H22:K22)/4 -> 0.375 | L23: =SUM(L22:O22)/4 -> 0.2
D24: =H19*D23 -> 252354.38 | H24: =H19*H23 -> 222665.62 | L24: =H19*L23 -> 118755
C25: Federal 5311 | D25: =D24/2 -> 126177.19 | H25: =H24/2 -> 111332.81
C26: State/Local | D26: =D24/2 -> 126177.19 | H26: =H24/2 -> 111332.81 | L26: =L24 -> 118755
C27: Share | G27: =D24 -> 252354.38 | K27: =H24 -> 222665.62 | O27: =L24 -> 118755
D29: Potential Operator TART?
D30: Estimated Operating Expense | H30: ='FY27 Financial Forecast'!I72 -> 446775
B31: Route 28 | D31: TART | H31: Douglas County | L31: JPA/City of South Lake Tahoe
D32: Miles | E32: Hours | F32: Stops | G32: Ridership | H32: Miles | I32: Hours | J32: Stops | K32: Ridership | L32: Miles | M32: Hours | N32: Stops | O32: Ridership
D33: 1 | E33: 1 | F33: 1 | G33: 1
D34: =SUM(D33:G33)/4 -> 1
D35: =H30 -> 446775
C36: Federal 5307 | D36: =D35/2 -> 223387.5
C37: State/Local | D37: =D35/2 -> 223387.5
C38: Share | G38: =D35 -> 446775 | K38: =H35 -> 0 | O38: =L35 -> 0
D41: Potential Operators = JAC/Douglas County/JPA
D42: Estimated Operating Expense | H42: =(30*3000*12)/3 -> 360000
B43: Vanpool Option for Route 19/22 | D43: Carson /JAC | H43: Douglas County | L43: JPA/City of South Lake Tahoe
D44: Miles | E44: Hours | F44: Stops | G44: Ridership | H44: Miles | I44: Hours | J44: Stops | K44: Ridership | L44: Miles | M44: Hours | N44: Stops | O44: Ridership
D45: 0.4 | E45: 0.45 | F45: 0.45 | G45: 0.4 | H45: 0.4 | I45: 0.45 | J45: 0.45 | K45: 0.2 | L45: 0.2 | M45: 0.1 | N45: 0.1 | O45: 0.4
D46: =SUM(D45:G45)/4 -> 0.425 | H46: =SUM(H45:K45)/4 -> 0.375 | L46: =SUM(L45:O45)/4 -> 0.2
D47: =H42*D46 -> 153000 | H47: =H42*H46 -> 135000 | L47: =H42*L46 -> 72000
C48: Federal 5311 | D48: =D47/2 -> 76500 | H48: =H47/2 -> 67500
C49: State/Local | D49: =D47/2 -> 76500 | H49: =H47/2 -> 67500 | L49: =L47 -> 72000
C50: Share | G50: =D47 -> 153000 | K50: =H47 -> 135000 | O50: =L47 -> 72000
C65: Route 19X Interlined Fare = Proposed $7 oneway fare (local) $ 15 Regional?
C66: Route 22 Interlined Fare = Proposed $7 oneway fare (local) $ 15 Regional?

Sheet FTA Sub Allocation 2024 Model
A1: FTA Sub-Allocation (5307, 5339, 5310) | E1: FY24 Full Year Apportionments
E2: https://www.transit.dot.gov/funding/apportionments/current-apportionments
B5: National Transit Database and TRPA LT Info Data (2021/2022)
B6: TTD | C6: Revenue Miles (urban) | F6: Ridership
C7: CA | D7: 266378.81 | F7: TTD | H7: =269576 -> 269576
C8: NV | D8: 157442.19 | F8: Placer-TART | H8: 490752
B9: Placer-TART | C9: Revenue Miles (urban) | H9: =SUM(H7:H8) -> 760328
C10: CA | D10: 625051
C11: NV | D11: 85334 | F11: FY21 FTA Allocation 5307 | H11: 5339 | I11: 5310
B12: Population (US Census) | F12: CA | G12: 2682893 | H12: -
B13: TTD | C13: 31420 | D13: 2020 Census | F13: NV | G13: 1219321 | H13: - | I13: -
B14: Placer-TART | C14: 16643 | D14: 2020 Census | F14: TOTAL | G14: =SUM(G12:G13) -> 3902214 | H14: 356088 | I14: 67399
B17: Earned Share Factors
C18: Revenue Miles Factor | E18: Population Factor | G18: Ridership Factor | H18: Final %
B19: TTD | C19: =D7+D8 -> 423821 | D19: =C19/C21 -> 0.37367198 | E19: =C13 -> 31420 | F19: =E19/E21 -> 0.65372532 | G19: =H7/(H7+H8) -> 0.35455225 | H19: =(D19+F19+G19)/3 -> 0.46064985
B20: Placer | C20: =D10+D11 -> 710385 | D20: =C20/C21 -> 0.62632802 | E20: =C14 -> 16643 | F20: =E20/E21 -> 0.34627468 | G20: =H8/(H7+H8) -> 0.64544775 | H20: =(D20+F20+G20)/3 -> 0.53935015
B21: Total | C21: =SUM(C19:C20) -> 1134206 | E21: =SUM(E19:E20) -> 48063
B23: 5307 Operating Assistance Special Rule - FY24 | G23: Totals by Operator
C24: Max Section 5307 Operating Assistance Allowed 5307(a)(2)(B) | H24: 5307-Total | I24: 5307-Ops (75%) | J24: 5307-Cap (25%) | K24: 5339 | L24: 5310
G25: TTD | H25: 1352065.3 | I25: =H25*0.75 -> 1014049 | J25: =H25*0.25 -> 338016.33 | K25: =H14*H19 -> 164031.88 | L25: 0
B26: TTD | C26: 1014049 | G26: Placer | H26: 2550148.7 | I26: =H26*0.75 -> 1912611.5 | J26: =H26*0.25 -> 637537.17 | K26: =H14*H20 -> 192056.12 | L26: =I14 -> 67399
B27: Placer | C27: 2205277 | G27: Total | H27: =SUM(H25:H26) -> 3902214 | I27: =SUM(I25:I26) -> 2926660.5 | J27: =SUM(J25:J26) -> 975553.5 | K27: =SUM(K25:K26) -> 356088 | L27: =SUM(L25:L26) -> 67399

Sheet FTA FY23 FULL Modified
A1: FTA Sub-Allocation (5307, 5339, 5310) | E1: FY23 Full Year Apportionments
E2: https://www.transit.dot.gov/funding/apportionments/current-apportionments
J4: 1. Updated with current NTD information
B5: National Transit Database and TRPA LT Info Data (2020/2021) | J5: 2. Updated Allocation amounts from the FTA Apportionment table
B6: TTD | C6: Revenue Miles (urban) | F6: Ridership | H6: 20/21
C7: CA | D7: 300196.81 | F7: TTD | H7: 257443
C8: NV | D8: 177430.19 | F8: Placer-TART | H8: 199752
B9: Placer-TART | C9: Revenue Miles (urban) | H9: =SUM(H7:H8) -> 457195
C10: CA | D10: 596889
C11: NV | D11: 85857 | F11: FY21 FTA Allocation 5307 | H11: 5339 | I11: 5310
B12: Population (US Census) | F12: CA | G12: 2647686 | H12: -
B13: TTD | C13: 31420 | D13: 2020 Census | F13: NV | G13: 1197619 | H13: - | I13: -
B14: Placer-TART | C14: 16643 | D14: 2020 Census | F14: TOTAL | G14: =SUM(G12:G13) -> 3845305 | H14: 345232 | I14: 64333
B17: Earned Share Factors
C18: Revenue Miles Factor | E18: Population Factor | G18: Ridership Factor | H18: Final %
B19: TTD | C19: =D7+D8 -> 477627 | D19: =C19/C21 -> 0.41161506 | E19: =C13 -> 31420 | F19: =E19/E21 -> 0.65372532 | G19: =H7/(H7+H8) -> 0.56309233 | H19: =(D19+F19+G19)/3 -> 0.5428109 | I19: 0.5428109
B20: Placer | C20: =D10+D11 -> 682746 | D20: =C20/C21 -> 0.58838494 | E20: =C14 -> 16643 | F20: =E20/E21 -> 0.34627468 | G20: =H8/(H7+H8) -> 0.43690767 | H20: =(D20+F20+G20)/3 -> 0.4571891 | I20: 0.4571891
B21: Total | C21: =SUM(C19:C20) -> 1160373 | E21: =SUM(E19:E20) -> 48063
B23: Base + Earned Allocations | G23: Totals by Operator (Earned + Base)
C24: 5307-Base | D24: 5307-Earned | H24: 5307-Total | I24: 5307-Ops (75%) | J24: 5307-Cap (25%) | K24: 5339 | L24: 5310
B25: TTD | C25: 1300000 | D25: =(G14-C27)*H19 -> 1001651.7 | G25: TTD | H25: =(G14-SUM(C25:C26))*H19+C25 -> 2301651.7 | I25: =H25*0.75 -> 1726238.8 | J25: =H25*0.25 -> 575412.92 | K25: =H14*H19 -> 187395.69 | L25: 64333
B26: Placer | C26: 700000 | D26: =(G14-C27)*H20 -> 843653.32 | G26: Placer | H26: =(G14-SUM(C25:C26))*H20+C26 -> 1543653.3 | I26: =H26*0.75 -> 1157740 | J26: =H26*0.25 -> 385913.33 | K26: =H14*H20 -> 157836.31 | L26: 0
B27: Total | C27: =SUM(C25:C26) -> 2000000 | D27: =SUM(D25:D26) -> 1845305 | G27: Total | H27: =SUM(H25:H26) -> 3845305 | I27: =SUM(I25:I26) -> 2883978.8 | J27: =SUM(J25:J26) -> 961326.25 | K27: =SUM(K25:K26) -> 345232 | L27: =SUM(L25:L26) -> 64333
D28: =SUM(C27:D27) -> 3845305

Sheet FY 2024 5307 & 5340 Table 3 (2)
A1: FEDERAL TRANSIT ADMINISTRATION
A2: Table 3
A4: FY 2024 FULL YEAR SECTION 5307 AND SECTION 5340 URBANIZED AREA APPORTIONMENTS
A6: The amount apportioned in this notice includes funding authorized under the Bipartisan Infrastructure Law, enacted as the Infrastructure Investment and Jobs Act (Pub. L. 117-58), and is based on funding made available under the Consolidated Appropriations Act, 2024 (H.R. 4366 / Public Law 118-42, March 9, 2024).
A7: Note: This table shows the amounts attributable to each State of a Multi-State Urbanized Area over 200,000 in population. These amounts are for illustrative purposes only. Designated recipients shall continue to sub-allocate funds allocated to an urbanized area based on a locally determined process, consistent with Section 5307 statutory requirements. Each State's share of a multi-state urbanized area was calculated on the basis of the percentage of population attributable to the States in the UZA, as determined by the 2020 Census.
A9: URBANIZED AREA/STATE | C9: Grand Total
A11: 1,000,000 or more in Population (Large) | C11: =C94 -> 4993057781
A13: 200,000 - 999,999 in Population (Medium) | C13: =C291 -> 1352064684
A15: 50,000 - 199,999 in Population (Small) | C15: =C699 -> 899882095
A17: Total: | C17: =C11+C13+C15 -> 7245004560
A20: Amounts Apportioned to Urbanized Areas 1,000,000 or more in Population:
A21: Atlanta, GA | B21: Georgia | C21: 98814891
A22: Austin, TX | B22: Texas | C22: 49141608
A23: Baltimore, MD | B23: Maryland | C23: 95731989
A24: Boston, MA-NH | B24: Massachusetts | C24: 209208982
A25: Boston, MA-NH | B25: New Hampshire | C25: 2935880
A26: Boston, MA-NH Total | C26: 212144862
A27: Charlotte, NC-SC | B27: North Carolina | C27: 26934025
A28: Charlotte, NC-SC | B28: South Carolina | C28: 406288
A29: Charlotte, NC-SC Total | C29: 27340313
A30: Chicago, IL-IN | B30: Illinois | C30: 313871830
A31: Chicago, IL-IN | B31: Indiana | C31: 20598059
A32: Chicago, IL-IN Total | C32: 334469889
A33: Cincinnati, OH-KY | B33: Kentucky | C33: 5863450
A34: Cincinnati, OH-KY | B34: Ohio | C34: 21933407
A35: Cincinnati, OH-KY Total | C35: 27796857
A36: Cleveland, OH | B36: Ohio | C36: 38112803
A37: Columbus, OH | B37: Ohio | C37: 25683489
A38: Dallas-Fort Worth-Arlington, TX | B38: Texas | C38: 120234995
A39: Denver-Aurora, CO | B39: Colorado | C39: 80953802
A40: Detroit, MI | B40: Michigan | C40: 55066282
A41: Houston, TX | B41: Texas | C41: 117452082
A42: Indianapolis, IN | B42: Indiana | C42: 24659802
A43: Jacksonville, FL | B43: Florida | C43: 22676560
A44: Kansas City, MO-KS | B44: Kansas | C44: 10558563
A45: Kansas City, MO-KS | B45: Missouri | C45: 13274896
A46: Kansas City, MO-KS Total | C46: 23833459
A47: Las Vegas-Henderson-Paradise, NV | B47: Nevada | C47: 55064602
A48: Los Angeles-Long Beach-Anaheim, CA | B48: California | C48: 387165053
A49: Memphis, TN-MS-AR | B49: Arkansas | C49: 522414
A50: Memphis, TN-MS-AR | B50: Mississippi | C50: 1901021
A51: Memphis, TN-MS-AR | B51: Tennessee | C51: 11654215
A52: Memphis, TN-MS-AR Total | C52: 14077650
A53: Miami-Fort Lauderdale, FL | B53: Florida | C53: 179169072
A54: Milwaukee, WI | B54: Wisconsin | C54: 29526974
A55: Minneapolis-St. Paul, MN | B55: Minnesota | C55: 80053446
A56: Nashville-Davidson, TN | B56: Tennessee | C56: 31793869
A57: New York-Jersey City-Newark, NY-NJ | B57: New Jersey | C57: 458858148
A58: New York-Jersey City-Newark, NY-NJ | B58: New York | C58: 827705831
A59: New York-Jersey City-Newark, NY-NJ Total | C59: 1286563979
A60: Orlando, FL | B60: Florida | C60: 53336707
A61: Philadelphia, PA-NJ-DE-MD | B61: Delaware | C61: 22120619
A62: Philadelphia, PA-NJ-DE-MD | B62: Maryland | C62: 1705014
A63: Philadelphia, PA-NJ-DE-MD | B63: New Jersey | C63: 50848378
A64: Philadelphia, PA-NJ-DE-MD | B64: Pennsylvania | C64: 131990548
A65: Philadelphia, PA-NJ-DE-MD Total | C65: 206664559
A66: Phoenix-Mesa-Scottsdale, AZ | B66: Arizona | C66: 75811477
A67: Pittsburgh, PA | B67: Pennsylvania | C67: 43216698
A68: Portland, OR-WA | B68: Oregon | C68: 50280523
A69: Portland, OR-WA | B69: Washington | C69: 12749235
A70: Portland, OR-WA Total | C70: 63029758
A71: Providence, RI-MA | B71: Massachusetts | C71: 11857789
A72: Providence, RI-MA | B72: Rhode Island | C72: 37566264
A73: Providence, RI-MA Total | C73: 49424053
A74: Raleigh, NC | B74: North Carolina | C74: 18399963
A75: Richmond, VA | B75: Virginia | C75: 16304228
A76: Riverside-San Bernardino, CA | B76: California | C76: 47025684
A77: Sacramento, CA | B77: California | C77: 36728332
A78: Salt Lake City, UT | B78: Utah | C78: 38899149
A79: San Antonio, TX | B79: Texas | C79: 46513022
A80: San Diego, CA | B80: California | C80: 96829834
A81: San Francisco-Oakland, CA | B81: California | C81: 195641364
A82: San Jose, CA | B82: California | C82: 58331841
A83: San Juan, PR | B83: Puerto Rico | C83: 27013461
A84: Seattle-Tacoma, WA | B84: Washington | C84: 138430271
A85: St. Louis, MO-IL | B85: Illinois | C85: 7388049
A86: St. Louis, MO-IL | B86: Missouri | C86: 37692776
A87: St. Louis, MO-IL Total | C87: 45080825
A88: Tampa-St. Petersburg, FL | B88: Florida | C88: 54137606
A89: Virginia Beach-Norfolk, VA | B89: Virginia | C89: 24559225
A90: Washington-Arlington, DC-VA-MD | B90: District of Columbia | C90: 28990825
A91: Washington-Arlington, DC-VA-MD | B91: Maryland | C91: 101790997
A92: Washington-Arlington, DC-VA-MD | B92: Virginia | C92: 109369574
A93: Washington-Arlington, DC-VA-MD Total | C93: 240151396
A94: Total | C94: =SUM(C21:C23,C26,C29,C32,C35:C43,C46:C48,C52:C56,C59:C60,C65:C67,C70,C73:C84,C87:C89,C93) -> 4993057781
A96: Amounts Apportioned to Urbanized Areas 200,000 to 1 million in Population:
A97: Aguadilla-Isabela-San Sebastián, PR | B97: Puerto Rico | C97: 2015419
A98: Akron, OH | B98: Ohio | C98: 9791022
A99: Albany-Schenectady, NY | B99: New York | C99: 18901765
A100: Albuquerque, NM | B100: New Mexico | C100: 26862473
A101: Allentown-Bethlehem, PA-NJ | B101: New Jersey | C101: 837697
A102: Allentown-Bethlehem, PA-NJ | B102: Pennsylvania | C102: 9609990
A103: Allentown-Bethlehem, PA-NJ Total | C103: 10447687
A104: Amarillo, TX | B104: Texas | C104: 3502352
A105: Anchorage, AK | B105: Alaska | C105: 21918361
A106: Ann Arbor, MI | B106: Michigan | C106: 9850086
A107: Antioch, CA | B107: California | C107: 11218558
A108: Appleton, WI | B108: Wisconsin | C108: 3482987
A109: Asheville, NC | B109: North Carolina | C109: 4129092
A110: Atlantic City-Ocean City-Villas, NJ | B110: New Jersey | C110: 17265580
...

Sheet Expense Detail
B5: A | C5: B | D5: Projected Annual Budget
D6: FY27 | F6: FY28 | H6: FY29 | J6: FY30 | M6: FY31 | N6: Total | P6: %
A7: 1 | B7: LOCAL DIVISION EXPENSE
A8: 2
A9: 3 | B9: 5110 | C9: SALARIES | D9: ='FY27 Financial Forecast'!$I$37*P9 -> 4833704.2 | F9: ='FY27 Financial Forecast'!$J$37*$P9 -> 4954546.8 | H9: ='FY27 Financial Forecast'!$K$37*$P9 -> 5078410.5 | J9: ='FY27 Financial Forecast'!$L$37*$P9 -> 5205370.8 | M9: ='FY27 Financial Forecast'!$M$37*$P9 -> 5335505 | N9: =SUM(D9:M9) -> 25407537 | P9: 0.61155397
A10: 4. | C10: General Administration | H10: ='FY27 Financial Forecast'!$J$37*$P10 -> 0
A11: 5. | C11: Vehicle Maintenance | H11: ='FY27 Financial Forecast'!$J$37*$P11 -> 0
A12: 6. | C12: Vehicle Operator Others | H12: ='FY27 Financial Forecast'!$J$37*$P12 -> 0
A13: 7. | C13: Vehicle Operators | H13: ='FY27 Financial Forecast'!$J$37*$P13 -> 0
H14: ='FY27 Financial Forecast'!$J$37*$P14 -> 0
A15: 4 | B15: 5210 | C15: FRINGE | D15: ='FY27 Financial Forecast'!$I$37*P15 -> 1139297.9 | F15: ='FY27 Financial Forecast'!$J$37*$P15 -> 1167780.3 | H15: ='FY27 Financial Forecast'!$K$37*$P15 -> 1196974.8 | J15: ='FY27 Financial Forecast'!$L$37*$P15 -> 1226899.2 | M15: ='FY27 Financial Forecast'!$M$37*$P15 -> 1257571.7 | N15: =SUM(D15:M15) -> 5988524 | P15: 0.14414249
A16: 5 | B16: 6310 | C16: CONSULTANT/CONTRACTUAL | D16: ='FY27 Financial Forecast'!$I$37*P16 -> 5520.3681 | F16: ='FY27 Financial Forecast'!$J$37*$P16 -> 5658.3773 | H16: ='FY27 Financial Forecast'!$K$37*$P16 -> 5799.8367 | J16: ='FY27 Financial Forecast'!$L$37*$P16 -> 5944.8326 | M16: ='FY27 Financial Forecast'!$M$37*$P16 -> 6093.4534 | N16: =SUM(D16:M16) -> 29016.868 | P16: 0.00069842979
A17: 6 | B17: 6320 | C17: AUDIT | D17: ='FY27 Financial Forecast'!$I$37*P17 -> 27618.368 | F17: ='FY27 Financial Forecast'!$J$37*$P17 -> 28308.828 | H17: ='FY27 Financial Forecast'!$K$37*$P17 -> 29016.548 | J17: ='FY27 Financial Forecast'!$L$37*$P17 -> 29741.962 | M17: ='FY27 Financial Forecast'!$M$37*$P17 -> 30485.511 | N17: =SUM(D17:M17) -> 145171.22 | P17: 0.00349424
A18: 7 | B18: 6330 | C18: PROFESSIONAL FEES | D18: ='FY27 Financial Forecast'!$I$37*P18 -> 12950.883 | F18: ='FY27 Financial Forecast'!$J$37*$P18 -> 13274.655 | H18: ='FY27 Financial Forecast'!$K$37*$P18 -> 13606.521 | J18: ='FY27 Financial Forecast'!$L$37*$P18 -> 13946.684 | M18: ='FY27 Financial Forecast'!$M$37*$P18 -> 14295.351 | N18: =SUM(D18:M18) -> 68074.094 | P18: 0.0016385288
A19: 8 | B19: 6431 | C19: CONSUMABLE ADMIN SUPPLIES | D19: ='FY27 Financial Forecast'!$I$37*P19 -> 13419.854 | F19: ='FY27 Financial Forecast'!$J$37*$P19 -> 13755.351 | H19: ='FY27 Financial Forecast'!$K$37*$P19 -> 14099.234 | J19: ='FY27 Financial Forecast'!$L$37*$P19 -> 14451.715 | M19: ='FY27 Financial Forecast'!$M$37*$P19 -> 14813.008 | N19: =SUM(D19:M19) -> 70539.162 | P19: 0.0016978625
A20: 9 | B20: 6432 | C20: TECHNOLOGY | D20: ='FY27 Financial Forecast'!$I$37*P20 -> 143339.57 | F20: ='FY27 Financial Forecast'!$J$37*$P20 -> 146923.06 | H20: ='FY27 Financial Forecast'!$K$37*$P20 -> 150596.13 | J20: ='FY27 Financial Forecast'!$L$37*$P20 -> 154361.04 | M20: ='FY27 Financial Forecast'!$M$37*$P20 -> 158220.06 | N20: =SUM(D20:M20) -> 753439.86 | P20: 0.018135136
A21: 10 | C21: PURCHASED TRANSPORTATION (TNC PROVIDER) | D21: ='FY27 Financial Forecast'!$I$37*P21 -> 0 | F21: ='FY27 Financial Forecast'!$J$37*$P21 -> 0 | H21: ='FY27 Financial Forecast'!$K$37*$P21 -> 0 | J21: ='FY27 Financial Forecast'!$L$37*$P21 -> 0 | M21: ='FY27 Financial Forecast'!$M$37*$P21 -> 0 | N21: =SUM(D21:M21) -> 0 | P21: 0
A22: 11 | B22: 6510 | C22: UTILITIES-ADMIN | D22: ='FY27 Financial Forecast'!$I$37*P22 -> 14605.411 | F22: ='FY27 Financial Forecast'!$J$37*$P22 -> 14970.546 | H22: ='FY27 Financial Forecast'!$K$37*$P22 -> 15344.81 | J22: ='FY27 Financial Forecast'!$L$37*$P22 -> 15728.43 | M22: ='FY27 Financial Forecast'!$M$37*$P22 -> 16121.641 | N22: =SUM(D22:M22) -> 76770.839 | P22: 0.0018478576
A23: 12 | B23: 6530 | C23: TELEPHONE-ADMIN | D23: ='FY27 Financial Forecast'!$I$37*P23 -> 3000.2657 | F23: ='FY27 Financial Forecast'!$J$37*$P23 -> 3075.2724 | H23: ='FY27 Financial Forecast'!$K$37*$P23 -> 3152.1542 | J23: ='FY27 Financial Forecast'!$L$37*$P23 -> 3230.958 | M23: ='FY27 Financial Forecast'!$M$37*$P23 -> 3311.732 | N23: =SUM(D23:M23) -> 15770.382 | P23: 0.00037958972
A24: 13 | B24: 6610 | C24: INSURANCE - LIABILITY | D24: ='FY27 Financial Forecast'!$I$37*P24 -> 7881.2109 | F24: ='FY27 Financial Forecast'!$J$37*$P24 -> 8078.2411 | H24: ='FY27 Financial Forecast'!$K$37*$P24 -> 8280.1972 | J24: ='FY27 Financial Forecast'!$L$37*$P24 -> 8487.2021 | M24: ='FY27 Financial Forecast'!$M$37*$P24 -> 8699.3821 | N24: =SUM(D24:M24) -> 41426.233 | P24: 0.00099712054
A25: 14 | B25: 6810 | C25: OFFICE EQUIPMENT LEASING | D25: ='FY27 Financial Forecast'!$I$37*P25 -> 20337.126 | F25: ='FY27 Financial Forecast'!$J$37*$P25 -> 20845.554 | H25: ='FY27 Financial Forecast'!$K$37*$P25 -> 21366.693 | J25: ='FY27 Financial Forecast'!$L$37*$P25 -> 21900.86 | M25: ='FY27 Financial Forecast'!$M$37*$P25 -> 22448.382 | N25: =SUM(D25:M25) -> 106898.61 | P25: 0.0025730267
A26: 15 | B26: 6815 | C26: OFFICE EQUIPMENT/FIXTURES | D26: ='FY27 Financial Forecast'!$I$37*P26 -> 921.2734 | F26: ='FY27 Financial Forecast'!$J$37*$P26 -> 944.30524 | H26: ='FY27 Financial Forecast'!$K$37*$P26 -> 967.91287 | J26: ='FY27 Financial Forecast'!$L$37*$P26 -> 992.11069 | M26: ='FY27 Financial Forecast'!$M$37*$P26 -> 1016.9135 | N26: =SUM(D26:M26) -> 4842.5157 | P26: 0.00011655831
A27: 16 | B27: 6825 | C27: TRAVEL OUT-OF-AREA | D27: ='FY27 Financial Forecast'!$I$37*P27 -> 2302.8293 | F27: ='FY27 Financial Forecast'!$J$37*$P27 -> 2360.4001 | H27: ='FY27 Financial Forecast'!$K$37*$P27 -> 2419.4101 | J27: ='FY27 Financial Forecast'!$L$37*$P27 -> 2479.8953 | M27: ='FY27 Financial Forecast'!$M$37*$P27 -> 2541.8927 | N27: =SUM(D27:M27) -> 12104.427 | P27: 0.00029135097
A28: 17 | B28: 6830 | C28: MILEAGE | D28: ='FY27 Financial Forecast'!$I$37*P28 -> 4184.0754 | F28: ='FY27 Financial Forecast'!$J$37*$P28 -> 4288.6773 | H28: ='FY27 Financial Forecast'!$K$37*$P28 -> 4395.8942 | J28: ='FY27 Financial Forecast'!$L$37*$P28 -> 4505.7916 | M28: ='FY27 Financial Forecast'!$M$37*$P28 -> 4618.4363 | N28: =SUM(D28:M28) -> 21992.875 | P28: 0.00052936377
A29: 18 | B29: 6835 | C29: PUBLIC NOTICES | D29: ='FY27 Financial Forecast'!$I$37*P29 -> 0 | F29: ='FY27 Financial Forecast'!$J$37*$P29 -> 0 | H29: ='FY27 Financial Forecast'!$K$37*$P29 -> 0 | J29: ='FY27 Financial Forecast'!$L$37*$P29 -> 0 | M29: ='FY27 Financial Forecast'!$M$37*$P29 -> 0 | N29: =SUM(D29:M29) -> 0 | P29: 0
A30: 19 | B30: 6840 | C30: REGISTRATION FEES | D30: ='FY27 Financial Forecast'!$I$37*P30 -> 681.78198 | F30: ='FY27 Financial Forecast'!$J$37*$P30 -> 698.82653 | H30: ='FY27 Financial Forecast'!$K$37*$P30 -> 716.2972 | J30: ='FY27 Financial Forecast'!$L$37*$P30 -> 734.20463 | M30: ='FY27 Financial Forecast'!$M$37*$P30 -> 752.55974 | N30: =SUM(D30:M30) -> 3583.6701 | P30: 8.625817e-05
A31: 20 | B31: 6845 | C31: MEMBERSHIP DUES | D31: ='FY27 Financial Forecast'!$I$37*P31 -> 1652.7576 | F31: ='FY27 Financial Forecast'!$J$37*$P31 -> 1694.0765 | H31: ='FY27 Financial Forecast'!$K$37*$P31 -> 1736.4284 | J31: ='FY27 Financial Forecast'!$L$37*$P31 -> 1779.8392 | M31: ='FY27 Financial Forecast'!$M$37*$P31 -> 1824.3351 | N31: =SUM(D31:M31) -> 8687.4368 | P31: 0.00020910474
A32: 21 | B32: 6850 | C32: MARKETING | D32: ='FY27 Financial Forecast'!$I$37*P32 -> -420.40271 | F32: ='FY27 Financial Forecast'!$J$37*$P32 -> -430.91278 | H32: ='FY27 Financial Forecast'!$K$37*$P32 -> -441.6856 | J32: ='FY27 Financial Forecast'!$L$37*$P32 -> -452.72774 | M32: ='FY27 Financial Forecast'!$M$37*$P32 -> -464.04593 | N32: =SUM(D32:M32) -> -2209.7748 | P32: -5.3188804e-05
A33: 22 | B33: 6855 | C33: MISCELLANEOUS ADMIN | D33: ='FY27 Financial Forecast'!$I$37*P33 -> 53212.476 | F33: ='FY27 Financial Forecast'!$J$37*$P33 -> 54542.788 | H33: ='FY27 Financial Forecast'!$K$37*$P33 -> 55906.358 | J33: ='FY27 Financial Forecast'!$L$37*$P33 -> 57304.016 | M33: ='FY27 Financial Forecast'!$M$37*$P33 -> 58736.617 | N33: =SUM(D33:M33) -> 279702.25 | P33: 0.0067323732
... A52: 41 | B52: 9865 | C52: MISCELLANEOUS OPERATING | D52: ='FY27 Financial Forecast'!$I$37*P52 -> 3741.3598 | F52: ='FY27 Financial Forecast'!$J$37*$P52 -> 3834.8938 | H52: ='FY27 Financial Forecast'!$K$37*$P52 -> 3930.7661 | J52: ='FY27 Financial Forecast'!$L$37*$P52 -> 4029.0353 | M52: ='FY27 Financial Forecast'!$M$37*$P52 -> 4129.7612 | N52: =SUM(D52:M52) -> 19665.816 | P52: 0.00047335197
A53: 42 | D53: ='FY27 Financial Forecast'!$I$37*P53 -> 0 | F53: ='FY27 Financial Forecast'!$J$37*$P53 -> 0 | H53: ='FY27 Financial Forecast'!$K$37*$P53 -> 0 | J53: ='FY27 Financial Forecast'!$L$37*$P53 -> 0 | M53: ='FY27 Financial Forecast'!$M$37*$P53 -> 0 | N53: =SUM(D53:M53) -> 0
A54: 43 | B54: 8850 | C54: VEHICLE REPAIR, MAINT., INSPECT., REGISTR. | D54: ='FY27 Financial Forecast'!$I$37*P54 -> 0 | F54: ='FY27 Financial Forecast'!$J$37*$P54 -> 0 | H54: ='FY27 Financial Forecast'!$K$37*$P54 -> 0 | J54: ='FY27 Financial Forecast'!$L$37*$P54 -> 0 | M54: ='FY27 Financial Forecast'!$M$37*$P54 -> 0 | N54: =SUM(D54:M54) -> 0 | P54: 0
A55: 44 | B55: 8855 | C55: VEHICLE MAINT LABOR | D55: ='FY27 Financial Forecast'!$I$37*P55 -> 0 | F55: ='FY27 Financial Forecast'!$J$37*$P55 -> 0 | H55: ='FY27 Financial Forecast'!$K$37*$P55 -> 0 | J55: ='FY27 Financial Forecast'!$L$37*$P55 -> 0 | M55: ='FY27 Financial Forecast'!$M$37*$P55 -> 0 | N55: =SUM(D55:M55) -> 0 | P55: 0
A56: 45 | B56: 9931 | C56: PREV MNT - OTHER VEH MNT MATERIALS | D56: ='FY27 Financial Forecast'!$I$37*P56 -> 189292.52 | F56: ='FY27 Financial Forecast'!$J$37*$P56 -> 194024.84 | H56: ='FY27 Financial Forecast'!$K$37*$P56 -> 198875.46 | J56: ='FY27 Financial Forecast'!$L$37*$P56 -> 203847.34 | M56: ='FY27 Financial Forecast'!$M$37*$P56 -> 208943.53 | N56: =SUM(D56:M56) -> 994983.69 | P56: 0.023949044
A57: 46 | B57: 9932 | C57: PREV MNT - SHOP EQUIPMENT | D57: ='FY27 Financial Forecast'!$I$37*P57 -> 37847.955 | F57: ='FY27 Financial Forecast'!$J$37*$P57 -> 38794.154 | H57: ='FY27 Financial Forecast'!$K$37*$P57 -> 39764.008 | J57: ='FY27 Financial Forecast'!$L$37*$P57 -> 40758.108 | M57: ='FY27 Financial Forecast'!$M$37*$P57 -> 41777.061 | N57: =SUM(D57:M57) -> 198941.29 | P57: 0.004788474
A58: 47 | B58: 9933 | C58: PREV MNT - SHOP SUPPLIES | D58: ='FY27 Financial Forecast'!$I$37*P58 -> 88809.736 | F58: ='FY27 Financial Forecast'!$J$37*$P58 -> 91029.979 | H58: ='FY27 Financial Forecast'!$K$37*$P58 -> 93305.729 | J58: ='FY27 Financial Forecast'!$L$37*$P58 -> 95638.372 | M58: ='FY27 Financial Forecast'!$M$37*$P58 -> 98029.331 | N58: =SUM(D58:M58) -> 466813.15 | P58: 0.011236092
A59: 48 | B59: 9934 | C59: PREV MNT - VEH MNT INVENTORY | D59: ='FY27 Financial Forecast'!$I$37*P59 -> 136507.37 | F59: ='FY27 Financial Forecast'!$J$37*$P59 -> 139920.05 | H59: ='FY27 Financial Forecast'!$K$37*$P59 -> 143418.05 | J59: ='FY27 Financial Forecast'!$L$37*$P59 -> 147003.51 | M59: ='FY27 Financial Forecast'!$M$37*$P59 -> 150678.59 | N59: =SUM(D59:M59) -> 717527.58 | P59: 0.017270735
A60: 49 | B60: 9935 | C60: PREV MNT - FLEET MNT | D60: ='FY27 Financial Forecast'!$I$37*P60 -> 14626.473 | F60: ='FY27 Financial Forecast'!$J$37*$P60 -> 14992.134 | H60: ='FY27 Financial Forecast'!$K$37*$P60 -> 15366.938 | J60: ='FY27 Financial Forecast'!$L$37*$P60 -> 15751.111 | M60: ='FY27 Financial Forecast'!$M$37*$P60 -> 16144.889 | N60: =SUM(D60:M60) -> 76881.545 | P60: 0.0018505223
A61: 50 | B61: 9936 | C61: PREV MNT - VEH REP,MNT,INSP,RG | D61: ='FY27 Financial Forecast'!$I$37*P61 -> 53465.331 | F61: ='FY27 Financial Forecast'!$J$37*$P61 -> 54801.965 | H61: ='FY27 Financial Forecast'!$K$37*$P61 -> 56172.014 | J61: ='FY27 Financial Forecast'!$L$37*$P61 -> 57576.314 | M61: ='FY27 Financial Forecast'!$M$37*$P61 -> 59015.722 | N61: =SUM(D61:M61) -> 281031.35 | P61: 0.0067643642
A62: 51 | B62: 9945 | C62: FACILITY REPAIR & MAINT | D62: ='FY27 Financial Forecast'!$I$37*P62 -> 105900.94 | F62: ='FY27 Financial Forecast'!$J$37*$P62 -> 108548.47 | H62: ='FY27 Financial Forecast'!$K$37*$P62 -> 111262.18 | J62: ='FY27 Financial Forecast'!$L$37*$P62 -> 114043.73 | M62: ='FY27 Financial Forecast'!$M$37*$P62 -> 116894.82 | N62: =SUM(D62:M62) -> 556650.14 | P62: 0.013398449
A63: 52 | D63: ='FY27 Financial Forecast'!$I$37*P63 -> 0 | F63: ='FY27 Financial Forecast'!$J$37*$P63 -> 0 | H63: ='FY27 Financial Forecast'!$K$37*$P63 -> 0 | J63: ='FY27 Financial Forecast'!$L$37*$P63 -> 0 | M63: ='FY27 Financial Forecast'!$M$37*$P63 -> 0 | N63: =SUM(D63:M63) -> 0 | P63: 0
A64: 53 | B64: TOTAL EXPENSE | D64: =SUM(D7:D63) -> 7903970 | F64: =SUM(F7:F63) -> 8101569.2 | H64: =SUM(H9:H63) -> 8304108.5 | J64: =SUM(J9:J63) -> 8511711.2 | M64: =SUM(M9:M63) -> 8724504 | N64: =SUM(N9:N63) -> 41545863 | P64: =SUM(P7:P63) -> 1
A65: 54
A66: 55 | B66: TOTAL REVENUE
A67: 56 | C67: FEDERAL CARES & ARPA | F67: 0 | H67: 0
A68: 57 | C68: FEDERAL FORMULA | F68: 0 | H68: 0
A69: 58 | C69: STATE | F69: 0 | H69: 0
A70: 60 | C70: EARNED REVENUE - CITY | F70: 0 | H70: 0
A71: 61 | C71: EARNED REVENUE - County | F71: 0 | H71: 0
A72: 62 | C72: FARES EARNED | F72: 0 | H72: 0
A73: 63 | C73: OTHER REVENUE | F73: 0 | H73: 0
A74: 64 | C74: TOTAL | F74: =SUM(F67:F73) -> 0 | H74: =SUM(H67:H73) -> 0 | J74: =SUM(J67:J73) -> 0 | M74: =SUM(M67:M73) -> 0 | N74: =SUM(N67:N73) -> 0
A75: 65
A76: 82
A77: 83 | B77: TOTAL REVENUE | D77: =SUM(D74:D75) -> 0 | F77: =SUM(F74:F75) -> 0 | H77: =SUM(H74:H75) -> 0 | J77: =SUM(J74:J75) -> 0 | M77: =SUM(M74:M75) -> 0 | N77: =SUM(N74:N75) -> 0

Sheet Service Parameters
C73: ZONE 6 ALTERNATIVE TO ROUTE 55

Sheet Lake Link 23-24 Data
A1: Microtransit 12month Rolling Ridership - 2023/2024
B2: 45170 | C2: 45200 | D2: 45231 | E2: 45261 | F2: 45292 | G2: 45323 | H2: 45352 | I2: 45383 | J2: 45413 | K2: 45444 | L2: 45474 | M2: 45505 | N2: Total
A3: Passengers | B3: 15390 | C3: 12235 | D3: 11359 | E3: 19738 | F3: 24392 | G3: 25301 | H3: 23546 | I3: 18830 | J3: 19932 | K3: 24029 | L3: 25365 | M3: 24121 | N3: 244238
A4: Vehicle Revenue Hours | B4: 1929 | C4: 1430 | D4: 1315 | E4: 1924 | F4: 2463 | G4: 2572 | H4: 2619 | I4: 2062 | J4: 2047 | K4: 2507 | L4: 2655 | M4: 2585 | N4: 26108
A5: Total Vehicle Hours | B5: 2088 | C5: 1529 | D5: 1412 | E5: 2056 | F5: 2630 | G5: 2753 | H5: 2822 | I5: 2230 | J5: 2221 | K5: 2717 | L5: 2880 | M5: 2825 | N5: 28163
A6: Vehicle Revenue Miles | B6: 23772 | C6: 18326 | D6: 17325 | E6: 23657 | F6: 29638 | G6: 31591 | H6: 35502 | I6: 28463 | J6: 27637 | K6: 32486 | L6: 33127 | M6: 33199 | N6: 334723
A7: Total Vehicle Miles | B7: 25004 | C7: 19081 | D7: 18119 | E7: 24593 | F7: 30803 | G7: 32863 | H7: 33785 | I7: 29681 | J7: 28887 | K7: 33981 | L7: 34744 | M7: 34825 | N7: 346366
A8: Passenger Miles | B8: 24785 | C8: 19110 | D8: 17402 | E8: 29440 | F8: 38011 | G8: 41594 | H8: 38682 | I8: 33069 | J8: 37284 | K8: 47653 | L8: 48929 | M8: 46932 | N8: 422891

Sheet TTD 2022 NTD DATA
R22: FY27 | S22: FY28
R23: Vehicle | S23: Vehicle
R24: Revenue | S24: Revenue
R25: Miles | S25: Miles
R28: =(208928/7)*3 -> 89540.571 | S28: =208928/7*4 -> 119387.43 | T28: VRM JPA
R29: =423821-R28 -> 334280.43 | S29: =423821-S28 -> 304433.57 | T29: VRM TTD
R30: =R29+R28 -> 423821 | S30: =S29+S28 -> 423821
R31: 0.75 | S31: 0.75
R32: =(269576-22739)*0.75 -> 185127.75 | T32: Px
R33: =R28/12 -> 7461.7143 | S33: =S28/12 -> 9948.9524 | T33: VRH JPA

Sheet SSTMA CY24 Budget
B3: CY24 Budget
B4: Hendrickson Transporation Group Management Fees | D4: HTG | E4: Downtowner | F4: Admin | G4: Total Total
B5: 45138 | D5: 10625 | E5: 112937 | F5: 150 | G5: =SUM(D5:E5) -> 123562
B6: 45169 | D6: 10625 | E6: 102937 | F6: 150 | G6: =SUM(D6:E6) -> 113562
B7: 45199 | D7: 10625 | E7: 151111 | F7: 150 | G7: =SUM(D7:E7) -> 161736
B8: 45200 | D8: 10625 | E8: 102537 | F8: 150 | G8: =SUM(D8:E8) -> 113162
B9: 45260 | D9: 10625 | E9: 102537 | F9: 150 | G9: =SUM(D9:E9) -> 113162
B10: 45291 | D10: 10625 | E10: 102537 | F10: 150 | G10: =SUM(D10:E10) -> 113162
B11: Expenses | D11: HTG | E11: Downtowner | F11: Admin | G11: Total
B12: January | D12: =10625+(15000/12) -> 11875 | E12: 150395 | F12: 150 | G12: =SUM(D12:F12) -> 162420
B13: February | D13: =10625+(15000/12) -> 11875 | E13: 166786 | F13: 150 | G13: =SUM(D13:F13) -> 178811
B14: March | D14: =10625+(15000/12) -> 11875 | E14: 166786 | F14: 150 | G14: =SUM(D14:F14) -> 178811
B15: April | D15: =10625+(15000/12) -> 11875 | E15: 166786 | F15: 150 | G15: =SUM(D15:F15) -> 178811
B16: May | D16: =10625+(15000/12) -> 11875 | E16: 166786 | F16: 150 | G16: =SUM(D16:F16) -> 178811
B17: June | D17: =10625+(15000/12) -> 11875 | E17: 166786 | F17: 150 | G17: =SUM(D17:F17) -> 178811
B18: July | D18: =10625+(15000/12) -> 11875 | E18: 166786 | F18: 150 | G18: =SUM(D18:F18) -> 178811
B19: August | D19: =10625+(15000/12) -> 11875 | E19: 166786 | F19: 150 | G19: =SUM(D19:F19) -> 178811
B20: September | D20: =10625+(15000/12) -> 11875 | E20: 166786 | F20: 150 | G20: =SUM(D20:F20) -> 178811
B21: October | D21: =10625+(15000/12) -> 11875 | E21: 166786 | F21: 150 | G21: =SUM(D21:F21) -> 178811
B22: November | D22: =10625+(15000/12) -> 11875 | E22: 166786 | F22: 150 | G22: =SUM(D22:F22) -> 178811
B23: December | D23: =10625+(15000/12) -> 11875 | E23: 166786 | F23: 150 | G23: =SUM(D23:F23) -> 178811
B24: Total | D24: =SUM(D12:D23) -> 142500 | E24: =SUM(E12:E23) -> 1985041 | F24: =SUM(F12:F23) -> 1800 | G24: =SUM(G12:G23) -> 2129341
B26: 45688 | D26: 10625 | E26: 166786 | F26: 0 | G26: =SUM(D26:E26) -> 177411
B27: 45716 | D27: 10625 | E27: 166786 | F27: 0 | G27: =SUM(D27:E27) -> 177411
B28: 45747 | D28: 10625 | E28: 166786 | F28: 0 | G28: =SUM(D28:E28) -> 177411
B29: 45777 | D29: 10625 | E29: 166786 | F29: 0 | G29: =SUM(D29:E29) -> 177411
B30: 45808 | D30: 10625 | E30: 166786 | F30: 0 | G30: =SUM(D30:E30) -> 177411
B31: 45838 | D31: 10625 | E31: 166786 | F31: 150 | G31: =SUM(D31:E31) -> 177411
B32: Annual Travel Epenses | D32: 15000 | G32: =SUM(D32:E32) -> 15000
B33: Total | D33: =SUM(D18:D32) -> 292500 | E33: =SUM(E18:E32) -> 3986473 | F33: =SUM(F18:F32) -> 2850 | G33: =SUM(D33:E33) -> 4278973 | J33: =SUM(J18:J32) -> 0
B35: FY24 Revenues | G35: Total
B36: City of South Lake Tahoe | G36: 750000
B37: Douglas County | G37: 600000
B38: Event Center | G38: 340000
B39: El Dorado County | G39: 200000
B40: State of Nevada | G40: 300000
B41: Heavenly | G41: 100000
B42: Tourism Implovement District | G42: 25000
B43: ADVANCE | G43: 25000
B44: LTVA | G44: 50000
B45: TDVA
B46: Other Private Partners
B47: Total | G47: =SUM(G36:G44) -> 2390000
B48: Reserves | G48: =G47-G24 -> 260659

Sheet Operating Assistance
B1: FY27 JPA ASSUMPTIONS USING - FTA FY 2020 SECTION 5307 OPERATING ASSISTANCE SPECIAL RULE OPERATOR CAPS FOR URBANIZED AREAS OVER 200,000 IN POPULATION
B2: The total available for operating assistance is based on FY 2018 NTD Data and the Section 5307 funding shown in FTA Apportionment Table #3.
B4: NOTES:
B5: 1. Agencies that are included in this table AND that are eligible for grants under the Section 5307 Urbanized Area Formula Program are eligible to receive operating assistance under the provisions of 5307(a)(2)(A), subject to local allocation, up to the amounts specified in column "H" in Fiscal Year 2020.
B6: 2. Beginning in FY17, agencies may alternatively use program funds up to the amount shown in column "I" for operating assistance under 5307(a)(2)(B), provided that this amount is no greater than 50 or 75 percent of the total amount allocated to them for eligible projects through the local planning process, consistent with the eligible percent factor shown in column "G".
B7: 3. This list does NOT indicate an agency's eligibility or entitlement for funding and does not represent an allocation of funding under the Urbanized Area Formula Program or any other FTA program.
B8: 4. Public agencies that operate fixed route bus service and demand response service, excluding complementary ADA service, are permitted to use this provision in their Urbanized Area Formula Program grants.
B9: 5. Certain transit operators that reported to NTD in a consolidated (multi-agency) report are included based on a vehicle revenue hour share proportional to the number of vehicles reported in maximum service.
B10: 6. Transit operators may receive a cap for each urbanized area in which they operate and report transit service.
B11: 7. Agencies that contract for public transportation service from a private operator, and which otherwise qualify for an operating cap under this provision, have been credited with the vehicle revenue hours reported by the private provider as attributable to the public agency.
B13: Urbanized Area of Service Provided | C13: Public Transportation System Operator | D13: Vehicles Operated in Peak Fixed Route and Demand Response Service | E13: Apportionment to Urbanized Area | F13: Percent of Apportionment Attributable to Operator based on Vehicle Revenue Hours | G13: Eligible Percent Factor Category | H13: FY 2020 Maximum Amount of Section 5307 Operating Assistance Allowed | I13: FY 2020 Maximum Amount of Section 5307 Operating Assistance Allowed 5307(a)(2)(B)
A14: FY18 | B14: Lake Tahoe Region, CA-NV | C14: Placer County Department of Public Works and Facilities | D14: 20 | E14: 2891532 | F14: 0.34623809 | G14: 0.75 | H14: 750868.89 | I14: 825955.78
A15: FY18 | B15: Lake Tahoe Region, CA-NV | C15: Tahoe Transportation District | D15: 29 | E15: 2891532 | F15: 0.65376191 | G15: 0.75 | H15: 1417780.1 | I15: 1559558.1
A16: FY19 | B16: Lake Tahoe Region, CA-NV | C16: Placer County Department of Public Works and Facilities | D16: 21 | E16: 2944091 | F16: 0.39535193 | G16: 0.75 | H16: 872964.04 | I16: 960260.45
A17: FY19 | B17: Lake Tahoe Region, CA-NV | C17: Tahoe Transportation District | D17: 21 | E17: 2944091 | F17: 0.60464807 | G17: 0.75 | H17: 1335104.2 | I17: 1468614.6
A18: FY20 | B18: Lake Tahoe, CA-NV | C18: County of Placer | D18: 21 | E18: 3057188 | F18: 0.40196644 | G18: 0.75 | H18: 921665.22 | I18: 1013831.7
A19: FY20 | B19: Lake Tahoe, CA-NV | C19: Tahoe Transportation District | D19: 19 | E19: 3057188 | F19: 0.59803356 | G19: 0.75 | H19: 1371225.8 | I19: 1508348.4
A20: FY21 | B20: Lake Tahoe Region, CA-NV | C20: County of Placer | D20: 21 | E20: 2964270 | F20: 0.47846577 | G20: 0.75 | H20: 1063726.3 | I20: 1170098.9
A21: FY21 | B21: Lake Tahoe Region, CA-NV | C21: Tahoe Transportation District | D21: 15 | E21: 2964270 | F21: 0.52153423 | G21: 0.75 | H21: 1159476.2 | I21: 1275423.8
A22: FY22 | B22: Lake Tahoe, CA-NV | C22: County of Placer | D22: 21 | E22: 3805886 | F22: 0.47846577 | G22: 0.75 | H22: 1365739.6 | I22: 1502313.6
A23: FY22 | B23: Lake Tahoe, CA-NV | C23: Tahoe Transportation District | D23: 15 | E23: 3805886 | F23: 0.52153423 | G23: 0.75 | H23: 1488674.9 | I23: 1637542.4
A24: FY23 | B24: Lake Tahoe Region, CA-NV | C24: County of Placer | D24: 21 | E24: 3845305 | F24: 0.47846577 | G24: 0.75 | H24: 1379885.1 | I24: 1517873.6
A25: FY23 | B25: Lake Tahoe Region, CA-NV | C25: Tahoe Transportation District | D25: 15 | E25: 3845305 | F25: 0.52153423 | G25: 0.75 | H25: 1504093.6 | I25: 1654503
A26: FY24 | B26: Lake Tahoe Region, CA-NV | C26: County of Placer | D26: 21 | E26: 3902214 | F26: =D26/(D26+D27) -> 0.53846154 | G26: 0.75 | H26: =E26*F26 -> 2101192.2 | I26: 2205277
A27: FY24 | B27: Lake Tahoe Region, CA-NV | C27: Tahoe Transportation District | D27: 18 | E27: 3902214 | F27: =D27/(D26+D27) -> 0.46153846 | G27: 0.75 | H27: =E27*F27 -> 1801021.8 | I27: 1014049
A28: FY27 | B28: Lake Tahoe Region, CA-NV | C28: Tahoe Transportation District | D28: 4 | E28: 2682000 | F28: =D28/(D27+D28) -> 0.18181818 | G28: 0.75 | H28: =E28*F28 -> 487636.36
A29: FY27 | B29: Lake Tahoe Region, CA-NV | C29: JPA | D29: 14 | E29: 2682000 | F29: =D29/(D28+D29) -> 0.77777778 | G29: 0.75 | H29: =E29*F29 -> 2086000

Sheet Kira's Total Revenue Miles
B3: Hi Raymond,
B5: Here’s a breakdown of the actual annual revenue miles TTD operated for 22 and 19x in FY23. These are the latest numbers I have for them. And then I’ve included my estimate for Route 21x assuming it operates every 60 minutes from 6am to 7pm. I’m probably overestimating the actual service TTD has planned, but it’s not totally clear from their SRTP how it would operate.
B7: FY23 Total Revenue Miles
B8: 19x | C8: 45032 | D8: =C8/C10 -> 0.42276423
B9: 22 | C9: 61486 | D9: =C9/C10 -> 0.57723577
C10: =SUM(C8:C9) -> 106518
B11: 21x (estimate) | C11: 208780
B13: Unfortunately, I don’t have revenue miles separated out by jurisdiction. It hasn’t been a statistic we thought was important to collect until now. TTD might have those figures, but I’m not sure. I think your methodology could work, but I’m a little concerned it will back us into a corner of only providing services according to available dollars and not based on community need. I’d be interested to see what the formula shows, but very hesitant to bring it forward as an actual method of assigning costs…
B15: Thanks,
B17: Kira Richardson (she/her)
B18: Senior Transportation Planner
B19: Regional Planning Department
B20: 775-589-5236 | krichardson@trpa.gov
B21: **Note new name and email
B22: 775-901-3466 mobile

Sheet Capital
A1: STILL NEED TO DEFINE CAPITAL DECISION MAKING MODEL
